Workbook

Sheet TB
A1: Ultrafine Mineral & Admixtures Pvt. Ltd.
A2: 76/1N, Wardha Road, Mouza Dongargaon, Nagpur,
A3: Maharashtra- 441108
A4: UDYAM : UDYAM-MH-20-0007365 (Small/Mfgr)
A5: CIN: U24100MH2020PTC338575
A6: Sundry Creditors
A7: Group Summary
A8: 1-Apr-26 to 30-Jun-26 | B8: =SUBTOTAL(9,B11:B266) -> 44503459 | C8: =SUBTOTAL(9,C11:C266) -> 3.1335228e+08
B9: Closing Balance
A10: Particulars | B10: Debit | C10: Credit
A12: Abhay Dongare - Employee | B12: 15161
A13: Abhay Singh-Employee | C13: 3519
A14: Abhishek Kumar Nayak - Employee | C14: 18812
A15: Accurate Engineering Works-Crs | C15: 30444
A16: ACE HIMALAYAN FERRO ALLOYS PRIVATE LIMITED - CRS | B16: 94000
A17: ADHUNIK TRASNPORT ORGANISATION LIMITED - Crs | C17: 80439.38
A18: ADVITA POLYCRAFT LLP - Crs | C18: 655797.08
A19: AIRMAX AUTOMATION - CRS | C19: 35913.4
A20: Akash Body Bildders-CRS | C20: 300000.02
A21: AKBAR TRAVELS OF INDIA PVT. LTD-Crs | C21: 104715
A22: AKRUTI ENTERPRISE-CRS | C22: 24564.26
A23: AMBUJA CEMENTS LIMITED -Crs | C23: 8563184.6
A24: Arcelormittal Nippon Steel India Limited - Crs | B24: 557957.34
A25: ARKAY LOGISTICS-Crs | C25: 848978.08
A26: Arya CS - Crs | C26: 3000
A27: ASHCONNECT GLOBAL TRADING Pvt Ltd- Crs | C27: 8639888.8
A28: ASHOKA BUILDCON LIMITED-Crs | B28: 163127.04
A29: Ashvarya Kumar Verma-Employee | B29: 23510
A30: Asia Minerals and Machinery Company - Crs | C30: 603502
A31: Asl Logistics Private Limited-Crs | C31: 6959753.5
A32: Atharva Enterprises - Crs | C32: 200175.08
A33: AVENGERS SECURITY SERVICES-CR | C33: 42305.6
A34: Avijit Chaubey - Employee | C34: 125285.4
A35: BAHUBALI CHEMICAL INDUSTRIES-CRS | C35: 7521130.2
A36: Balram Kumar Chakrawarti - Employee | C36: 372600
A37: Bandu Naik - Employee | B37: 187920
A38: BGR Constructions - Crs | C38: 968310
A39: Bhailal Jethva - Employee | C39: 78300
A40: Bhamra Transport - Crs | C40: 464872.27
A41: Bhandari Automobiles Pvt Ltd - Crs | C41: 9150
A42: Bharat Engineering - Crs | B42: 37850
A43: Bharti Airtel Limited - Crs | C43: 2472.1
A44: BHARTIBEN SATISHBHAI PATEL-CR | C44: 8000
A45: BHASKAR ENTERPRISE - Crs | C45: 239300
A46: BHUMAN ENTERPRISE-Crs | C46: 1610545.9
A47: Bhushan Deshpande - Employee | B47: 17998
A48: Bipin Jadhav Guest House - Crs | C48: 4500
A49: BISWAJIT RUI DAS - Crs | C49: 36262.88
A50: BN TRADING AND TRANSPORT COMPANY-CR | C50: 417743.16
A51: BOMMI SUNEEL KUMAR-Employee | B51: 25000
A52: B Stone Product - Crs | B52: 40.5
A53: CB SURATWALA AND SONS-CRS | C53: 88777
A54: Chettinad Cement Corporation Private Limited - Crs | C54: 3897886
A55: Chukha Ferro Alloys Pvt Ltd- Crs | C55: 32191.76
A56: CJ DARCL Logistics Limited-Crs | C56: 5095578.4
A57: Connect Residuary Pvt Ltd - Crs | C57: 32005897
A58: Continental Belting Pvt Ltd - Crs | B58: 24886
A59: Csrl-Structwel Lab (Pune) Private Limited Crs | C59: 3933
A60: CtrlP Solutions Private Limited - Crs | C60: 19952
A61: DAKSHIN GUJARAT VIJ CO LTD RTGS NEFT COLLECTION-CR | C61: 84591.33
A62: Dattakrupa Minerals - Crs | C62: 310552.2
A63: Deepak Shrivastava - Employee | C63: 17552
A64: DEEP ENTERPRISES-CRS | C64: 3000
A65: Desai Cement Company Pvt Ltd-Crs | B65: 13962953
A66: Devanand B. Singh - Employee | C66: 827999.28
A67: DEVENDRA CHAUHAN REFRACTORY WORKS -CRS | C67: 43200
A68: Dev Security Services- Crs | C68: 110640
A69: D & H SECHERON INFRASTRUCTURE PVT LTD - CRS | C69: 1376713
A70: Digambar A. Naik - Crs | B70: 29669.94
A71: D.K. SERVICES - Crs | C71: 16379.2
A72: DOED JUNG KUEN PHEN TRADING HOUSE-CRS | B72: 1949646.5
A73: DRS Cargo Movers Limited - Crs | B73: 21712
A74: Dutta Auto Centre | C74: 89869.4
A75: ECOGENT INDUSTRIES PRIVATE LIMITED - CRS | C75: 156615
A76: Eon Infotech Ltd - Crs | C76: 61970.68
A77: ETC POOL - Crs | B77: 183000
A78: Eurocem Additives Private Limited-Crs | B78: 714140
A79: Exalt Druk Enviroklens Pvt Ltd - Crs | B79: 2387615
A80: FAITH INFRA-CRS | C80: 542308.24
A81: FIRDOSH ERUCH ICHHAPORIA-Crs | C81: 20000
A82: Fourteckh Enviro India Pvt Ltd - Crs | B82: 1228000
A83: Ganesh Trading & Industries LLP - Crs | C83: 1800000
A84: Gautam Trading Company -Crs | C84: 9801.08
A85: G D Packaging - Crs | C85: 274308
A86: Harish Ludhani - Employee | C86: 459993.6
A87: Harrier Security Services Private Limited-Crs | C87: 172861.25
A88: Harsh Raj - EMPLOYEE | B88: 21035
A89: HDFC IOCL CREDIT CARD | C89: 1726002
A90: Hella Infra Market Limited-Crs | C90: 13769963
A91: Horiba India Private Limited - Crs | C91: 130732
A92: H R Industries - Crs | B92: 19032.8
A93: INDIA INTERNATIONAL COMPANY - Crs | C93: 1035872
A94: Indian Oil Corporation Limited - Crs | B94: 327580.04
A95: Info Tech Computers - Crs | C95: 10947
A96: JAI Energy Giant Engineering and consultancy - Crs | B96: 4692357
A97: JASSPER SHIPPING INDIA LIMITED- CRS | B97: 653396
A98: JFC Logistics - Crs | C98: 646998.8
A99: Jhuman Bagdi- Crs | C99: 6000
A100: JINDAL POWER LIMITED-Crs | C100: 249687
A101: JINENDRA AUTO PARTS-Crs | C101: 3800
...

Sheet Bill Wise
A1: Group : | B1: Sundry Creditors | D1: 1-Apr-26 to 30-Jun-26
A2: Details of: | B2: Pending Bills
A4: Date | B4: Ref. No. | C4: Party's Name | D4: Cost Center/Location | E4: Opening Amount | F4: Pending Amount | G4: Overdue Days | H4: Ageing Bucket | I4: New Amt
A5: 44357 | B5: CHN/2122/00447 | C5: Neptune Readymix Concrete Pvt. Ltd.(Cochin)-Vendor - Crs | D5: Bangalore | E5: 85567 | F5: 85567 | G5: 1846 | H5: Above 365 Days | I5: 85567
A6: 44361 | B6: CHN/2122/00452 | C6: Neptune Readymix Concrete Pvt. Ltd.(Cochin)-Vendor - Crs | D6: Bangalore | E6: 62940 | F6: 62940 | G6: 1842 | H6: Above 365 Days | I6: 62940
A7: 44383 | B7: CHN/2122/00448 | C7: Neptune Readymix Concrete Pvt. Ltd.(Cochin)-Vendor - Crs | D7: Bangalore | E7: 78182 | F7: 78182 | G7: 1820 | H7: Above 365 Days | I7: 78182
A8: 44400 | B8: CHN/2122/00453 | C8: Neptune Readymix Concrete Pvt. Ltd.(Cochin)-Vendor - Crs | D8: Bangalore | E8: 73765 | F8: 73765 | G8: 1803 | H8: Above 365 Days | I8: 73765
A9: 44456 | B9: CHN/2122/00543 | C9: Neptune Readymix Concrete Pvt. Ltd.(Cochin)-Vendor - Crs | D9: Bangalore | E9: 74180 | F9: 74180 | G9: 1747 | H9: Above 365 Days | I9: 74180
A10: 44473 | B10: CHN/2122/00547 | C10: Neptune Readymix Concrete Pvt. Ltd.(Cochin)-Vendor - Crs | D10: Bangalore | E10: 92865 | F10: 92865 | G10: 1730 | H10: Above 365 Days | I10: 92865
A11: 44488 | B11: CHN/2122/00548 | C11: Neptune Readymix Concrete Pvt. Ltd.(Cochin)-Vendor - Crs | D11: Bangalore | E11: 71512 | F11: 71512 | G11: 1715 | H11: Above 365 Days | I11: 71512
A12: 44493 | B12: CHN/2122/00560 | C12: Neptune Readymix Concrete Pvt. Ltd.(Cochin)-Vendor - Crs | D12: Bangalore | E12: 15314 | F12: 15314 | G12: 1710 | H12: Above 365 Days | I12: 15314
A13: 44500 | B13: CHN/2122/00562 | C13: Neptune Readymix Concrete Pvt. Ltd.(Cochin)-Vendor - Crs | D13: Bangalore | E13: 81842 | F13: 81842 | G13: 1703 | H13: Above 365 Days | I13: 81842
A14: 44535 | B14: CHN/2122/00579 | C14: Neptune Readymix Concrete Pvt. Ltd.(Cochin)-Vendor - Crs | D14: Bangalore | E14: 19959 | F14: 19959 | G14: 1668 | H14: Above 365 Days | I14: 19959
A15: 44545 | B15: CHN/21-22/00577 | C15: NEPTUNE READYMIX CONCRETE.PVT.LTD - MUPPATHADOM - Crs | D15: Bangalore | E15: 72416 | F15: 72416 | G15: 1658 | H15: Above 365 Days | I15: 72416
A16: 44546 | B16: CHN/21-22/00578 | C16: NEPTUNE READYMIX CONCRETE.PVT.LTD - MUPPATHADOM - Crs | D16: Bangalore | E16: 56484 | F16: 56484 | G16: 1657 | H16: Above 365 Days | I16: 56484
... A78: 45594 | B78: LSPL/24-25/400 | C78: Lub Solutions Pvt Ltd - Crs | D78: Goa | E78: 786935 | F78: 786935 | G78: 609 | H78: Above 365 Days | I78: 786935
A79: 45692 | B79: 509 | C79: ASHOKA BUILDCON LIMITED-Crs | E79: 800000 | F79: 13127.04 | G79: 511 | H79: Above 365 Days | I79: -13127.04
A80: 45722 | B80: 1750246755 | C80: SOCIAM EQUIPMENT SOLUTIONS PRIVATE LIMITED-CRS | D80: Gujarat | E80: 875733.94 | F80: 1529560 | G80: 481 | H80: Above 365 Days | I80: 1529560
A81: 45747 | B81: WEET/RDC/024 | C81: Well Erectors Of Engineering Technology Private Limited - Crs | E81: 1318560.8 | F81: 819292.57 | G81: 456 | H81: Above 365 Days | I81: 819292.57
A82: 45777 | B82: JV/HO/2526/0009 | C82: RDC Concrete (India) Pvt Ltd (Head Office) - Crs | D82: Head Office | E82: 943113.04 | F82: 1736215 | G82: 426 | H82: Above 365 Days | I82: 1736215
A83: 45798 | B83: 20KGRL/2025-26 | C83: KGR Logistics - Crs | D83: Nellore | E83: 1503348 | F83: 300000.7 | G83: 405 | H83: Above 365 Days | I83: 300000.7
A84: 45806 | B84: 038 | C84: SREERAMA INDUSTRIES PRIVATE LIMITED-Crs | D84: Vizag | E84: 247299 | F84: 172046 | G84: 397 | H84: Above 365 Days | I84: 172046
A85: 45808 | B85: JV/HO/2526/0024 | C85: RDC Concrete (India) Pvt Ltd (Head Office) - Crs | D85: Head Office | E85: 834281.26 | F85: 834281.26 | G85: 395 | H85: Above 365 Days | I85: 834281.26
A86: 45808 | B86: 07 | C86: TMS ENTERPRISES - Crs | D86: Gujarat | E86: 292918.56 | F86: 346127.76 | G86: 395 | H86: Above 365 Days | I86: 346127.76
A87: 45811 | B87: 027 | C87: Dattakrupa Minerals - Crs | D87: Goa | E87: 5610552.2 | F87: 310552.2 | G87: 392 | H87: Above 365 Days | I87: 310552.2
A88: 45812 | B88: PV/GUJ/2526/0123 | C88: Steel & Power-CR (CAP) - Crs | E88: 300000 | F88: 300000 | G88: 391 | H88: Above 365 Days | I88: -300000
A89: 45813 | B89: 190 | C89: SULTAN ENTERPRISES-CRS | E89: 110487.82 | F89: 110487.82 | G89: 390 | H89: Above 365 Days | I89: 110487.82
A90: 45814 | B90: 189 | C90: SULTAN ENTERPRISES-CRS | E90: 100716 | F90: 100716 | G90: 389 | H90: Above 365 Days | I90: 100716
A91: 45818 | B91: 191 | C91: SULTAN ENTERPRISES-CRS | E91: 106677.9 | F91: 106677.9 | G91: 385 | H91: Above 365 Days | I91: 106677.9
A92: 45825 | B92: 192 | C92: SULTAN ENTERPRISES-CRS | E92: 108055.5 | F92: 108055.5 | G92: 378 | H92: Above 365 Days | I92: 108055.5
A93: 45826 | B93: Ash/12 | C93: ASHCONNECT GLOBAL TRADING Pvt Ltd- Crs | E93: 537661 | F93: 64759.02 | G93: 377 | H93: Above 365 Days | I93: 64759.02
A94: 45838 | B94: ASH/13 | C94: ASHCONNECT GLOBAL TRADING Pvt Ltd- Crs | E94: 246403.27 | F94: 246403.27 | G94: 365 | H94: 181-365 Days | I94: 246403.27
A95: 45838 | B95: 2KL25ARMN10 | C95: RDC Concrete (India) Pvt Ltd (Kolkata)-Crs | D95: Panagarh (Aggregate) WB | E95: 3092863.7 | F95: 3022863.7 | G95: 365 | H95: 181-365 Days | I95: 3022863.7
A96: 45838 | B96: 2KL25ARMN12 | C96: RDC Concrete (India) Pvt Ltd (Kolkata)-Crs | D96: Gujarat | E96: 1279904.3 | F96: 1276850.8 | G96: 365 | H96: 181-365 Days | I96: 1276850.8
A97: 45839 | B97: JV/HO/2526/0073 | C97: RDC Concrete (India) Pvt Ltd (Head Office) - Crs | E97: 740750 | F97: 740750 | G97: 364 | H97: 181-365 Days | I97: 740750
A98: 45839 | B98: JV/GUJ/2526/0038 | C98: SHIVSHAKTI ENTERPRISES - Crs | E98: 649762.84 | F98: 649762.84 | G98: 364 | H98: 181-365 Days | I98: -649762.84
A99: 45858 | B99: Ash/15 | C99: ASHCONNECT GLOBAL TRADING Pvt Ltd- Crs | E99: 99570 | F99: 99570 | G99: 345 | H99: 181-365 Days | I99: 99570
A100: 45863 | B100: Ash/16 | C100: ASHCONNECT GLOBAL TRADING Pvt Ltd- Crs | E100: 150479 | F100: 150479 | G100: 340 | H100: 181-365 Days | I100: 150479
A101: 45869 | B101: HM27/2526/069328 | C101: Hella Infra Market Limited-Crs | E101: 1214662.7 | F101: 1214662.7 | G101: 334 | H101: 181-365 Days | I101: 1214662.7
A102: 45869 | B102: JV/HO/2526/0070 | C102: RDC Concrete (India) Pvt Ltd (Head Office) - Crs | E102: 821726.7 | F102: 821726.7 | G102: 334 | H102: 181-365 Days | I102: 821726.7
A103: 45869 | B103: 2KL25ARMN18 | C103: RDC Concrete (India) Pvt Ltd (Kolkata)-Crs | E103: 470229.2 | F103: 540132.83 | G103: 334 | H103: 181-365 Days | I103: 540132.83
A104: 45869 | B104: 13HY25ARMN18 | C104: RDC Concrete (India) Pvt Ltd (Telangana)- Crs | E104: 78487.5 | F104: 78487.5 | G104: 334 | H104: 181-365 Days | I104: 78487.5
A105: 45869 | B105: 252900006 | C105: ROBO SILICON PRIVATE LIMITED - Crs | E105: 1537000 | F105: 1462209 | G105: 334 | H105: 181-365 Days | I105: 1462209
A106: 45869 | B106: 252900007 | C106: ROBO SILICON PRIVATE LIMITED - Crs | E106: 87000 | F106: 87000 | G106: 334 | H106: 181-365 Days | I106: 87000
A107: 45874 | B107: 1CH25ARMN126 | C107: RDC Concrete (India) Pvt Ltd (Chennai)-Crs | E107: 23600 | F107: 23600 | G107: 329 | H107: 181-365 Days | I107: 23600
A108: 45884 | B108: 84 | C108: BAHUBALI CHEMICAL INDUSTRIES-CRS | D108: Gujarat | E108: 315544 | F108: 315544 | G108: 319 | H108: 181-365 Days | I108: 315544
A109: 45889 | B109: SE/27/2526/00182 | C109: SOCIAM EQUIPMENT SOLUTIONS PRIVATE LIMITED-CRS | E109: 329692 | F109: 297042 | G109: 314 | H109: 181-365 Days | I109: 297042
A110: 45891 | B110: Ash/21 | C110: ASHCONNECT GLOBAL TRADING Pvt Ltd- Crs | E110: 148183.88 | F110: 148183.88 | G110: 312 | H110: 181-365 Days | I110: 148183.88
A111: 45895 | B111: 88 | C111: BAHUBALI CHEMICAL INDUSTRIES-CRS | E111: 381352 | F111: 381352 | G111: 308 | H111: 181-365 Days | I111: 381352
A112: 45895 | B112: 89 | C112: BAHUBALI CHEMICAL INDUSTRIES-CRS | E112: 261936 | F112: 261936 | G112: 308 | H112: 181-365 Days | I112: 261936
A113: 45900 | B113: Ash/22 | C113: ASHCONNECT GLOBAL TRADING Pvt Ltd- Crs | E113: 315051.48 | F113: 315051.48 | G113: 303 | H113: 181-365 Days | I113: 315051.48
A114: 45900 | B114: JV/HO/2526/0085 | C114: RDC Concrete (India) Pvt Ltd (Head Office) - Crs | E114: 836447.59 | F114: 836447.59 | G114: 303 | H114: 181-365 Days | I114: 836447.59
A115: 45900 | B115: 2KL25ARMN56 | C115: RDC Concrete (India) Pvt Ltd (Kolkata)-Crs | E115: 470229.2 | F115: 470229.2 | G115: 303 | H115: 181-365 Days | I115: 470229.2
A116: 45900 | B116: 3KL25ARMN17 | C116: RDC Concrete (India) Pvt Ltd (Kolkata)-Crs | E116: 371831.28 | F116: 371831.28 | G116: 303 | H116: 181-365 Days | I116: 371831.28
A117: 45900 | B117: 13HY25ARMN19 | C117: RDC Concrete (India) Pvt Ltd (Telangana)- Crs | E117: 39243.75 | F117: 39243.75 | G117: 303 | H117: 181-365 Days | I117: 39243.75
A118: 45900 | B118: WEET/RDC/026 | C118: Well Erectors Of Engineering Technology Private Limited - Crs | E118: 474690.06 | F118: 474690.06 | G118: 303 | H118: 181-365 Days | I118: 474690.06
A119: 45901 | B119: SKA/ULT/0625/001 | C119: SOCIAM EQUIPMENT SOLUTIONS PRIVATE LIMITED-CRS | E119: 516200 | F119: 516200 | G119: 302 | H119: 181-365 Days | I119: 516200
A120: 45902 | B120: SKA/ULT/0625/002 | C120: SOCIAM EQUIPMENT SOLUTIONS PRIVATE LIMITED-CRS | E120: 516200 | F120: 1032400 | G120: 301 | H120: 181-365 Days | I120: 1032400
A121: 45903 | B121: 92 | C121: BAHUBALI CHEMICAL INDUSTRIES-CRS | D121: Gujarat | E121: 359676 | F121: 359676 | G121: 300 | H121: 181-365 Days | I121: 359676
A122: 45904 | B122: SE/29/2526/00146 | C122: SOCIAM EQUIPMENT SOLUTIONS PRIVATE LIMITED-CRS | E122: 516200 | F122: 516200 | G122: 299 | H122: 181-365 Days | I122: 516200
A123: 45905 | B123: SE/29/2526/00181 | C123: SOCIAM EQUIPMENT SOLUTIONS PRIVATE LIMITED-CRS | E123: 516199.76 | F123: 516199.76 | G123: 298 | H123: 181-365 Days | I123: 516199.76
A124: 45906 | B124: 95 | C124: BAHUBALI CHEMICAL INDUSTRIES-CRS | E124: 333716 | F124: 333716 | G124: 297 | H124: 181-365 Days | I124: 333716
A125: 45909 | B125: 99 | C125: BAHUBALI CHEMICAL INDUSTRIES-CRS | E125: 353965 | F125: 353965 | G125: 294 | H125: 181-365 Days | I125: 353965
A126: 45919 | B126: PV/WBA/2526/0170 | C126: ASHOKA BUILDCON LIMITED-Crs | E126: 150000 | F126: 150000 | G126: 284 | H126: 181-365 Days | I126: -150000
A127: 45919 | B127: PV/WBA/2526/0156 | C127: M/s Manuwar Shaikh (Crusher)- Crs | E127: 1600000 | F127: 600000 | G127: 284 | H127: 181-365 Days | I127: -600000
A128: 45929 | B128: 13HY25ARMN23 | C128: RDC Concrete (India) Pvt Ltd (Telangana)- Crs | E128: 78487.5 | F128: 78487.5 | G128: 274 | H128: 181-365 Days | I128: 78487.5
A129: 45930 | B129: GOA/25-26/0340 | C129: JFC Logistics - Crs | D129: Goa | E129: 31320 | F129: 14265.9 | G129: 273 | H129: 181-365 Days | I129: 14265.9
A130: 45930 | B130: 6CH25ARMN109 | C130: RDC Concrete (India) Pvt Ltd (Chennai)-Crs | E130: 63720 | F130: 63720 | G130: 273 | H130: 181-365 Days | I130: 63720
A131: 45930 | B131: JV/HO/2526/0099 | C131: RDC Concrete (India) Pvt Ltd (Head Office) - Crs | E131: 927486 | F131: 927486 | G131: 273 | H131: 181-365 Days | I131: 927486
A132: 45930 | B132: 3KL25ARMN26 | C132: RDC Concrete (India) Pvt Ltd (Kolkata)-Crs | E132: 311495.64 | F132: 311495.64 | G132: 273 | H132: 181-365 Days | I132: 311495.64
A133: 45930 | B133: 2KL25ARMN86 | C133: RDC Concrete (India) Pvt Ltd (Kolkata)-Crs | E133: 470229.6 | F133: 470229.6 | G133: 273 | H133: 181-365 Days | I133: 470229.6
A134: 45930 | B134: 13HY25ARMN22 | C134: RDC Concrete (India) Pvt Ltd (Telangana)- Crs | E134: 180521.26 | F134: 180521.26 | G134: 273 | H134: 181-365 Days | I134: 180521.26
A135: 45930 | B135: 13HY25ARMN21 | C135: RDC Concrete (India) Pvt Ltd (Telangana)- Crs | E135: 78487.5 | F135: 78487.5 | G135: 273 | H135: 181-365 Days | I135: 78487.5
A136: 45930 | B136: 252900008 | C136: ROBO SILICON PRIVATE LIMITED - Crs | E136: 1537000 | F136: 1537000 | G136: 273 | H136: 181-365 Days | I136: 1537000
A137: 45930 | B137: 252900009 | C137: ROBO SILICON PRIVATE LIMITED - Crs | E137: 87000 | F137: 87000 | G137: 273 | H137: 181-365 Days | I137: 87000
A138: 45931 | B138: 2SR25ARS33 | C138: RDC Concrete (India) Pvt Ltd (Gujarat)-Crs | E138: 41919.5 | F138: 41919.5 | G138: 272 | H138: 181-365 Days | I138: 41919.5
A139: 45931 | B139: 2SR25ARS34 | C139: RDC Concrete (India) Pvt Ltd (Gujarat)-Crs | E139: 35931 | F139: 35931 | G139: 272 | H139: 181-365 Days | I139: 35931
A140: 45931 | B140: BNWBDRG25000223 | C140: SIS LIMITED-CRS | E140: 81264.24 | F140: 81264.24 | G140: 272 | H140: 181-365 Days | I140: 81264.24
A141: 45931 | B141: BNWBDRG25000386 | C141: SIS LIMITED-CRS | E141: 81257.24 | F141: 51455.36 | G141: 272 | H141: 181-365 Days | I141: 51455.36
... A155: 45961 | B155: Ash/23 | C155: ASHCONNECT GLOBAL TRADING Pvt Ltd- Crs | E155: 1220804 | F155: 1220804 | G155: 242 | H155: 181-365 Days | I155: 1220804
A156: 45961 | B156: LUK/UF-ST/RA 10 | C156: Luk Enterprises - Crs | D156: Gujarat | E156: 972689.57 | F156: 627771.51 | G156: 242 | H156: 181-365 Days | I156: 627771.51
A157: 45961 | B157: 6CH25ARMN120 | C157: RDC Concrete (India) Pvt Ltd (Chennai)-Crs | E157: 63720 | F157: 63720 | G157: 242 | H157: 181-365 Days | I157: 63720
A158: 45961 | B158: JV/HO/2526/0124 | C158: RDC Concrete (India) Pvt Ltd (Head Office) - Crs | E158: 912752.5 | F158: 912752.5 | G158: 242 | H158: 181-365 Days | I158: 912752.5
A159: 45961 | B159: 2KL25ARMN116 | C159: RDC Concrete (India) Pvt Ltd (Kolkata)-Crs | E159: 470229.6 | F159: 470229.6 | G159: 242 | H159: 181-365 Days | I159: 470229.6
A160: 45961 | B160: 3KL25ARMN29 | C160: RDC Concrete (India) Pvt Ltd (Kolkata)-Crs | E160: 316850.64 | F160: 316850.64 | G160: 242 | H160: 181-365 Days | I160: 316850.64
A161: 45961 | B161: 13HY25ARMN24 | C161: RDC Concrete (India) Pvt Ltd (Telangana)- Crs | E161: 78487.5 | F161: 78487.5 | G161: 242 | H161: 181-365 Days | I161: 78487.5
A162: 45961 | B162: 252900012 | C162: ROBO SILICON PRIVATE LIMITED - Crs | E162: 1537000 | F162: 1537000 | G162: 242 | H162: 181-365 Days | I162: 1537000
A163: 45961 | B163: 252900011 | C163: ROBO SILICON PRIVATE LIMITED - Crs | E163: 87000 | F163: 87000 | G163: 242 | H163: 181-365 Days | I163: 87000
A164: 45961 | B164: 252900010 | C164: ROBO SILICON PRIVATE LIMITED - Crs | E164: 1537000 | F164: 1537000 | G164: 242 | H164: 181-365 Days | I164: 1537000
A165: 45961 | B165: SE/29/2526/00252 | C165: SOCIAM EQUIPMENT SOLUTIONS PRIVATE LIMITED-CRS | E165: 412960 | F165: 412960 | G165: 242 | H165: 181-365 Days | I165: 412960
A166: 45961 | B166: SE/29/2526/00254 | C166: SOCIAM EQUIPMENT SOLUTIONS PRIVATE LIMITED-CRS | E166: 412960 | F166: 412960 | G166: 242 | H166: 181-365 Days | I166: 412960
A167: 45962 | B167: ABB/018/25-26 | C167: Akash Body Bildders-CRS | E167: 977175.5 | F167: 300000.02 | G167: 241 | H167: 181-365 Days | I167: 300000.02
A168: 45962 | B168: JV/GOA/2526/0231 | C168: JASSPER SHIPPING INDIA LIMITED- CRS | E168: 653396 | F168: 653396 | G168: 241 | H168: 181-365 Days | I168: -653396
... A193: 45993 | B193: 132 | C193: BAHUBALI CHEMICAL INDUSTRIES-CRS | E193: 322293 | F193: 322293 | G193: 210 | H193: 181-365 Days | I193: 322293
A194: 46000 | B194: 72_04.12.2025 | C194: P A Steel and Co - Crs | D194: Nagpur | E194: 1031733 | F194: 231733 | G194: 203 | H194: 181-365 Days | I194: 231733
A195: 46000 | B195: 13HY25ARMN36 | C195: RDC Concrete (India) Pvt Ltd (Telangana)- Crs | E195: 78487.5 | F195: 78487.5 | G195: 203 | H195: 181-365 Days | I195: 78487.5
A196: 46002 | B196: 139 | C196: BAHUBALI CHEMICAL INDUSTRIES-CRS | E196: 334624 | F196: 334624 | G196: 201 | H196: 181-365 Days | I196: 334624
A197: 46007 | B197: 13HY25ARMN39 | C197: RDC Concrete (India) Pvt Ltd (Telangana)- Crs | E197: 78487.5 | F197: 78487.5 | G197: 196 | H197: 181-365 Days | I197: 78487.5
A198: 46009 | B198: 145 | C198: BAHUBALI CHEMICAL INDUSTRIES-CRS | D198: wada | E198: 329432 | F198: 329432 | G198: 194 | H198: 181-365 Days | I198: 329432
A199: 46011 | B199: 13HY25ARMN40 | C199: RDC Concrete (India) Pvt Ltd (Telangana)- Crs | E199: 47092.5 | F199: 47092.5 | G199: 192 | H199: 181-365 Days | I199: 47092.5
...

Sheet Only Creditors
A1: Ultrafine Mineral & Admixtures Pvt. Ltd.
A2: Creditors Ageing Report | As at 30-June-2026
B3: SUBTOTAL | G3: =SUBTOTAL(9,G5:G189) -> 1.8275048e+08 | H3: =SUBTOTAL(9,H5:H189) -> 1.0932552e+08 | I3: =SUBTOTAL(9,I5:I189) -> 13959870 | J3: =SUBTOTAL(9,J5:J189) -> 12910755 | K3: =SUBTOTAL(9,K5:K189) -> 10238610 | L3: =SUBTOTAL(9,L5:L189) -> 18449869 | M3: =SUBTOTAL(9,M5:M189) -> 1354071.3 | N3: =SUBTOTAL(9,N5:N189) -> 10572313 | ... Q3: =SUBTOTAL(9,Q5:Q189) -> 660.95
A4: # | B4: Vendor Name | C4: Location | D4: Vendor Type | E4: Vendor Sub Type | G4: TB Balance (Cr) | H4: 0-30 Days | I4: 31-60 Days | J4: 61-90 Days | K4: 91-120 Days | L4: 121-150 Days | M4: 151-180 Days | N4: 181-365 Days | O4: Above 365 Days | P4: BW Total | Q4: Diff (TB-BW)
A6: 1 | B6: Ram Innovation & Solutions-Crs | C6: Gujarat | D6: Raw Material | E6: Slag | G6: =IFERROR(SUMIFS(TB!C:C,TB!A:A,B6)-SUMIFS(TB!B:B,TB!A:A,B6),0) -> 1000 | H6: =SUMIFS('Bill Wise'!I:I,'Bill Wise'!C:C,B6,'Bill Wise'!H:H,"0-30 Days") -> 1000 | I6: =SUMIFS('Bill Wise'!I:I,'Bill Wise'!C:C,B6,'Bill Wise'!H:H,"31-60 Days") -> 0 | J6: =SUMIFS('Bill Wise'!I:I,'Bill Wise'!C:C,B6,'Bill Wise'!H:H,"61-90 Days") -> 0 | K6: =SUMIFS('Bill Wise'!I:I,'Bill Wise'!C:C,B6,'Bill Wise'!H:H,"91-120 Days") -> 0 | L6: =SUMIFS('Bill Wise'!I:I,'Bill Wise'!C:C,B6,'Bill Wise'!H:H,"121-150 Days") -> 0 | M6: =SUMIFS('Bill Wise'!I:I,'Bill Wise'!C:C,B6,'Bill Wise'!H:H,"151-180 Days") -> 0 | N6: =SUMIFS('Bill Wise'!I:I,'Bill Wise'!C:C,B6,'Bill Wise'!H:H,"181-365 Days") -> 0 | O6: =SUMIFS('Bill Wise'!I:I,'Bill Wise'!C:C,B6,'Bill Wise'!H:H,"Above 365 Days") -> 0 | P6: =SUM(H6:O6) -> 1000 | Q6: =G6-P6 -> 0
A7: 2 | B7: Sumangala Naik - Crs | C7: Goa | D7: Expenses | E7: Rent | G7: =IFERROR(SUMIFS(TB!C:C,TB!A:A,B7)-SUMIFS(TB!B:B,TB!A:A,B7),0) -> 2000 | H7: =SUMIFS('Bill Wise'!I:I,'Bill Wise'!C:C,B7,'Bill Wise'!H:H,"0-30 Days") -> 2000 | I7: =SUMIFS('Bill Wise'!I:I,'Bill Wise'!C:C,B7,'Bill Wise'!H:H,"31-60 Days") -> 0 | J7: =SUMIFS('Bill Wise'!I:I,'Bill Wise'!C:C,B7,'Bill Wise'!H:H,"61-90 Days") -> 0 | K7: =SUMIFS('Bill Wise'!I:I,'Bill Wise'!C:C,B7,'Bill Wise'!H:H,"91-120 Days") -> 0 | L7: =SUMIFS('Bill Wise'!I:I,'Bill Wise'!C:C,B7,'Bill Wise'!H:H,"121-150 Days") -> 0 | M7: =SUMIFS('Bill Wise'!I:I,'Bill Wise'!C:C,B7,'Bill Wise'!H:H,"151-180 Days") -> 0 | N7: =SUMIFS('Bill Wise'!I:I,'Bill Wise'!C:C,B7,'Bill Wise'!H:H,"181-365 Days") -> 0 | O7: =SUMIFS('Bill Wise'!I:I,'Bill Wise'!C:C,B7,'Bill Wise'!H:H,"Above 365 Days") -> 0 | P7: =SUM(H7:O7) -> 2000 | Q7: =G7-P7 -> 0
A8: 3 | B8: Bharti Airtel Limited - Crs | C8: Goa | D8: Expenses | E8: Telephone Exps | G8: =IFERROR(SUMIFS(TB!C:C,TB!A:A,B8)-SUMIFS(TB!B:B,TB!A:A,B8),0) -> 2472.1 | H8: =SUMIFS('Bill Wise'!I:I,'Bill Wise'!C:C,B8,'Bill Wise'!H:H,"0-30 Days") -> 2472.1 | I8: =SUMIFS('Bill Wise'!I:I,'Bill Wise'!C:C,B8,'Bill Wise'!H:H,"31-60 Days") -> 0 | J8: =SUMIFS('Bill Wise'!I:I,'Bill Wise'!C:C,B8,'Bill Wise'!H:H,"61-90 Days") -> 0 | K8: =SUMIFS('Bill Wise'!I:I,'Bill Wise'!C:C,B8,'Bill Wise'!H:H,"91-120 Days") -> 0 | L8: =SUMIFS('Bill Wise'!I:I,'Bill Wise'!C:C,B8,'Bill Wise'!H:H,"121-150 Days") -> 0 | M8: =SUMIFS('Bill Wise'!I:I,'Bill Wise'!C:C,B8,'Bill Wise'!H:H,"151-180 Days") -> 0 | N8: =SUMIFS('Bill Wise'!I:I,'Bill Wise'!C:C,B8,'Bill Wise'!H:H,"181-365 Days") -> 0 | O8: =SUMIFS('Bill Wise'!I:I,'Bill Wise'!C:C,B8,'Bill Wise'!H:H,"Above 365 Days") -> 0 | P8: =SUM(H8:O8) -> 2472.1 | Q8: =G8-P8 -> 0
A9: 4 | B9: Arya CS - Crs | C9: Kerala | D9: Expenses | E9: Rent | G9: =IFERROR(SUMIFS(TB!C:C,TB!A:A,B9)-SUMIFS(TB!B:B,TB!A:A,B9),0) -> 3000 | H9: =SUMIFS('Bill Wise'!I:I,'Bill Wise'!C:C,B9,'Bill Wise'!H:H,"0-30 Days") -> 3000 | I9: =SUMIFS('Bill Wise'!I:I,'Bill Wise'!C:C,B9,'Bill Wise'!H:H,"31-60 Days") -> 0 | J9: =SUMIFS('Bill Wise'!I:I,'Bill Wise'!C:C,B9,'Bill Wise'!H:H,"61-90 Days") -> 0 | K9: =SUMIFS('Bill Wise'!I:I,'Bill Wise'!C:C,B9,'Bill Wise'!H:H,"91-120 Days") -> 0 | L9: =SUMIFS('Bill Wise'!I:I,'Bill Wise'!C:C,B9,'Bill Wise'!H:H,"121-150 Days") -> 0 | M9: =SUMIFS('Bill Wise'!I:I,'Bill Wise'!C:C,B9,'Bill Wise'!H:H,"151-180 Days") -> 0 | N9: =SUMIFS('Bill Wise'!I:I,'Bill Wise'!C:C,B9,'Bill Wise'!H:H,"181-365 Days") -> 0 | O9: =SUMIFS('Bill Wise'!I:I,'Bill Wise'!C:C,B9,'Bill Wise'!H:H,"Above 365 Days") -> 0 | P9: =SUM(H9:O9) -> 3000 | Q9: =G9-P9 -> 0
A10: 5 | B10: DEEP ENTERPRISES-CRS | C10: Nagpur | D10: Expenses | E10: Office Exps | G10: =IFERROR(SUMIFS(TB!C:C,TB!A:A,B10)-SUMIFS(TB!B:B,TB!A:A,B10),0) -> 3000 | H10: =SUMIFS('Bill Wise'!I:I,'Bill Wise'!C:C,B10,'Bill Wise'!H:H,"0-30 Days") -> 3000 | I10: =SUMIFS('Bill Wise'!I:I,'Bill Wise'!C:C,B10,'Bill Wise'!H:H,"31-60 Days") -> 0 | J10: =SUMIFS('Bill Wise'!I:I,'Bill Wise'!C:C,B10,'Bill Wise'!H:H,"61-90 Days") -> 0 | K10: =SUMIFS('Bill Wise'!I:I,'Bill Wise'!C:C,B10,'Bill Wise'!H:H,"91-120 Days") -> 0 | L10: =SUMIFS('Bill Wise'!I:I,'Bill Wise'!C:C,B10,'Bill Wise'!H:H,"121-150 Days") -> 0 | M10: =SUMIFS('Bill Wise'!I:I,'Bill Wise'!C:C,B10,'Bill Wise'!H:H,"151-180 Days") -> 0 | N10: =SUMIFS('Bill Wise'!I:I,'Bill Wise'!C:C,B10,'Bill Wise'!H:H,"181-365 Days") -> 0 | O10: =SUMIFS('Bill Wise'!I:I,'Bill Wise'!C:C,B10,'Bill Wise'!H:H,"Above 365 Days") -> 0 | P10: =SUM(H10:O10) -> 3000 | Q10: =G10-P10 -> 0
A11: 6 | B11: Abhay Singh-Employee | C11: Head Office | D11: Employee | E11: Claim Exps | G11: =IFERROR(SUMIFS(TB!C:C,TB!A:A,B11)-SUMIFS(TB!B:B,TB!A:A,B11),0) -> 3519 | H11: =SUMIFS('Bill Wise'!I:I,'Bill Wise'!C:C,B11,'Bill Wise'!H:H,"0-30 Days") -> 3519 | I11: =SUMIFS('Bill Wise'!I:I,'Bill Wise'!C:C,B11,'Bill Wise'!H:H,"31-60 Days") -> 0 | J11: =SUMIFS('Bill Wise'!I:I,'Bill Wise'!C:C,B11,'Bill Wise'!H:H,"61-90 Days") -> 0 | K11: =SUMIFS('Bill Wise'!I:I,'Bill Wise'!C:C,B11,'Bill Wise'!H:H,"91-120 Days") -> 0 | L11: =SUMIFS('Bill Wise'!I:I,'Bill Wise'!C:C,B11,'Bill Wise'!H:H,"121-150 Days") -> 0 | M11: =SUMIFS('Bill Wise'!I:I,'Bill Wise'!C:C,B11,'Bill Wise'!H:H,"151-180 Days") -> 0 | N11: =SUMIFS('Bill Wise'!I:I,'Bill Wise'!C:C,B11,'Bill Wise'!H:H,"181-365 Days") -> 0 | O11: =SUMIFS('Bill Wise'!I:I,'Bill Wise'!C:C,B11,'Bill Wise'!H:H,"Above 365 Days") -> 0 | P11: =SUM(H11:O11) -> 3519 | Q11: =G11-P11 -> 0
A12: 7 | B12: Yaa Baba Taj Restaurants - CRS | C12: Nagpur | D12: Expenses | E12: Office Exps | G12: =IFERROR(SUMIFS(TB!C:C,TB!A:A,B12)-SUMIFS(TB!B:B,TB!A:A,B12),0) -> 3606 | H12: =SUMIFS('Bill Wise'!I:I,'Bill Wise'!C:C,B12,'Bill Wise'!H:H,"0-30 Days") -> 3606 | I12: =SUMIFS('Bill Wise'!I:I,'Bill Wise'!C:C,B12,'Bill Wise'!H:H,"31-60 Days") -> 0 | J12: =SUMIFS('Bill Wise'!I:I,'Bill Wise'!C:C,B12,'Bill Wise'!H:H,"61-90 Days") -> 0 | K12: =SUMIFS('Bill Wise'!I:I,'Bill Wise'!C:C,B12,'Bill Wise'!H:H,"91-120 Days") -> 0 | L12: =SUMIFS('Bill Wise'!I:I,'Bill Wise'!C:C,B12,'Bill Wise'!H:H,"121-150 Days") -> 0 | M12: =SUMIFS('Bill Wise'!I:I,'Bill Wise'!C:C,B12,'Bill Wise'!H:H,"151-180 Days") -> 0 | N12: =SUMIFS('Bill Wise'!I:I,'Bill Wise'!C:C,B12,'Bill Wise'!H:H,"181-365 Days") -> 0 | O12: =SUMIFS('Bill Wise'!I:I,'Bill Wise'!C:C,B12,'Bill Wise'!H:H,"Above 365 Days") -> 0 | P12: =SUM(H12:O12) -> 3606 | Q12: =G12-P12 -> 0
A13: 8 | B13: JINENDRA AUTO PARTS-Crs | C13: Gujarat | D13: Expenses | E13: Store and spare | G13: =IFERROR(SUMIFS(TB!C:C,TB!A:A,B13)-SUMIFS(TB!B:B,TB!A:A,B13),0) -> 3800 | H13: =SUMIFS('Bill Wise'!I:I,'Bill Wise'!C:C,B13,'Bill Wise'!H:H,"0-30 Days") -> 3800 | I13: =SUMIFS('Bill Wise'!I:I,'Bill Wise'!C:C,B13,'Bill Wise'!H:H,"31-60 Days") -> 0 | J13: =SUMIFS('Bill Wise'!I:I,'Bill Wise'!C:C,B13,'Bill Wise'!H:H,"61-90 Days") -> 0 | K13: =SUMIFS('Bill Wise'!I:I,'Bill Wise'!C:C,B13,'Bill Wise'!H:H,"91-120 Days") -> 0 | L13: =SUMIFS('Bill Wise'!I:I,'Bill Wise'!C:C,B13,'Bill Wise'!H:H,"121-150 Days") -> 0 | M13: =SUMIFS('Bill Wise'!I:I,'Bill Wise'!C:C,B13,'Bill Wise'!H:H,"151-180 Days") -> 0 | N13: =SUMIFS('Bill Wise'!I:I,'Bill Wise'!C:C,B13,'Bill Wise'!H:H,"181-365 Days") -> 0 | O13: =SUMIFS('Bill Wise'!I:I,'Bill Wise'!C:C,B13,'Bill Wise'!H:H,"Above 365 Days") -> 0 | P13: =SUM(H13:O13) -> 3800 | Q13: =G13-P13 -> 0
A14: 9 | B14: Csrl-Structwel Lab (Pune) Private Limited Crs | C14: Nagpur | D14: Expenses | E14: 0 | G14: =IFERROR(SUMIFS(TB!C:C,TB!A:A,B14)-SUMIFS(TB!B:B,TB!A:A,B14),0) -> 3933 | H14: =SUMIFS('Bill Wise'!I:I,'Bill Wise'!C:C,B14,'Bill Wise'!H:H,"0-30 Days") -> 3933 | I14: =SUMIFS('Bill Wise'!I:I,'Bill Wise'!C:C,B14,'Bill Wise'!H:H,"31-60 Days") -> 0 | J14: =SUMIFS('Bill Wise'!I:I,'Bill Wise'!C:C,B14,'Bill Wise'!H:H,"61-90 Days") -> 0 | K14: =SUMIFS('Bill Wise'!I:I,'Bill Wise'!C:C,B14,'Bill Wise'!H:H,"91-120 Days") -> 0 | L14: =SUMIFS('Bill Wise'!I:I,'Bill Wise'!C:C,B14,'Bill Wise'!H:H,"121-150 Days") -> 0 | M14: =SUMIFS('Bill Wise'!I:I,'Bill Wise'!C:C,B14,'Bill Wise'!H:H,"151-180 Days") -> 0 | N14: =SUMIFS('Bill Wise'!I:I,'Bill Wise'!C:C,B14,'Bill Wise'!H:H,"181-365 Days") -> 0 | O14: =SUMIFS('Bill Wise'!I:I,'Bill Wise'!C:C,B14,'Bill Wise'!H:H,"Above 365 Days") -> 0 | P14: =SUM(H14:O14) -> 3933 | Q14: =G14-P14 -> 0
A15: 10 | B15: S. K. Traders-Crs | C15: Gujarat | D15: Expenses | E15: 0 | G15: =IFERROR(SUMIFS(TB!C:C,TB!A:A,B15)-SUMIFS(TB!B:B,TB!A:A,B15),0) -> 4130 | H15: =SUMIFS('Bill Wise'!I:I,'Bill Wise'!C:C,B15,'Bill Wise'!H:H,"0-30 Days") -> 4130 | I15: =SUMIFS('Bill Wise'!I:I,'Bill Wise'!C:C,B15,'Bill Wise'!H:H,"31-60 Days") -> 0 | J15: =SUMIFS('Bill Wise'!I:I,'Bill Wise'!C:C,B15,'Bill Wise'!H:H,"61-90 Days") -> 0 | K15: =SUMIFS('Bill Wise'!I:I,'Bill Wise'!C:C,B15,'Bill Wise'!H:H,"91-120 Days") -> 0 | L15: =SUMIFS('Bill Wise'!I:I,'Bill Wise'!C:C,B15,'Bill Wise'!H:H,"121-150 Days") -> 0 | M15: =SUMIFS('Bill Wise'!I:I,'Bill Wise'!C:C,B15,'Bill Wise'!H:H,"151-180 Days") -> 0 | N15: =SUMIFS('Bill Wise'!I:I,'Bill Wise'!C:C,B15,'Bill Wise'!H:H,"181-365 Days") -> 0 | O15: =SUMIFS('Bill Wise'!I:I,'Bill Wise'!C:C,B15,'Bill Wise'!H:H,"Above 365 Days") -> 0 | P15: =SUM(H15:O15) -> 4130 | Q15: =G15-P15 -> 0
A16: 11 | B16: Bipin Jadhav Guest House - Crs | C16: Wada | D16: Expenses | E16: Rent | G16: =IFERROR(SUMIFS(TB!C:C,TB!A:A,B16)-SUMIFS(TB!B:B,TB!A:A,B16),0) -> 4500 | H16: =SUMIFS('Bill Wise'!I:I,'Bill Wise'!C:C,B16,'Bill Wise'!H:H,"0-30 Days") -> 4500 | I16: =SUMIFS('Bill Wise'!I:I,'Bill Wise'!C:C,B16,'Bill Wise'!H:H,"31-60 Days") -> 0 | J16: =SUMIFS('Bill Wise'!I:I,'Bill Wise'!C:C,B16,'Bill Wise'!H:H,"61-90 Days") -> 0 | K16: =SUMIFS('Bill Wise'!I:I,'Bill Wise'!C:C,B16,'Bill Wise'!H:H,"91-120 Days") -> 0 | L16: =SUMIFS('Bill Wise'!I:I,'Bill Wise'!C:C,B16,'Bill Wise'!H:H,"121-150 Days") -> 0 | M16: =SUMIFS('Bill Wise'!I:I,'Bill Wise'!C:C,B16,'Bill Wise'!H:H,"151-180 Days") -> 0 | N16: =SUMIFS('Bill Wise'!I:I,'Bill Wise'!C:C,B16,'Bill Wise'!H:H,"181-365 Days") -> 0 | O16: =SUMIFS('Bill Wise'!I:I,'Bill Wise'!C:C,B16,'Bill Wise'!H:H,"Above 365 Days") -> 0 | P16: =SUM(H16:O16) -> 4500 | Q16: =G16-P16 -> 0
A17: 12 | B17: Ramakant L Dalal - Crs | C17: Nagpur | D17: Expenses | E17: Repair & Maintenance | G17: =IFERROR(SUMIFS(TB!C:C,TB!A:A,B17)-SUMIFS(TB!B:B,TB!A:A,B17),0) -> 4851 | H17: =SUMIFS('Bill Wise'!I:I,'Bill Wise'!C:C,B17,'Bill Wise'!H:H,"0-30 Days") -> 4851 | I17: =SUMIFS('Bill Wise'!I:I,'Bill Wise'!C:C,B17,'Bill Wise'!H:H,"31-60 Days") -> 0 | J17: =SUMIFS('Bill Wise'!I:I,'Bill Wise'!C:C,B17,'Bill Wise'!H:H,"61-90 Days") -> 0 | K17: =SUMIFS('Bill Wise'!I:I,'Bill Wise'!C:C,B17,'Bill Wise'!H:H,"91-120 Days") -> 0 | L17: =SUMIFS('Bill Wise'!I:I,'Bill Wise'!C:C,B17,'Bill Wise'!H:H,"121-150 Days") -> 0 | M17: =SUMIFS('Bill Wise'!I:I,'Bill Wise'!C:C,B17,'Bill Wise'!H:H,"151-180 Days") -> 0 | N17: =SUMIFS('Bill Wise'!I:I,'Bill Wise'!C:C,B17,'Bill Wise'!H:H,"181-365 Days") -> 0 | O17: =SUMIFS('Bill Wise'!I:I,'Bill Wise'!C:C,B17,'Bill Wise'!H:H,"Above 365 Days") -> 0 | P17: =SUM(H17:O17) -> 4851 | Q17: =G17-P17 -> 0
A18: 13 | B18: MADAN MOHAN SINGH-CRS | C18: Gujarat | D18: Expenses | E18: Staff Welfare | G18: =IFERROR(SUMIFS(TB!C:C,TB!A:A,B18)-SUMIFS(TB!B:B,TB!A:A,B18),0) -> 4970 | H18: =SUMIFS('Bill Wise'!I:I,'Bill Wise'!C:C,B18,'Bill Wise'!H:H,"0-30 Days") -> 4970 | I18: =SUMIFS('Bill Wise'!I:I,'Bill Wise'!C:C,B18,'Bill Wise'!H:H,"31-60 Days") -> 0 | J18: =SUMIFS('Bill Wise'!I:I,'Bill Wise'!C:C,B18,'Bill Wise'!H:H,"61-90 Days") -> 0 | K18: =SUMIFS('Bill Wise'!I:I,'Bill Wise'!C:C,B18,'Bill Wise'!H:H,"91-120 Days") -> 0 | L18: =SUMIFS('Bill Wise'!I:I,'Bill Wise'!C:C,B18,'Bill Wise'!H:H,"121-150 Days") -> 0 | M18: =SUMIFS('Bill Wise'!I:I,'Bill Wise'!C:C,B18,'Bill Wise'!H:H,"151-180 Days") -> 0 | N18: =SUMIFS('Bill Wise'!I:I,'Bill Wise'!C:C,B18,'Bill Wise'!H:H,"181-365 Days") -> 0 | O18: =SUMIFS('Bill Wise'!I:I,'Bill Wise'!C:C,B18,'Bill Wise'!H:H,"Above 365 Days") -> 0 | P18: =SUM(H18:O18) -> 4970 | Q18: =G18-P18 -> 0
A19: 14 | B19: KAPIL THAKARE - Crs | C19: wada | D19: Expenses | E19: Office Exps | G19: =IFERROR(SUMIFS(TB!C:C,TB!A:A,B19)-SUMIFS(TB!B:B,TB!A:A,B19),0) -> 5705 | H19: =SUMIFS('Bill Wise'!I:I,'Bill Wise'!C:C,B19,'Bill Wise'!H:H,"0-30 Days") -> 5705 | I19: =SUMIFS('Bill Wise'!I:I,'Bill Wise'!C:C,B19,'Bill Wise'!H:H,"31-60 Days") -> 0 | J19: =SUMIFS('Bill Wise'!I:I,'Bill Wise'!C:C,B19,'Bill Wise'!H:H,"61-90 Days") -> 0 | K19: =SUMIFS('Bill Wise'!I:I,'Bill Wise'!C:C,B19,'Bill Wise'!H:H,"91-120 Days") -> 0 | L19: =SUMIFS('Bill Wise'!I:I,'Bill Wise'!C:C,B19,'Bill Wise'!H:H,"121-150 Days") -> 0 | M19: =SUMIFS('Bill Wise'!I:I,'Bill Wise'!C:C,B19,'Bill Wise'!H:H,"151-180 Days") -> 0 | N19: =SUMIFS('Bill Wise'!I:I,'Bill Wise'!C:C,B19,'Bill Wise'!H:H,"181-365 Days") -> 0 | O19: =SUMIFS('Bill Wise'!I:I,'Bill Wise'!C:C,B19,'Bill Wise'!H:H,"Above 365 Days") -> 0 | P19: =SUM(H19:O19) -> 5705 | Q19: =G19-P19 -> 0
A20: 15 | B20: Mohd. Saif - Employee | C20: Head Office | D20: Employee | E20: Claim Exps | G20: =IFERROR(SUMIFS(TB!C:C,TB!A:A,B20)-SUMIFS(TB!B:B,TB!A:A,B20),0) -> 5757 | H20: =SUMIFS('Bill Wise'!I:I,'Bill Wise'!C:C,B20,'Bill Wise'!H:H,"0-30 Days") -> 5757 | I20: =SUMIFS('Bill Wise'!I:I,'Bill Wise'!C:C,B20,'Bill Wise'!H:H,"31-60 Days") -> 0 | J20: =SUMIFS('Bill Wise'!I:I,'Bill Wise'!C:C,B20,'Bill Wise'!H:H,"61-90 Days") -> 0 | K20: =SUMIFS('Bill Wise'!I:I,'Bill Wise'!C:C,B20,'Bill Wise'!H:H,"91-120 Days") -> 0 | L20: =SUMIFS('Bill Wise'!I:I,'Bill Wise'!C:C,B20,'Bill Wise'!H:H,"121-150 Days") -> 0 | M20: =SUMIFS('Bill Wise'!I:I,'Bill Wise'!C:C,B20,'Bill Wise'!H:H,"151-180 Days") -> 0 | N20: =SUMIFS('Bill Wise'!I:I,'Bill Wise'!C:C,B20,'Bill Wise'!H:H,"181-365 Days") -> 0 | O20: =SUMIFS('Bill Wise'!I:I,'Bill Wise'!C:C,B20,'Bill Wise'!H:H,"Above 365 Days") -> 0 | P20: =SUM(H20:O20) -> 5757 | Q20: =G20-P20 -> 0
A21: 16 | B21: Krishna Enterprise(Guj)-Crs | C21: Gujarat | D21: Expenses | E21: Repair & Maintenance | G21: =IFERROR(SUMIFS(TB!C:C,TB!A:A,B21)-SUMIFS(TB!B:B,TB!A:A,B21),0) -> 5782 | H21: =SUMIFS('Bill Wise'!I:I,'Bill Wise'!C:C,B21,'Bill Wise'!H:H,"0-30 Days") -> 5782 | I21: =SUMIFS('Bill Wise'!I:I,'Bill Wise'!C:C,B21,'Bill Wise'!H:H,"31-60 Days") -> 0 | J21: =SUMIFS('Bill Wise'!I:I,'Bill Wise'!C:C,B21,'Bill Wise'!H:H,"61-90 Days") -> 0 | K21: =SUMIFS('Bill Wise'!I:I,'Bill Wise'!C:C,B21,'Bill Wise'!H:H,"91-120 Days") -> 0 | L21: =SUMIFS('Bill Wise'!I:I,'Bill Wise'!C:C,B21,'Bill Wise'!H:H,"121-150 Days") -> 0 | M21: =SUMIFS('Bill Wise'!I:I,'Bill Wise'!C:C,B21,'Bill Wise'!H:H,"151-180 Days") -> 0 | N21: =SUMIFS('Bill Wise'!I:I,'Bill Wise'!C:C,B21,'Bill Wise'!H:H,"181-365 Days") -> 0 | O21: =SUMIFS('Bill Wise'!I:I,'Bill Wise'!C:C,B21,'Bill Wise'!H:H,"Above 365 Days") -> 0 | P21: =SUM(H21:O21) -> 5782 | Q21: =G21-P21 -> 0
A22: 17 | B22: Kapadia Global Actuaries-Crs | C22: Head Office | D22: Expenses | E22: Professional Fees | G22: =IFERROR(SUMIFS(TB!C:C,TB!A:A,B22)-SUMIFS(TB!B:B,TB!A:A,B22),0) -> 5900 | H22: =SUMIFS('Bill Wise'!I:I,'Bill Wise'!C:C,B22,'Bill Wise'!H:H,"0-30 Days") -> 5900 | I22: =SUMIFS('Bill Wise'!I:I,'Bill Wise'!C:C,B22,'Bill Wise'!H:H,"31-60 Days") -> 0 | J22: =SUMIFS('Bill Wise'!I:I,'Bill Wise'!C:C,B22,'Bill Wise'!H:H,"61-90 Days") -> 0 | K22: =SUMIFS('Bill Wise'!I:I,'Bill Wise'!C:C,B22,'Bill Wise'!H:H,"91-120 Days") -> 0 | L22: =SUMIFS('Bill Wise'!I:I,'Bill Wise'!C:C,B22,'Bill Wise'!H:H,"121-150 Days") -> 0 | M22: =SUMIFS('Bill Wise'!I:I,'Bill Wise'!C:C,B22,'Bill Wise'!H:H,"151-180 Days") -> 0 | N22: =SUMIFS('Bill Wise'!I:I,'Bill Wise'!C:C,B22,'Bill Wise'!H:H,"181-365 Days") -> 0 | O22: =SUMIFS('Bill Wise'!I:I,'Bill Wise'!C:C,B22,'Bill Wise'!H:H,"Above 365 Days") -> 0 | P22: =SUM(H22:O22) -> 5900 | Q22: =G22-P22 -> 0
A23: 18 | B23: Jhuman Bagdi- Crs | C23: Galsi | D23: Expenses | E23: Staff Welfare | G23: =IFERROR(SUMIFS(TB!C:C,TB!A:A,B23)-SUMIFS(TB!B:B,TB!A:A,B23),0) -> 6000 | H23: =SUMIFS('Bill Wise'!I:I,'Bill Wise'!C:C,B23,'Bill Wise'!H:H,"0-30 Days") -> 6000 | I23: =SUMIFS('Bill Wise'!I:I,'Bill Wise'!C:C,B23,'Bill Wise'!H:H,"31-60 Days") -> 0 | J23: =SUMIFS('Bill Wise'!I:I,'Bill Wise'!C:C,B23,'Bill Wise'!H:H,"61-90 Days") -> 0 | K23: =SUMIFS('Bill Wise'!I:I,'Bill Wise'!C:C,B23,'Bill Wise'!H:H,"91-120 Days") -> 0 | L23: =SUMIFS('Bill Wise'!I:I,'Bill Wise'!C:C,B23,'Bill Wise'!H:H,"121-150 Days") -> 0 | M23: =SUMIFS('Bill Wise'!I:I,'Bill Wise'!C:C,B23,'Bill Wise'!H:H,"151-180 Days") -> 0 | N23: =SUMIFS('Bill Wise'!I:I,'Bill Wise'!C:C,B23,'Bill Wise'!H:H,"181-365 Days") -> 0 | O23: =SUMIFS('Bill Wise'!I:I,'Bill Wise'!C:C,B23,'Bill Wise'!H:H,"Above 365 Days") -> 0 | P23: =SUM(H23:O23) -> 6000 | Q23: =G23-P23 -> 0
A24: 19 | B24: BHARTIBEN SATISHBHAI PATEL-CR | C24: Gujarat | D24: Expenses | E24: Guest House Rent | G24: =IFERROR(SUMIFS(TB!C:C,TB!A:A,B24)-SUMIFS(TB!B:B,TB!A:A,B24),0) -> 8000 | H24: =SUMIFS('Bill Wise'!I:I,'Bill Wise'!C:C,B24,'Bill Wise'!H:H,"0-30 Days") -> 8000 | I24: =SUMIFS('Bill Wise'!I:I,'Bill Wise'!C:C,B24,'Bill Wise'!H:H,"31-60 Days") -> 0 | J24: =SUMIFS('Bill Wise'!I:I,'Bill Wise'!C:C,B24,'Bill Wise'!H:H,"61-90 Days") -> 0 | K24: =SUMIFS('Bill Wise'!I:I,'Bill Wise'!C:C,B24,'Bill Wise'!H:H,"91-120 Days") -> 0 | L24: =SUMIFS('Bill Wise'!I:I,'Bill Wise'!C:C,B24,'Bill Wise'!H:H,"121-150 Days") -> 0 | M24: =SUMIFS('Bill Wise'!I:I,'Bill Wise'!C:C,B24,'Bill Wise'!H:H,"151-180 Days") -> 0 | N24: =SUMIFS('Bill Wise'!I:I,'Bill Wise'!C:C,B24,'Bill Wise'!H:H,"181-365 Days") -> 0 | O24: =SUMIFS('Bill Wise'!I:I,'Bill Wise'!C:C,B24,'Bill Wise'!H:H,"Above 365 Days") -> 0 | P24: =SUM(H24:O24) -> 8000 | Q24: =G24-P24 -> 0
A25: 20 | B25: Pramod Marotirao Kumbhare- Crs | C25: Nagpur | D25: Expenses | E25: Contract Labour | G25: =IFERROR(SUMIFS(TB!C:C,TB!A:A,B25)-SUMIFS(TB!B:B,TB!A:A,B25),0) -> 8232 | H25: =SUMIFS('Bill Wise'!I:I,'Bill Wise'!C:C,B25,'Bill Wise'!H:H,"0-30 Days") -> 8232 | I25: =SUMIFS('Bill Wise'!I:I,'Bill Wise'!C:C,B25,'Bill Wise'!H:H,"31-60 Days") -> 0 | J25: =SUMIFS('Bill Wise'!I:I,'Bill Wise'!C:C,B25,'Bill Wise'!H:H,"61-90 Days") -> 0 | K25: =SUMIFS('Bill Wise'!I:I,'Bill Wise'!C:C,B25,'Bill Wise'!H:H,"91-120 Days") -> 0 | L25: =SUMIFS('Bill Wise'!I:I,'Bill Wise'!C:C,B25,'Bill Wise'!H:H,"121-150 Days") -> 0 | M25: =SUMIFS('Bill Wise'!I:I,'Bill Wise'!C:C,B25,'Bill Wise'!H:H,"151-180 Days") -> 0 | N25: =SUMIFS('Bill Wise'!I:I,'Bill Wise'!C:C,B25,'Bill Wise'!H:H,"181-365 Days") -> 0 | O25: =SUMIFS('Bill Wise'!I:I,'Bill Wise'!C:C,B25,'Bill Wise'!H:H,"Above 365 Days") -> 0 | P25: =SUM(H25:O25) -> 8232 | Q25: =G25-P25 -> 0
A26: 21 | B26: Om Sai Krupa Chai - Crs | C26: wada | D26: Expenses | E26: Office Exps | G26: =IFERROR(SUMIFS(TB!C:C,TB!A:A,B26)-SUMIFS(TB!B:B,TB!A:A,B26),0) -> 9114 | H26: =SUMIFS('Bill Wise'!I:I,'Bill Wise'!C:C,B26,'Bill Wise'!H:H,"0-30 Days") -> 9114 | I26: =SUMIFS('Bill Wise'!I:I,'Bill Wise'!C:C,B26,'Bill Wise'!H:H,"31-60 Days") -> 0 | J26: =SUMIFS('Bill Wise'!I:I,'Bill Wise'!C:C,B26,'Bill Wise'!H:H,"61-90 Days") -> 0 | K26: =SUMIFS('Bill Wise'!I:I,'Bill Wise'!C:C,B26,'Bill Wise'!H:H,"91-120 Days") -> 0 | L26: =SUMIFS('Bill Wise'!I:I,'Bill Wise'!C:C,B26,'Bill Wise'!H:H,"121-150 Days") -> 0 | M26: =SUMIFS('Bill Wise'!I:I,'Bill Wise'!C:C,B26,'Bill Wise'!H:H,"151-180 Days") -> 0 | N26: =SUMIFS('Bill Wise'!I:I,'Bill Wise'!C:C,B26,'Bill Wise'!H:H,"181-365 Days") -> 0 | O26: =SUMIFS('Bill Wise'!I:I,'Bill Wise'!C:C,B26,'Bill Wise'!H:H,"Above 365 Days") -> 0 | P26: =SUM(H26:O26) -> 9114 | Q26: =G26-P26 -> 0
A27: 22 | B27: Bhandari Automobiles Pvt Ltd - Crs | C27: Aggregate | D27: Expenses | E27: Vehicle Exps | G27: =IFERROR(SUMIFS(TB!C:C,TB!A:A,B27)-SUMIFS(TB!B:B,TB!A:A,B27),0) -> 9150 | H27: =SUMIFS('Bill Wise'!I:I,'Bill Wise'!C:C,B27,'Bill Wise'!H:H,"0-30 Days") -> 9150 | I27: =SUMIFS('Bill Wise'!I:I,'Bill Wise'!C:C,B27,'Bill Wise'!H:H,"31-60 Days") -> 0 | J27: =SUMIFS('Bill Wise'!I:I,'Bill Wise'!C:C,B27,'Bill Wise'!H:H,"61-90 Days") -> 0 | K27: =SUMIFS('Bill Wise'!I:I,'Bill Wise'!C:C,B27,'Bill Wise'!H:H,"91-120 Days") -> 0 | L27: =SUMIFS('Bill Wise'!I:I,'Bill Wise'!C:C,B27,'Bill Wise'!H:H,"121-150 Days") -> 0 | M27: =SUMIFS('Bill Wise'!I:I,'Bill Wise'!C:C,B27,'Bill Wise'!H:H,"151-180 Days") -> 0 | N27: =SUMIFS('Bill Wise'!I:I,'Bill Wise'!C:C,B27,'Bill Wise'!H:H,"181-365 Days") -> 0 | O27: =SUMIFS('Bill Wise'!I:I,'Bill Wise'!C:C,B27,'Bill Wise'!H:H,"Above 365 Days") -> 0 | P27: =SUM(H27:O27) -> 9150 | Q27: =G27-P27 -> 0
... A43: 38 | B43: FIRDOSH ERUCH ICHHAPORIA-Crs | C43: Gujarat | D43: Expenses | E43: Guest House Rent | G43: =IFERROR(SUMIFS(TB!C:C,TB!A:A,B43)-SUMIFS(TB!B:B,TB!A:A,B43),0) -> 20000 | H43: =SUMIFS('Bill Wise'!I:I,'Bill Wise'!C:C,B43,'Bill Wise'!H:H,"0-30 Days") -> 20000 | I43: =SUMIFS('Bill Wise'!I:I,'Bill Wise'!C:C,B43,'Bill Wise'!H:H,"31-60 Days") -> 0 | J43: =SUMIFS('Bill Wise'!I:I,'Bill Wise'!C:C,B43,'Bill Wise'!H:H,"61-90 Days") -> 0 | K43: =SUMIFS('Bill Wise'!I:I,'Bill Wise'!C:C,B43,'Bill Wise'!H:H,"91-120 Days") -> 0 | L43: =SUMIFS('Bill Wise'!I:I,'Bill Wise'!C:C,B43,'Bill Wise'!H:H,"121-150 Days") -> 0 | M43: =SUMIFS('Bill Wise'!I:I,'Bill Wise'!C:C,B43,'Bill Wise'!H:H,"151-180 Days") -> 0 | N43: =SUMIFS('Bill Wise'!I:I,'Bill Wise'!C:C,B43,'Bill Wise'!H:H,"181-365 Days") -> 0 | O43: =SUMIFS('Bill Wise'!I:I,'Bill Wise'!C:C,B43,'Bill Wise'!H:H,"Above 365 Days") -> 0 | P43: =SUM(H43:O43) -> 20000 | Q43: =G43-P43 -> 0
A44: 39 | B44: N P Services - Crs | C44: Nagpur | D44: Expenses | E44: 0 | G44: =IFERROR(SUMIFS(TB!C:C,TB!A:A,B44)-SUMIFS(TB!B:B,TB!A:A,B44),0) -> 20535 | H44: =SUMIFS('Bill Wise'!I:I,'Bill Wise'!C:C,B44,'Bill Wise'!H:H,"0-30 Days") -> 0 | I44: =SUMIFS('Bill Wise'!I:I,'Bill Wise'!C:C,B44,'Bill Wise'!H:H,"31-60 Days") -> 20535 | J44: =SUMIFS('Bill Wise'!I:I,'Bill Wise'!C:C,B44,'Bill Wise'!H:H,"61-90 Days") -> 0 | K44: =SUMIFS('Bill Wise'!I:I,'Bill Wise'!C:C,B44,'Bill Wise'!H:H,"91-120 Days") -> 0 | L44: =SUMIFS('Bill Wise'!I:I,'Bill Wise'!C:C,B44,'Bill Wise'!H:H,"121-150 Days") -> 0 | M44: =SUMIFS('Bill Wise'!I:I,'Bill Wise'!C:C,B44,'Bill Wise'!H:H,"151-180 Days") -> 0 | N44: =SUMIFS('Bill Wise'!I:I,'Bill Wise'!C:C,B44,'Bill Wise'!H:H,"181-365 Days") -> 0 | O44: =SUMIFS('Bill Wise'!I:I,'Bill Wise'!C:C,B44,'Bill Wise'!H:H,"Above 365 Days") -> 0 | P44: =SUM(H44:O44) -> 20535 | Q44: =G44-P44 -> 0
A45: 40 | B45: Naresh Gupta - Employee | C45: Gujarat | D45: Employee | E45: Employee | G45: =IFERROR(SUMIFS(TB!C:C,TB!A:A,B45)-SUMIFS(TB!B:B,TB!A:A,B45),0) -> 21729 | H45: =SUMIFS('Bill Wise'!I:I,'Bill Wise'!C:C,B45,'Bill Wise'!H:H,"0-30 Days") -> 21729 | I45: =SUMIFS('Bill Wise'!I:I,'Bill Wise'!C:C,B45,'Bill Wise'!H:H,"31-60 Days") -> 0 | J45: =SUMIFS('Bill Wise'!I:I,'Bill Wise'!C:C,B45,'Bill Wise'!H:H,"61-90 Days") -> 0 | K45: =SUMIFS('Bill Wise'!I:I,'Bill Wise'!C:C,B45,'Bill Wise'!H:H,"91-120 Days") -> 0 | L45: =SUMIFS('Bill Wise'!I:I,'Bill Wise'!C:C,B45,'Bill Wise'!H:H,"121-150 Days") -> 0 | M45: =SUMIFS('Bill Wise'!I:I,'Bill Wise'!C:C,B45,'Bill Wise'!H:H,"151-180 Days") -> 0 | N45: =SUMIFS('Bill Wise'!I:I,'Bill Wise'!C:C,B45,'Bill Wise'!H:H,"181-365 Days") -> 0 | O45: =SUMIFS('Bill Wise'!I:I,'Bill Wise'!C:C,B45,'Bill Wise'!H:H,"Above 365 Days") -> 0 | P45: =SUM(H45:O45) -> 21729 | Q45: =G45-P45 -> 0
A46: 41 | B46: Nanak Auto Parts-Crs | C46: Gujarat | D46: Expenses | E46: Repair & Maintenance | G46: =IFERROR(SUMIFS(TB!C:C,TB!A:A,B46)-SUMIFS(TB!B:B,TB!A:A,B46),0) -> 22148 | H46: =SUMIFS('Bill Wise'!I:I,'Bill Wise'!C:C,B46,'Bill Wise'!H:H,"0-30 Days") -> 22148 | I46: =SUMIFS('Bill Wise'!I:I,'Bill Wise'!C:C,B46,'Bill Wise'!H:H,"31-60 Days") -> 0 | J46: =SUMIFS('Bill Wise'!I:I,'Bill Wise'!C:C,B46,'Bill Wise'!H:H,"61-90 Days") -> 0 | K46: =SUMIFS('Bill Wise'!I:I,'Bill Wise'!C:C,B46,'Bill Wise'!H:H,"91-120 Days") -> 0 | L46: =SUMIFS('Bill Wise'!I:I,'Bill Wise'!C:C,B46,'Bill Wise'!H:H,"121-150 Days") -> 0 | M46: =SUMIFS('Bill Wise'!I:I,'Bill Wise'!C:C,B46,'Bill Wise'!H:H,"151-180 Days") -> 0 | N46: =SUMIFS('Bill Wise'!I:I,'Bill Wise'!C:C,B46,'Bill Wise'!H:H,"181-365 Days") -> 0 | O46: =SUMIFS('Bill Wise'!I:I,'Bill Wise'!C:C,B46,'Bill Wise'!H:H,"Above 365 Days") -> 0 | P46: =SUM(H46:O46) -> 22148 | Q46: =G46-P46 -> 0
A47: 42 | B47: Rohit Prasad - Employee | C47: Gujarat | D47: Employee | E47: Claim Exps | G47: =IFERROR(SUMIFS(TB!C:C,TB!A:A,B47)-SUMIFS(TB!B:B,TB!A:A,B47),0) -> 22423 | H47: =SUMIFS('Bill Wise'!I:I,'Bill Wise'!C:C,B47,'Bill Wise'!H:H,"0-30 Days") -> 47423 | I47: =SUMIFS('Bill Wise'!I:I,'Bill Wise'!C:C,B47,'Bill Wise'!H:H,"31-60 Days") -> 0 | J47: =SUMIFS('Bill Wise'!I:I,'Bill Wise'!C:C,B47,'Bill Wise'!H:H,"61-90 Days") -> -25000 | K47: =SUMIFS('Bill Wise'!I:I,'Bill Wise'!C:C,B47,'Bill Wise'!H:H,"91-120 Days") -> 0 | L47: =SUMIFS('Bill Wise'!I:I,'Bill Wise'!C:C,B47,'Bill Wise'!H:H,"121-150 Days") -> 0 | M47: =SUMIFS('Bill Wise'!I:I,'Bill Wise'!C:C,B47,'Bill Wise'!H:H,"151-180 Days") -> 0 | N47: =SUMIFS('Bill Wise'!I:I,'Bill Wise'!C:C,B47,'Bill Wise'!H:H,"181-365 Days") -> 0 | O47: =SUMIFS('Bill Wise'!I:I,'Bill Wise'!C:C,B47,'Bill Wise'!H:H,"Above 365 Days") -> 0 | P47: =SUM(H47:O47) -> 22423 | Q47: =G47-P47 -> 0
A48: 43 | B48: SHIV OM PREFAB INFRA AND LOGISTICS-Crs | C48: Nagpur | D48: Expenses | E48: Store and spare | G48: =IFERROR(SUMIFS(TB!C:C,TB!A:A,B48)-SUMIFS(TB!B:B,TB!A:A,B48),0) -> 23174.83 | H48: =SUMIFS('Bill Wise'!I:I,'Bill Wise'!C:C,B48,'Bill Wise'!H:H,"0-30 Days") -> 23174.57 | I48: =SUMIFS('Bill Wise'!I:I,'Bill Wise'!C:C,B48,'Bill Wise'!H:H,"31-60 Days") -> 0 | J48: =SUMIFS('Bill Wise'!I:I,'Bill Wise'!C:C,B48,'Bill Wise'!H:H,"61-90 Days") -> 0.26 | K48: =SUMIFS('Bill Wise'!I:I,'Bill Wise'!C:C,B48,'Bill Wise'!H:H,"91-120 Days") -> 0 | L48: =SUMIFS('Bill Wise'!I:I,'Bill Wise'!C:C,B48,'Bill Wise'!H:H,"121-150 Days") -> 0 | M48: =SUMIFS('Bill Wise'!I:I,'Bill Wise'!C:C,B48,'Bill Wise'!H:H,"151-180 Days") -> 0 | N48: =SUMIFS('Bill Wise'!I:I,'Bill Wise'!C:C,B48,'Bill Wise'!H:H,"181-365 Days") -> 0 | O48: =SUMIFS('Bill Wise'!I:I,'Bill Wise'!C:C,B48,'Bill Wise'!H:H,"Above 365 Days") -> 0 | P48: =SUM(H48:O48) -> 23174.83 | Q48: =G48-P48 -> 0
A49: 44 | B49: AKRUTI ENTERPRISE-CRS | C49: Head Office | D49: Expenses | E49: Office Exps | G49: =IFERROR(SUMIFS(TB!C:C,TB!A:A,B49)-SUMIFS(TB!B:B,TB!A:A,B49),0) -> 24564.26 | H49: =SUMIFS('Bill Wise'!I:I,'Bill Wise'!C:C,B49,'Bill Wise'!H:H,"0-30 Days") -> 24564.06 | I49: =SUMIFS('Bill Wise'!I:I,'Bill Wise'!C:C,B49,'Bill Wise'!H:H,"31-60 Days") -> 0 | J49: =SUMIFS('Bill Wise'!I:I,'Bill Wise'!C:C,B49,'Bill Wise'!H:H,"61-90 Days") -> 0 | K49: =SUMIFS('Bill Wise'!I:I,'Bill Wise'!C:C,B49,'Bill Wise'!H:H,"91-120 Days") -> 0 | L49: =SUMIFS('Bill Wise'!I:I,'Bill Wise'!C:C,B49,'Bill Wise'!H:H,"121-150 Days") -> 0.2 | M49: =SUMIFS('Bill Wise'!I:I,'Bill Wise'!C:C,B49,'Bill Wise'!H:H,"151-180 Days") -> 0 | N49: =SUMIFS('Bill Wise'!I:I,'Bill Wise'!C:C,B49,'Bill Wise'!H:H,"181-365 Days") -> 0 | O49: =SUMIFS('Bill Wise'!I:I,'Bill Wise'!C:C,B49,'Bill Wise'!H:H,"Above 365 Days") -> 0 | P49: =SUM(H49:O49) -> 24564.26 | Q49: =G49-P49 -> 0
A50: 45 | B50: Prabhat Crane Service-CRS | C50: Gujarat | D50: Expenses | E50: Repair & Maintenance | G50: =IFERROR(SUMIFS(TB!C:C,TB!A:A,B50)-SUMIFS(TB!B:B,TB!A:A,B50),0) -> 24592 | H50: =SUMIFS('Bill Wise'!I:I,'Bill Wise'!C:C,B50,'Bill Wise'!H:H,"0-30 Days") -> 24592 | I50: =SUMIFS('Bill Wise'!I:I,'Bill Wise'!C:C,B50,'Bill Wise'!H:H,"31-60 Days") -> 0 | J50: =SUMIFS('Bill Wise'!I:I,'Bill Wise'!C:C,B50,'Bill Wise'!H:H,"61-90 Days") -> 0 | K50: =SUMIFS('Bill Wise'!I:I,'Bill Wise'!C:C,B50,'Bill Wise'!H:H,"91-120 Days") -> 0 | L50: =SUMIFS('Bill Wise'!I:I,'Bill Wise'!C:C,B50,'Bill Wise'!H:H,"121-150 Days") -> 0 | M50: =SUMIFS('Bill Wise'!I:I,'Bill Wise'!C:C,B50,'Bill Wise'!H:H,"151-180 Days") -> 0 | N50: =SUMIFS('Bill Wise'!I:I,'Bill Wise'!C:C,B50,'Bill Wise'!H:H,"181-365 Days") -> 0 | O50: =SUMIFS('Bill Wise'!I:I,'Bill Wise'!C:C,B50,'Bill Wise'!H:H,"Above 365 Days") -> 0 | P50: =SUM(H50:O50) -> 24592 | Q50: =G50-P50 -> 0
A51: 46 | B51: Rice Lake Weighing System India - Crs | C51: Galsi | D51: Expenses | E51: 0 | G51: =IFERROR(SUMIFS(TB!C:C,TB!A:A,B51)-SUMIFS(TB!B:B,TB!A:A,B51),0) -> 24759 | H51: =SUMIFS('Bill Wise'!I:I,'Bill Wise'!C:C,B51,'Bill Wise'!H:H,"0-30 Days") -> 24759 | I51: =SUMIFS('Bill Wise'!I:I,'Bill Wise'!C:C,B51,'Bill Wise'!H:H,"31-60 Days") -> 0 | J51: =SUMIFS('Bill Wise'!I:I,'Bill Wise'!C:C,B51,'Bill Wise'!H:H,"61-90 Days") -> 0 | K51: =SUMIFS('Bill Wise'!I:I,'Bill Wise'!C:C,B51,'Bill Wise'!H:H,"91-120 Days") -> 0 | L51: =SUMIFS('Bill Wise'!I:I,'Bill Wise'!C:C,B51,'Bill Wise'!H:H,"121-150 Days") -> 0 | M51: =SUMIFS('Bill Wise'!I:I,'Bill Wise'!C:C,B51,'Bill Wise'!H:H,"151-180 Days") -> 0 | N51: =SUMIFS('Bill Wise'!I:I,'Bill Wise'!C:C,B51,'Bill Wise'!H:H,"181-365 Days") -> 0 | O51: =SUMIFS('Bill Wise'!I:I,'Bill Wise'!C:C,B51,'Bill Wise'!H:H,"Above 365 Days") -> 0 | P51: =SUM(H51:O51) -> 24759 | Q51: =G51-P51 -> 0
A52: 47 | B52: NAVEEN P REDDY - Crs | C52: Nellore | D52: Expenses | E52: Rent | G52: =IFERROR(SUMIFS(TB!C:C,TB!A:A,B52)-SUMIFS(TB!B:B,TB!A:A,B52),0) -> 27225 | H52: =SUMIFS('Bill Wise'!I:I,'Bill Wise'!C:C,B52,'Bill Wise'!H:H,"0-30 Days") -> 27225 | I52: =SUMIFS('Bill Wise'!I:I,'Bill Wise'!C:C,B52,'Bill Wise'!H:H,"31-60 Days") -> 0 | J52: =SUMIFS('Bill Wise'!I:I,'Bill Wise'!C:C,B52,'Bill Wise'!H:H,"61-90 Days") -> 0 | K52: =SUMIFS('Bill Wise'!I:I,'Bill Wise'!C:C,B52,'Bill Wise'!H:H,"91-120 Days") -> 0 | L52: =SUMIFS('Bill Wise'!I:I,'Bill Wise'!C:C,B52,'Bill Wise'!H:H,"121-150 Days") -> 0 | M52: =SUMIFS('Bill Wise'!I:I,'Bill Wise'!C:C,B52,'Bill Wise'!H:H,"151-180 Days") -> 0 | N52: =SUMIFS('Bill Wise'!I:I,'Bill Wise'!C:C,B52,'Bill Wise'!H:H,"181-365 Days") -> 0 | O52: =SUMIFS('Bill Wise'!I:I,'Bill Wise'!C:C,B52,'Bill Wise'!H:H,"Above 365 Days") -> 0 | P52: =SUM(H52:O52) -> 27225 | Q52: =G52-P52 -> 0
A53: 48 | B53: Accurate Engineering Works-Crs | C53: Gujarat | D53: Expenses | E53: Store and spare | G53: =IFERROR(SUMIFS(TB!C:C,TB!A:A,B53)-SUMIFS(TB!B:B,TB!A:A,B53),0) -> 30444 | H53: =SUMIFS('Bill Wise'!I:I,'Bill Wise'!C:C,B53,'Bill Wise'!H:H,"0-30 Days") -> 30444 | I53: =SUMIFS('Bill Wise'!I:I,'Bill Wise'!C:C,B53,'Bill Wise'!H:H,"31-60 Days") -> 0 | J53: =SUMIFS('Bill Wise'!I:I,'Bill Wise'!C:C,B53,'Bill Wise'!H:H,"61-90 Days") -> 0 | K53: =SUMIFS('Bill Wise'!I:I,'Bill Wise'!C:C,B53,'Bill Wise'!H:H,"91-120 Days") -> 0 | L53: =SUMIFS('Bill Wise'!I:I,'Bill Wise'!C:C,B53,'Bill Wise'!H:H,"121-150 Days") -> 0 | M53: =SUMIFS('Bill Wise'!I:I,'Bill Wise'!C:C,B53,'Bill Wise'!H:H,"151-180 Days") -> 0 | N53: =SUMIFS('Bill Wise'!I:I,'Bill Wise'!C:C,B53,'Bill Wise'!H:H,"181-365 Days") -> 0 | O53: =SUMIFS('Bill Wise'!I:I,'Bill Wise'!C:C,B53,'Bill Wise'!H:H,"Above 365 Days") -> 0 | P53: =SUM(H53:O53) -> 30444 | Q53: =G53-P53 -> 0
A54: 49 | B54: Chukha Ferro Alloys Pvt Ltd- Crs | C54: Haryana | D54: Trading | E54: Bhutan Vendor | G54: =IFERROR(SUMIFS(TB!C:C,TB!A:A,B54)-SUMIFS(TB!B:B,TB!A:A,B54),0) -> 32191.76 | H54: =SUMIFS('Bill Wise'!I:I,'Bill Wise'!C:C,B54,'Bill Wise'!H:H,"0-30 Days") -> 32191.76 | I54: =SUMIFS('Bill Wise'!I:I,'Bill Wise'!C:C,B54,'Bill Wise'!H:H,"31-60 Days") -> 0 | J54: =SUMIFS('Bill Wise'!I:I,'Bill Wise'!C:C,B54,'Bill Wise'!H:H,"61-90 Days") -> 0 | K54: =SUMIFS('Bill Wise'!I:I,'Bill Wise'!C:C,B54,'Bill Wise'!H:H,"91-120 Days") -> 0 | L54: =SUMIFS('Bill Wise'!I:I,'Bill Wise'!C:C,B54,'Bill Wise'!H:H,"121-150 Days") -> 0 | M54: =SUMIFS('Bill Wise'!I:I,'Bill Wise'!C:C,B54,'Bill Wise'!H:H,"151-180 Days") -> 0 | N54: =SUMIFS('Bill Wise'!I:I,'Bill Wise'!C:C,B54,'Bill Wise'!H:H,"181-365 Days") -> 0 | O54: =SUMIFS('Bill Wise'!I:I,'Bill Wise'!C:C,B54,'Bill Wise'!H:H,"Above 365 Days") -> 0 | P54: =SUM(H54:O54) -> 32191.76 | Q54: =G54-P54 -> 0
A55: 50 | B55: SAI SAMARTH SECURITY SERVICES & LABOUR SUPPLIER - Crs | C55: Nagpur | D55: Expenses | E55: Security charges | G55: =IFERROR(SUMIFS(TB!C:C,TB!A:A,B55)-SUMIFS(TB!B:B,TB!A:A,B55),0) -> 33320 | H55: =SUMIFS('Bill Wise'!I:I,'Bill Wise'!C:C,B55,'Bill Wise'!H:H,"0-30 Days") -> 33320 | I55: =SUMIFS('Bill Wise'!I:I,'Bill Wise'!C:C,B55,'Bill Wise'!H:H,"31-60 Days") -> 0 | J55: =SUMIFS('Bill Wise'!I:I,'Bill Wise'!C:C,B55,'Bill Wise'!H:H,"61-90 Days") -> 0 | K55: =SUMIFS('Bill Wise'!I:I,'Bill Wise'!C:C,B55,'Bill Wise'!H:H,"91-120 Days") -> 0 | L55: =SUMIFS('Bill Wise'!I:I,'Bill Wise'!C:C,B55,'Bill Wise'!H:H,"121-150 Days") -> 0 | M55: =SUMIFS('Bill Wise'!I:I,'Bill Wise'!C:C,B55,'Bill Wise'!H:H,"151-180 Days") -> 0 | N55: =SUMIFS('Bill Wise'!I:I,'Bill Wise'!C:C,B55,'Bill Wise'!H:H,"181-365 Days") -> 0 | O55: =SUMIFS('Bill Wise'!I:I,'Bill Wise'!C:C,B55,'Bill Wise'!H:H,"Above 365 Days") -> 0 | P55: =SUM(H55:O55) -> 33320 | Q55: =G55-P55 -> 0
A56: 51 | B56: Pramod Shinde - EMPLOYEE | C56: Head Office | D56: Employee | E56: Claim Exps | G56: =IFERROR(SUMIFS(TB!C:C,TB!A:A,B56)-SUMIFS(TB!B:B,TB!A:A,B56),0) -> 33829 | H56: =SUMIFS('Bill Wise'!I:I,'Bill Wise'!C:C,B56,'Bill Wise'!H:H,"0-30 Days") -> 33829 | I56: =SUMIFS('Bill Wise'!I:I,'Bill Wise'!C:C,B56,'Bill Wise'!H:H,"31-60 Days") -> 0 | J56: =SUMIFS('Bill Wise'!I:I,'Bill Wise'!C:C,B56,'Bill Wise'!H:H,"61-90 Days") -> 0 | K56: =SUMIFS('Bill Wise'!I:I,'Bill Wise'!C:C,B56,'Bill Wise'!H:H,"91-120 Days") -> 0 | L56: =SUMIFS('Bill Wise'!I:I,'Bill Wise'!C:C,B56,'Bill Wise'!H:H,"121-150 Days") -> 0 | M56: =SUMIFS('Bill Wise'!I:I,'Bill Wise'!C:C,B56,'Bill Wise'!H:H,"151-180 Days") -> 0 | N56: =SUMIFS('Bill Wise'!I:I,'Bill Wise'!C:C,B56,'Bill Wise'!H:H,"181-365 Days") -> 0 | O56: =SUMIFS('Bill Wise'!I:I,'Bill Wise'!C:C,B56,'Bill Wise'!H:H,"Above 365 Days") -> 0 | P56: =SUM(H56:O56) -> 33829 | Q56: =G56-P56 -> 0
A57: 52 | B57: KAMAL S PATIL - Crs | C57: wada | D57: Expenses | E57: Rent | G57: =IFERROR(SUMIFS(TB!C:C,TB!A:A,B57)-SUMIFS(TB!B:B,TB!A:A,B57),0) -> 34630.2 | H57: =SUMIFS('Bill Wise'!I:I,'Bill Wise'!C:C,B57,'Bill Wise'!H:H,"0-30 Days") -> 34630.2 | I57: =SUMIFS('Bill Wise'!I:I,'Bill Wise'!C:C,B57,'Bill Wise'!H:H,"31-60 Days") -> 0 | J57: =SUMIFS('Bill Wise'!I:I,'Bill Wise'!C:C,B57,'Bill Wise'!H:H,"61-90 Days") -> 0 | K57: =SUMIFS('Bill Wise'!I:I,'Bill Wise'!C:C,B57,'Bill Wise'!H:H,"91-120 Days") -> 0 | L57: =SUMIFS('Bill Wise'!I:I,'Bill Wise'!C:C,B57,'Bill Wise'!H:H,"121-150 Days") -> 0 | M57: =SUMIFS('Bill Wise'!I:I,'Bill Wise'!C:C,B57,'Bill Wise'!H:H,"151-180 Days") -> 0 | N57: =SUMIFS('Bill Wise'!I:I,'Bill Wise'!C:C,B57,'Bill Wise'!H:H,"181-365 Days") -> 0 | O57: =SUMIFS('Bill Wise'!I:I,'Bill Wise'!C:C,B57,'Bill Wise'!H:H,"Above 365 Days") -> 0 | P57: =SUM(H57:O57) -> 34630.2 | Q57: =G57-P57 -> 0
A58: 53 | B58: SHREE SIDDHIVINAYAK COOL CARS - CRS | C58: Head Office | D58: Expenses | E58: Staff Welfare | G58: =IFERROR(SUMIFS(TB!C:C,TB!A:A,B58)-SUMIFS(TB!B:B,TB!A:A,B58),0) -> 35340.76 | H58: =SUMIFS('Bill Wise'!I:I,'Bill Wise'!C:C,B58,'Bill Wise'!H:H,"0-30 Days") -> 35340.76 | I58: =SUMIFS('Bill Wise'!I:I,'Bill Wise'!C:C,B58,'Bill Wise'!H:H,"31-60 Days") -> 0 | J58: =SUMIFS('Bill Wise'!I:I,'Bill Wise'!C:C,B58,'Bill Wise'!H:H,"61-90 Days") -> 0 | K58: =SUMIFS('Bill Wise'!I:I,'Bill Wise'!C:C,B58,'Bill Wise'!H:H,"91-120 Days") -> 0 | L58: =SUMIFS('Bill Wise'!I:I,'Bill Wise'!C:C,B58,'Bill Wise'!H:H,"121-150 Days") -> 0 | M58: =SUMIFS('Bill Wise'!I:I,'Bill Wise'!C:C,B58,'Bill Wise'!H:H,"151-180 Days") -> 0 | N58: =SUMIFS('Bill Wise'!I:I,'Bill Wise'!C:C,B58,'Bill Wise'!H:H,"181-365 Days") -> 0 | O58: =SUMIFS('Bill Wise'!I:I,'Bill Wise'!C:C,B58,'Bill Wise'!H:H,"Above 365 Days") -> 0 | P58: =SUM(H58:O58) -> 35340.76 | Q58: =G58-P58 -> 0
A59: 54 | B59: AIRMAX AUTOMATION - CRS | C59: Wada | D59: Expenses | E59: Store and spare | G59: =IFERROR(SUMIFS(TB!C:C,TB!A:A,B59)-SUMIFS(TB!B:B,TB!A:A,B59),0) -> 35913.4 | H59: =SUMIFS('Bill Wise'!I:I,'Bill Wise'!C:C,B59,'Bill Wise'!H:H,"0-30 Days") -> 35913.4 | I59: =SUMIFS('Bill Wise'!I:I,'Bill Wise'!C:C,B59,'Bill Wise'!H:H,"31-60 Days") -> 0 | J59: =SUMIFS('Bill Wise'!I:I,'Bill Wise'!C:C,B59,'Bill Wise'!H:H,"61-90 Days") -> 0 | K59: =SUMIFS('Bill Wise'!I:I,'Bill Wise'!C:C,B59,'Bill Wise'!H:H,"91-120 Days") -> 0 | L59: =SUMIFS('Bill Wise'!I:I,'Bill Wise'!C:C,B59,'Bill Wise'!H:H,"121-150 Days") -> 0 | M59: =SUMIFS('Bill Wise'!I:I,'Bill Wise'!C:C,B59,'Bill Wise'!H:H,"151-180 Days") -> 0 | N59: =SUMIFS('Bill Wise'!I:I,'Bill Wise'!C:C,B59,'Bill Wise'!H:H,"181-365 Days") -> 0 | O59: =SUMIFS('Bill Wise'!I:I,'Bill Wise'!C:C,B59,'Bill Wise'!H:H,"Above 365 Days") -> 0 | P59: =SUM(H59:O59) -> 35913.4 | Q59: =G59-P59 -> 0
A60: 55 | B60: BISWAJIT RUI DAS - Crs | C60: Microsilica | D60: Expenses | E60: Transport | G60: =IFERROR(SUMIFS(TB!C:C,TB!A:A,B60)-SUMIFS(TB!B:B,TB!A:A,B60),0) -> 36262.88 | H60: =SUMIFS('Bill Wise'!I:I,'Bill Wise'!C:C,B60,'Bill Wise'!H:H,"0-30 Days") -> 36262.88 | I60: =SUMIFS('Bill Wise'!I:I,'Bill Wise'!C:C,B60,'Bill Wise'!H:H,"31-60 Days") -> 0 | J60: =SUMIFS('Bill Wise'!I:I,'Bill Wise'!C:C,B60,'Bill Wise'!H:H,"61-90 Days") -> 0 | K60: =SUMIFS('Bill Wise'!I:I,'Bill Wise'!C:C,B60,'Bill Wise'!H:H,"91-120 Days") -> 0 | L60: =SUMIFS('Bill Wise'!I:I,'Bill Wise'!C:C,B60,'Bill Wise'!H:H,"121-150 Days") -> 0 | M60: =SUMIFS('Bill Wise'!I:I,'Bill Wise'!C:C,B60,'Bill Wise'!H:H,"151-180 Days") -> 0 | N60: =SUMIFS('Bill Wise'!I:I,'Bill Wise'!C:C,B60,'Bill Wise'!H:H,"181-365 Days") -> 0 | O60: =SUMIFS('Bill Wise'!I:I,'Bill Wise'!C:C,B60,'Bill Wise'!H:H,"Above 365 Days") -> 0 | P60: =SUM(H60:O60) -> 36262.88 | Q60: =G60-P60 -> 0
A61: 56 | B61: Krishnendu Konar CRS | C61: Galsi | D61: Capex | E61: Rent | G61: =IFERROR(SUMIFS(TB!C:C,TB!A:A,B61)-SUMIFS(TB!B:B,TB!A:A,B61),0) -> 37000 | H61: =SUMIFS('Bill Wise'!I:I,'Bill Wise'!C:C,B61,'Bill Wise'!H:H,"0-30 Days") -> 37000 | I61: =SUMIFS('Bill Wise'!I:I,'Bill Wise'!C:C,B61,'Bill Wise'!H:H,"31-60 Days") -> 0 | J61: =SUMIFS('Bill Wise'!I:I,'Bill Wise'!C:C,B61,'Bill Wise'!H:H,"61-90 Days") -> 0 | K61: =SUMIFS('Bill Wise'!I:I,'Bill Wise'!C:C,B61,'Bill Wise'!H:H,"91-120 Days") -> 0 | L61: =SUMIFS('Bill Wise'!I:I,'Bill Wise'!C:C,B61,'Bill Wise'!H:H,"121-150 Days") -> 0 | M61: =SUMIFS('Bill Wise'!I:I,'Bill Wise'!C:C,B61,'Bill Wise'!H:H,"151-180 Days") -> 0 | N61: =SUMIFS('Bill Wise'!I:I,'Bill Wise'!C:C,B61,'Bill Wise'!H:H,"181-365 Days") -> 0 | O61: =SUMIFS('Bill Wise'!I:I,'Bill Wise'!C:C,B61,'Bill Wise'!H:H,"Above 365 Days") -> 0 | P61: =SUM(H61:O61) -> 37000 | Q61: =G61-P61 -> 0
A62: 57 | B62: Subhendu Konar - Crs | C62: Galsi | D62: Capex | E62: Rent | G62: =IFERROR(SUMIFS(TB!C:C,TB!A:A,B62)-SUMIFS(TB!B:B,TB!A:A,B62),0) -> 37000 | H62: =SUMIFS('Bill Wise'!I:I,'Bill Wise'!C:C,B62,'Bill Wise'!H:H,"0-30 Days") -> 37000 | I62: =SUMIFS('Bill Wise'!I:I,'Bill Wise'!C:C,B62,'Bill Wise'!H:H,"31-60 Days") -> 0 | J62: =SUMIFS('Bill Wise'!I:I,'Bill Wise'!C:C,B62,'Bill Wise'!H:H,"61-90 Days") -> 0 | K62: =SUMIFS('Bill Wise'!I:I,'Bill Wise'!C:C,B62,'Bill Wise'!H:H,"91-120 Days") -> 0 | L62: =SUMIFS('Bill Wise'!I:I,'Bill Wise'!C:C,B62,'Bill Wise'!H:H,"121-150 Days") -> 0 | M62: =SUMIFS('Bill Wise'!I:I,'Bill Wise'!C:C,B62,'Bill Wise'!H:H,"151-180 Days") -> 0 | N62: =SUMIFS('Bill Wise'!I:I,'Bill Wise'!C:C,B62,'Bill Wise'!H:H,"181-365 Days") -> 0 | O62: =SUMIFS('Bill Wise'!I:I,'Bill Wise'!C:C,B62,'Bill Wise'!H:H,"Above 365 Days") -> 0 | P62: =SUM(H62:O62) -> 37000 | Q62: =G62-P62 -> 0
A63: 58 | B63: AVENGERS SECURITY SERVICES-CR | C63: Nellore | D63: Expenses | E63: Security | G63: =IFERROR(SUMIFS(TB!C:C,TB!A:A,B63)-SUMIFS(TB!B:B,TB!A:A,B63),0) -> 42305.6 | H63: =SUMIFS('Bill Wise'!I:I,'Bill Wise'!C:C,B63,'Bill Wise'!H:H,"0-30 Days") -> 42305.6 | I63: =SUMIFS('Bill Wise'!I:I,'Bill Wise'!C:C,B63,'Bill Wise'!H:H,"31-60 Days") -> 0 | J63: =SUMIFS('Bill Wise'!I:I,'Bill Wise'!C:C,B63,'Bill Wise'!H:H,"61-90 Days") -> 0 | K63: =SUMIFS('Bill Wise'!I:I,'Bill Wise'!C:C,B63,'Bill Wise'!H:H,"91-120 Days") -> 0 | L63: =SUMIFS('Bill Wise'!I:I,'Bill Wise'!C:C,B63,'Bill Wise'!H:H,"121-150 Days") -> 0 | M63: =SUMIFS('Bill Wise'!I:I,'Bill Wise'!C:C,B63,'Bill Wise'!H:H,"151-180 Days") -> 0 | N63: =SUMIFS('Bill Wise'!I:I,'Bill Wise'!C:C,B63,'Bill Wise'!H:H,"181-365 Days") -> 0 | O63: =SUMIFS('Bill Wise'!I:I,'Bill Wise'!C:C,B63,'Bill Wise'!H:H,"Above 365 Days") -> 0 | P63: =SUM(H63:O63) -> 42305.6 | Q63: =G63-P63 -> 0
... A86: 81 | B86: Yantraman Automac Pvt Ltd-Crs | C86: Gujarat | D86: Expenses | E86: Repair & Maintenance | G86: =IFERROR(SUMIFS(TB!C:C,TB!A:A,B86)-SUMIFS(TB!B:B,TB!A:A,B86),0) -> 159686 | H86: =SUMIFS('Bill Wise'!I:I,'Bill Wise'!C:C,B86,'Bill Wise'!H:H,"0-30 Days") -> 159686 | I86: =SUMIFS('Bill Wise'!I:I,'Bill Wise'!C:C,B86,'Bill Wise'!H:H,"31-60 Days") -> 0 | J86: =SUMIFS('Bill Wise'!I:I,'Bill Wise'!C:C,B86,'Bill Wise'!H:H,"61-90 Days") -> 0 | K86: =SUMIFS('Bill Wise'!I:I,'Bill Wise'!C:C,B86,'Bill Wise'!H:H,"91-120 Days") -> 0 | L86: =SUMIFS('Bill Wise'!I:I,'Bill Wise'!C:C,B86,'Bill Wise'!H:H,"121-150 Days") -> 0 | M86: =SUMIFS('Bill Wise'!I:I,'Bill Wise'!C:C,B86,'Bill Wise'!H:H,"151-180 Days") -> 0 | N86: =SUMIFS('Bill Wise'!I:I,'Bill Wise'!C:C,B86,'Bill Wise'!H:H,"181-365 Days") -> 0 | O86: =SUMIFS('Bill Wise'!I:I,'Bill Wise'!C:C,B86,'Bill Wise'!H:H,"Above 365 Days") -> 0 | P86: =SUM(H86:O86) -> 159686 | Q86: =G86-P86 -> 0
A87: 82 | B87: Nachiyar Transport - Crs | C87: flyash | D87: Trading | E87: 0 | G87: =IFERROR(SUMIFS(TB!C:C,TB!A:A,B87)-SUMIFS(TB!B:B,TB!A:A,B87),0) -> 163689.76 | H87: =SUMIFS('Bill Wise'!I:I,'Bill Wise'!C:C,B87,'Bill Wise'!H:H,"0-30 Days") -> 163689.76 | I87: =SUMIFS('Bill Wise'!I:I,'Bill Wise'!C:C,B87,'Bill Wise'!H:H,"31-60 Days") -> 0 | J87: =SUMIFS('Bill Wise'!I:I,'Bill Wise'!C:C,B87,'Bill Wise'!H:H,"61-90 Days") -> 0 | K87: =SUMIFS('Bill Wise'!I:I,'Bill Wise'!C:C,B87,'Bill Wise'!H:H,"91-120 Days") -> 0 | L87: =SUMIFS('Bill Wise'!I:I,'Bill Wise'!C:C,B87,'Bill Wise'!H:H,"121-150 Days") -> 0 | M87: =SUMIFS('Bill Wise'!I:I,'Bill Wise'!C:C,B87,'Bill Wise'!H:H,"151-180 Days") -> 0 | N87: =SUMIFS('Bill Wise'!I:I,'Bill Wise'!C:C,B87,'Bill Wise'!H:H,"181-365 Days") -> 0 | O87: =SUMIFS('Bill Wise'!I:I,'Bill Wise'!C:C,B87,'Bill Wise'!H:H,"Above 365 Days") -> 0 | P87: =SUM(H87:O87) -> 163689.76 | Q87: =G87-P87 -> 0
A88: 83 | B88: Mehar Engineering Works | C88: Nagpur | D88: Expenses | E88: Store and spare | G88: =IFERROR(SUMIFS(TB!C:C,TB!A:A,B88)-SUMIFS(TB!B:B,TB!A:A,B88),0) -> 168150 | H88: =SUMIFS('Bill Wise'!I:I,'Bill Wise'!C:C,B88,'Bill Wise'!H:H,"0-30 Days") -> 102070 | I88: =SUMIFS('Bill Wise'!I:I,'Bill Wise'!C:C,B88,'Bill Wise'!H:H,"31-60 Days") -> 66080 | J88: =SUMIFS('Bill Wise'!I:I,'Bill Wise'!C:C,B88,'Bill Wise'!H:H,"61-90 Days") -> 0 | K88: =SUMIFS('Bill Wise'!I:I,'Bill Wise'!C:C,B88,'Bill Wise'!H:H,"91-120 Days") -> 0 | L88: =SUMIFS('Bill Wise'!I:I,'Bill Wise'!C:C,B88,'Bill Wise'!H:H,"121-150 Days") -> 0 | M88: =SUMIFS('Bill Wise'!I:I,'Bill Wise'!C:C,B88,'Bill Wise'!H:H,"151-180 Days") -> 0 | N88: =SUMIFS('Bill Wise'!I:I,'Bill Wise'!C:C,B88,'Bill Wise'!H:H,"181-365 Days") -> 0 | O88: =SUMIFS('Bill Wise'!I:I,'Bill Wise'!C:C,B88,'Bill Wise'!H:H,"Above 365 Days") -> 0 | P88: =SUM(H88:O88) -> 168150 | Q88: =G88-P88 -> 0
A89: 84 | B89: M/s Manuwar Shaikh - Crs | C89: Galsi | D89: Expenses | E89: 0 | G89: =IFERROR(SUMIFS(TB!C:C,TB!A:A,B89)-SUMIFS(TB!B:B,TB!A:A,B89),0) -> 170704.8 | H89: =SUMIFS('Bill Wise'!I:I,'Bill Wise'!C:C,B89,'Bill Wise'!H:H,"0-30 Days") -> 170704.8 | I89: =SUMIFS('Bill Wise'!I:I,'Bill Wise'!C:C,B89,'Bill Wise'!H:H,"31-60 Days") -> 0 | J89: =SUMIFS('Bill Wise'!I:I,'Bill Wise'!C:C,B89,'Bill Wise'!H:H,"61-90 Days") -> 0 | K89: =SUMIFS('Bill Wise'!I:I,'Bill Wise'!C:C,B89,'Bill Wise'!H:H,"91-120 Days") -> 0 | L89: =SUMIFS('Bill Wise'!I:I,'Bill Wise'!C:C,B89,'Bill Wise'!H:H,"121-150 Days") -> 0 | M89: =SUMIFS('Bill Wise'!I:I,'Bill Wise'!C:C,B89,'Bill Wise'!H:H,"151-180 Days") -> 0 | N89: =SUMIFS('Bill Wise'!I:I,'Bill Wise'!C:C,B89,'Bill Wise'!H:H,"181-365 Days") -> 0 | O89: =SUMIFS('Bill Wise'!I:I,'Bill Wise'!C:C,B89,'Bill Wise'!H:H,"Above 365 Days") -> 0 | P89: =SUM(H89:O89) -> 170704.8 | Q89: =G89-P89 -> 0
A90: 85 | B90: Harrier Security Services Private Limited-Crs | C90: Gujarat | D90: Expenses | E90: Security charges | G90: =IFERROR(SUMIFS(TB!C:C,TB!A:A,B90)-SUMIFS(TB!B:B,TB!A:A,B90),0) -> 172861.25 | H90: =SUMIFS('Bill Wise'!I:I,'Bill Wise'!C:C,B90,'Bill Wise'!H:H,"0-30 Days") -> 172861.25 | I90: =SUMIFS('Bill Wise'!I:I,'Bill Wise'!C:C,B90,'Bill Wise'!H:H,"31-60 Days") -> 0 | J90: =SUMIFS('Bill Wise'!I:I,'Bill Wise'!C:C,B90,'Bill Wise'!H:H,"61-90 Days") -> 0 | K90: =SUMIFS('Bill Wise'!I:I,'Bill Wise'!C:C,B90,'Bill Wise'!H:H,"91-120 Days") -> 0 | L90: =SUMIFS('Bill Wise'!I:I,'Bill Wise'!C:C,B90,'Bill Wise'!H:H,"121-150 Days") -> 0 | M90: =SUMIFS('Bill Wise'!I:I,'Bill Wise'!C:C,B90,'Bill Wise'!H:H,"151-180 Days") -> 0 | N90: =SUMIFS('Bill Wise'!I:I,'Bill Wise'!C:C,B90,'Bill Wise'!H:H,"181-365 Days") -> 0 | O90: =SUMIFS('Bill Wise'!I:I,'Bill Wise'!C:C,B90,'Bill Wise'!H:H,"Above 365 Days") -> 0 | P90: =SUM(H90:O90) -> 172861.25 | Q90: =G90-P90 -> 0
A91: 86 | B91: SK CONSTRUCTION - CRS | C91: Nagpur | D91: Capex | E91: Capex | G91: =IFERROR(SUMIFS(TB!C:C,TB!A:A,B91)-SUMIFS(TB!B:B,TB!A:A,B91),0) -> 177912.68 | H91: =SUMIFS('Bill Wise'!I:I,'Bill Wise'!C:C,B91,'Bill Wise'!H:H,"0-30 Days") -> 177912.68 | I91: =SUMIFS('Bill Wise'!I:I,'Bill Wise'!C:C,B91,'Bill Wise'!H:H,"31-60 Days") -> 0 | J91: =SUMIFS('Bill Wise'!I:I,'Bill Wise'!C:C,B91,'Bill Wise'!H:H,"61-90 Days") -> 0 | K91: =SUMIFS('Bill Wise'!I:I,'Bill Wise'!C:C,B91,'Bill Wise'!H:H,"91-120 Days") -> 0 | L91: =SUMIFS('Bill Wise'!I:I,'Bill Wise'!C:C,B91,'Bill Wise'!H:H,"121-150 Days") -> 0 | M91: =SUMIFS('Bill Wise'!I:I,'Bill Wise'!C:C,B91,'Bill Wise'!H:H,"151-180 Days") -> 0 | N91: =SUMIFS('Bill Wise'!I:I,'Bill Wise'!C:C,B91,'Bill Wise'!H:H,"181-365 Days") -> 0 | O91: =SUMIFS('Bill Wise'!I:I,'Bill Wise'!C:C,B91,'Bill Wise'!H:H,"Above 365 Days") -> 0 | P91: =SUM(H91:O91) -> 177912.68 | Q91: =G91-P91 -> 0
A92: 87 | B92: THORON TURNKEY SOLUTIONS PRIVATE LIMITED-CRS | C92: Gujarat | D92: Capex | E92: Capex | G92: =IFERROR(SUMIFS(TB!C:C,TB!A:A,B92)-SUMIFS(TB!B:B,TB!A:A,B92),0) -> 184839.75 | H92: =SUMIFS('Bill Wise'!I:I,'Bill Wise'!C:C,B92,'Bill Wise'!H:H,"0-30 Days") -> 184839.75 | I92: =SUMIFS('Bill Wise'!I:I,'Bill Wise'!C:C,B92,'Bill Wise'!H:H,"31-60 Days") -> 0 | J92: =SUMIFS('Bill Wise'!I:I,'Bill Wise'!C:C,B92,'Bill Wise'!H:H,"61-90 Days") -> 0 | K92: =SUMIFS('Bill Wise'!I:I,'Bill Wise'!C:C,B92,'Bill Wise'!H:H,"91-120 Days") -> 0 | L92: =SUMIFS('Bill Wise'!I:I,'Bill Wise'!C:C,B92,'Bill Wise'!H:H,"121-150 Days") -> 0 | M92: =SUMIFS('Bill Wise'!I:I,'Bill Wise'!C:C,B92,'Bill Wise'!H:H,"151-180 Days") -> 0 | N92: =SUMIFS('Bill Wise'!I:I,'Bill Wise'!C:C,B92,'Bill Wise'!H:H,"181-365 Days") -> 0 | O92: =SUMIFS('Bill Wise'!I:I,'Bill Wise'!C:C,B92,'Bill Wise'!H:H,"Above 365 Days") -> 0 | P92: =SUM(H92:O92) -> 184839.75 | Q92: =G92-P92 -> 0
A93: 88 | B93: Atharva Enterprises - Crs | C93: Haryana | D93: Expenses | E93: Sales promotion | G93: =IFERROR(SUMIFS(TB!C:C,TB!A:A,B93)-SUMIFS(TB!B:B,TB!A:A,B93),0) -> 200175.08 | H93: =SUMIFS('Bill Wise'!I:I,'Bill Wise'!C:C,B93,'Bill Wise'!H:H,"0-30 Days") -> 200175.08 | I93: =SUMIFS('Bill Wise'!I:I,'Bill Wise'!C:C,B93,'Bill Wise'!H:H,"31-60 Days") -> 0 | J93: =SUMIFS('Bill Wise'!I:I,'Bill Wise'!C:C,B93,'Bill Wise'!H:H,"61-90 Days") -> 0 | K93: =SUMIFS('Bill Wise'!I:I,'Bill Wise'!C:C,B93,'Bill Wise'!H:H,"91-120 Days") -> 0 | L93: =SUMIFS('Bill Wise'!I:I,'Bill Wise'!C:C,B93,'Bill Wise'!H:H,"121-150 Days") -> 0 | M93: =SUMIFS('Bill Wise'!I:I,'Bill Wise'!C:C,B93,'Bill Wise'!H:H,"151-180 Days") -> 0 | N93: =SUMIFS('Bill Wise'!I:I,'Bill Wise'!C:C,B93,'Bill Wise'!H:H,"181-365 Days") -> 0 | O93: =SUMIFS('Bill Wise'!I:I,'Bill Wise'!C:C,B93,'Bill Wise'!H:H,"Above 365 Days") -> 0 | P93: =SUM(H93:O93) -> 200175.08 | Q93: =G93-P93 -> 0
A94: 89 | B94: Sunshine Associates-Crs | C94: Howrah | D94: Capex | E94: Capex | G94: =IFERROR(SUMIFS(TB!C:C,TB!A:A,B94)-SUMIFS(TB!B:B,TB!A:A,B94),0) -> 202456 | H94: =SUMIFS('Bill Wise'!I:I,'Bill Wise'!C:C,B94,'Bill Wise'!H:H,"0-30 Days") -> 0 | I94: =SUMIFS('Bill Wise'!I:I,'Bill Wise'!C:C,B94,'Bill Wise'!H:H,"31-60 Days") -> 0 | J94: =SUMIFS('Bill Wise'!I:I,'Bill Wise'!C:C,B94,'Bill Wise'!H:H,"61-90 Days") -> 0 | K94: =SUMIFS('Bill Wise'!I:I,'Bill Wise'!C:C,B94,'Bill Wise'!H:H,"91-120 Days") -> 0 | L94: =SUMIFS('Bill Wise'!I:I,'Bill Wise'!C:C,B94,'Bill Wise'!H:H,"121-150 Days") -> 202456 | M94: =SUMIFS('Bill Wise'!I:I,'Bill Wise'!C:C,B94,'Bill Wise'!H:H,"151-180 Days") -> 0 | N94: =SUMIFS('Bill Wise'!I:I,'Bill Wise'!C:C,B94,'Bill Wise'!H:H,"181-365 Days") -> 0 | O94: =SUMIFS('Bill Wise'!I:I,'Bill Wise'!C:C,B94,'Bill Wise'!H:H,"Above 365 Days") -> 0 | P94: =SUM(H94:O94) -> 202456 | Q94: =G94-P94 -> 0
A95: 90 | B95: Lubricating Centre Pvt Ltd | C95: Aggregate | D95: Expenses | E95: Repair & Maintenance | G95: =IFERROR(SUMIFS(TB!C:C,TB!A:A,B95)-SUMIFS(TB!B:B,TB!A:A,B95),0) -> 208400 | H95: =SUMIFS('Bill Wise'!I:I,'Bill Wise'!C:C,B95,'Bill Wise'!H:H,"0-30 Days") -> 0 | I95: =SUMIFS('Bill Wise'!I:I,'Bill Wise'!C:C,B95,'Bill Wise'!H:H,"31-60 Days") -> 208400 | J95: =SUMIFS('Bill Wise'!I:I,'Bill Wise'!C:C,B95,'Bill Wise'!H:H,"61-90 Days") -> 0 | K95: =SUMIFS('Bill Wise'!I:I,'Bill Wise'!C:C,B95,'Bill Wise'!H:H,"91-120 Days") -> 0 | L95: =SUMIFS('Bill Wise'!I:I,'Bill Wise'!C:C,B95,'Bill Wise'!H:H,"121-150 Days") -> 0 | M95: =SUMIFS('Bill Wise'!I:I,'Bill Wise'!C:C,B95,'Bill Wise'!H:H,"151-180 Days") -> 0 | N95: =SUMIFS('Bill Wise'!I:I,'Bill Wise'!C:C,B95,'Bill Wise'!H:H,"181-365 Days") -> 0 | O95: =SUMIFS('Bill Wise'!I:I,'Bill Wise'!C:C,B95,'Bill Wise'!H:H,"Above 365 Days") -> 0 | P95: =SUM(H95:O95) -> 208400 | Q95: =G95-P95 -> 0
A96: 91 | B96: TPI Industries | C96: Microsilica | D96: Expenses | E96: Store and spare | G96: =IFERROR(SUMIFS(TB!C:C,TB!A:A,B96)-SUMIFS(TB!B:B,TB!A:A,B96),0) -> 212695 | H96: =SUMIFS('Bill Wise'!I:I,'Bill Wise'!C:C,B96,'Bill Wise'!H:H,"0-30 Days") -> 57820 | I96: =SUMIFS('Bill Wise'!I:I,'Bill Wise'!C:C,B96,'Bill Wise'!H:H,"31-60 Days") -> 0 | J96: =SUMIFS('Bill Wise'!I:I,'Bill Wise'!C:C,B96,'Bill Wise'!H:H,"61-90 Days") -> 0 | K96: =SUMIFS('Bill Wise'!I:I,'Bill Wise'!C:C,B96,'Bill Wise'!H:H,"91-120 Days") -> 0 | L96: =SUMIFS('Bill Wise'!I:I,'Bill Wise'!C:C,B96,'Bill Wise'!H:H,"121-150 Days") -> 154875 | M96: =SUMIFS('Bill Wise'!I:I,'Bill Wise'!C:C,B96,'Bill Wise'!H:H,"151-180 Days") -> 0 | N96: =SUMIFS('Bill Wise'!I:I,'Bill Wise'!C:C,B96,'Bill Wise'!H:H,"181-365 Days") -> 0 | O96: =SUMIFS('Bill Wise'!I:I,'Bill Wise'!C:C,B96,'Bill Wise'!H:H,"Above 365 Days") -> 0 | P96: =SUM(H96:O96) -> 212695 | Q96: =G96-P96 -> 0
A97: 92 | B97: RMB KNOVATECH PVT LTD. - Crs | C97: WADA | D97: Capex | E97: Capex | G97: =IFERROR(SUMIFS(TB!C:C,TB!A:A,B97)-SUMIFS(TB!B:B,TB!A:A,B97),0) -> 227360 | H97: =SUMIFS('Bill Wise'!I:I,'Bill Wise'!C:C,B97,'Bill Wise'!H:H,"0-30 Days") -> 227360 | I97: =SUMIFS('Bill Wise'!I:I,'Bill Wise'!C:C,B97,'Bill Wise'!H:H,"31-60 Days") -> 0 | J97: =SUMIFS('Bill Wise'!I:I,'Bill Wise'!C:C,B97,'Bill Wise'!H:H,"61-90 Days") -> 0 | K97: =SUMIFS('Bill Wise'!I:I,'Bill Wise'!C:C,B97,'Bill Wise'!H:H,"91-120 Days") -> 0 | L97: =SUMIFS('Bill Wise'!I:I,'Bill Wise'!C:C,B97,'Bill Wise'!H:H,"121-150 Days") -> 0 | M97: =SUMIFS('Bill Wise'!I:I,'Bill Wise'!C:C,B97,'Bill Wise'!H:H,"151-180 Days") -> 0 | N97: =SUMIFS('Bill Wise'!I:I,'Bill Wise'!C:C,B97,'Bill Wise'!H:H,"181-365 Days") -> 0 | O97: =SUMIFS('Bill Wise'!I:I,'Bill Wise'!C:C,B97,'Bill Wise'!H:H,"Above 365 Days") -> 0 | P97: =SUM(H97:O97) -> 227360 | Q97: =G97-P97 -> 0
A98: 93 | B98: BHASKAR ENTERPRISE - Crs | C98: Microsilica | D98: Raw Material | E98: Aggregate | G98: =IFERROR(SUMIFS(TB!C:C,TB!A:A,B98)-SUMIFS(TB!B:B,TB!A:A,B98),0) -> 239300 | H98: =SUMIFS('Bill Wise'!I:I,'Bill Wise'!C:C,B98,'Bill Wise'!H:H,"0-30 Days") -> 0 | I98: =SUMIFS('Bill Wise'!I:I,'Bill Wise'!C:C,B98,'Bill Wise'!H:H,"31-60 Days") -> 0 | J98: =SUMIFS('Bill Wise'!I:I,'Bill Wise'!C:C,B98,'Bill Wise'!H:H,"61-90 Days") -> 0 | K98: =SUMIFS('Bill Wise'!I:I,'Bill Wise'!C:C,B98,'Bill Wise'!H:H,"91-120 Days") -> 0 | L98: =SUMIFS('Bill Wise'!I:I,'Bill Wise'!C:C,B98,'Bill Wise'!H:H,"121-150 Days") -> 239300 | M98: =SUMIFS('Bill Wise'!I:I,'Bill Wise'!C:C,B98,'Bill Wise'!H:H,"151-180 Days") -> 0 | N98: =SUMIFS('Bill Wise'!I:I,'Bill Wise'!C:C,B98,'Bill Wise'!H:H,"181-365 Days") -> 0 | O98: =SUMIFS('Bill Wise'!I:I,'Bill Wise'!C:C,B98,'Bill Wise'!H:H,"Above 365 Days") -> 0 | P98: =SUM(H98:O98) -> 239300 | Q98: =G98-P98 -> 0
A99: 94 | B99: JINDAL POWER LIMITED-Crs | C99: Nellore | D99: Flyash | E99: Flyash | G99: =IFERROR(SUMIFS(TB!C:C,TB!A:A,B99)-SUMIFS(TB!B:B,TB!A:A,B99),0) -> 249687 | H99: =SUMIFS('Bill Wise'!I:I,'Bill Wise'!C:C,B99,'Bill Wise'!H:H,"0-30 Days") -> 249687 | I99: =SUMIFS('Bill Wise'!I:I,'Bill Wise'!C:C,B99,'Bill Wise'!H:H,"31-60 Days") -> 0 | J99: =SUMIFS('Bill Wise'!I:I,'Bill Wise'!C:C,B99,'Bill Wise'!H:H,"61-90 Days") -> 0 | K99: =SUMIFS('Bill Wise'!I:I,'Bill Wise'!C:C,B99,'Bill Wise'!H:H,"91-120 Days") -> 0 | L99: =SUMIFS('Bill Wise'!I:I,'Bill Wise'!C:C,B99,'Bill Wise'!H:H,"121-150 Days") -> 0 | M99: =SUMIFS('Bill Wise'!I:I,'Bill Wise'!C:C,B99,'Bill Wise'!H:H,"151-180 Days") -> 0 | N99: =SUMIFS('Bill Wise'!I:I,'Bill Wise'!C:C,B99,'Bill Wise'!H:H,"181-365 Days") -> 0 | O99: =SUMIFS('Bill Wise'!I:I,'Bill Wise'!C:C,B99,'Bill Wise'!H:H,"Above 365 Days") -> 0 | P99: =SUM(H99:O99) -> 249687 | Q99: =G99-P99 -> 0
A100: 95 | B100: Raju & Prasad Charted Accountant-Crs | C100: Head Office | D100: Expenses | E100: Professional Fees | G100: =IFERROR(SUMIFS(TB!C:C,TB!A:A,B100)-SUMIFS(TB!B:B,TB!A:A,B100),0) -> 263520 | H100: =SUMIFS('Bill Wise'!I:I,'Bill Wise'!C:C,B100,'Bill Wise'!H:H,"0-30 Days") -> 0 | I100: =SUMIFS('Bill Wise'!I:I,'Bill Wise'!C:C,B100,'Bill Wise'!H:H,"31-60 Days") -> 0 | J100: =SUMIFS('Bill Wise'!I:I,'Bill Wise'!C:C,B100,'Bill Wise'!H:H,"61-90 Days") -> 0 | K100: =SUMIFS('Bill Wise'!I:I,'Bill Wise'!C:C,B100,'Bill Wise'!H:H,"91-120 Days") -> 0 | L100: =SUMIFS('Bill Wise'!I:I,'Bill Wise'!C:C,B100,'Bill Wise'!H:H,"121-150 Days") -> 263520 | M100: =SUMIFS('Bill Wise'!I:I,'Bill Wise'!C:C,B100,'Bill Wise'!H:H,"151-180 Days") -> 0 | N100: =SUMIFS('Bill Wise'!I:I,'Bill Wise'!C:C,B100,'Bill Wise'!H:H,"181-365 Days") -> 0 | O100: =SUMIFS('Bill Wise'!I:I,'Bill Wise'!C:C,B100,'Bill Wise'!H:H,"Above 365 Days") -> 0 | P100: =SUM(H100:O100) -> 263520 | Q100: =G100-P100 -> 0
A101: 96 | B101: G D Packaging - Crs | C101: Vizag | D101: Expenses | E101: Store and spare | G101: =IFERROR(SUMIFS(TB!C:C,TB!A:A,B101)-SUMIFS(TB!B:B,TB!A:A,B101),0) -> 274308 | H101: =SUMIFS('Bill Wise'!I:I,'Bill Wise'!C:C,B101,'Bill Wise'!H:H,"0-30 Days") -> 233244 | I101: =SUMIFS('Bill Wise'!I:I,'Bill Wise'!C:C,B101,'Bill Wise'!H:H,"31-60 Days") -> 41064 | J101: =SUMIFS('Bill Wise'!I:I,'Bill Wise'!C:C,B101,'Bill Wise'!H:H,"61-90 Days") -> 0 | K101: =SUMIFS('Bill Wise'!I:I,'Bill Wise'!C:C,B101,'Bill Wise'!H:H,"91-120 Days") -> 0 | L101: =SUMIFS('Bill Wise'!I:I,'Bill Wise'!C:C,B101,'Bill Wise'!H:H,"121-150 Days") -> 0 | M101: =SUMIFS('Bill Wise'!I:I,'Bill Wise'!C:C,B101,'Bill Wise'!H:H,"151-180 Days") -> 0 | N101: =SUMIFS('Bill Wise'!I:I,'Bill Wise'!C:C,B101,'Bill Wise'!H:H,"181-365 Days") -> 0 | O101: =SUMIFS('Bill Wise'!I:I,'Bill Wise'!C:C,B101,'Bill Wise'!H:H,"Above 365 Days") -> 0 | P101: =SUM(H101:O101) -> 274308 | Q101: =G101-P101 -> 0
... A112: 107 | B112: S.K EARTHMOVERS-CRS | C112: Aggregate | D112: Expenses | E112: Repair & Maintenance | G112: =IFERROR(SUMIFS(TB!C:C,TB!A:A,B112)-SUMIFS(TB!B:B,TB!A:A,B112),0) -> 413451.98 | H112: =SUMIFS('Bill Wise'!I:I,'Bill Wise'!C:C,B112,'Bill Wise'!H:H,"0-30 Days") -> 413451.98 | I112: =SUMIFS('Bill Wise'!I:I,'Bill Wise'!C:C,B112,'Bill Wise'!H:H,"31-60 Days") -> 0 | J112: =SUMIFS('Bill Wise'!I:I,'Bill Wise'!C:C,B112,'Bill Wise'!H:H,"61-90 Days") -> 0 | K112: =SUMIFS('Bill Wise'!I:I,'Bill Wise'!C:C,B112,'Bill Wise'!H:H,"91-120 Days") -> 0 | L112: =SUMIFS('Bill Wise'!I:I,'Bill Wise'!C:C,B112,'Bill Wise'!H:H,"121-150 Days") -> 0 | M112: =SUMIFS('Bill Wise'!I:I,'Bill Wise'!C:C,B112,'Bill Wise'!H:H,"151-180 Days") -> 0 | N112: =SUMIFS('Bill Wise'!I:I,'Bill Wise'!C:C,B112,'Bill Wise'!H:H,"181-365 Days") -> 0 | O112: =SUMIFS('Bill Wise'!I:I,'Bill Wise'!C:C,B112,'Bill Wise'!H:H,"Above 365 Days") -> 0 | P112: =SUM(H112:O112) -> 413451.98 | Q112: =G112-P112 -> 0
A113: 108 | B113: Om Balaji - Crs | C113: Aggregate | D113: Raw Material | E113: 0 | G113: =IFERROR(SUMIFS(TB!C:C,TB!A:A,B113)-SUMIFS(TB!B:B,TB!A:A,B113),0) -> 416074.92 | H113: =SUMIFS('Bill Wise'!I:I,'Bill Wise'!C:C,B113,'Bill Wise'!H:H,"0-30 Days") -> 0 | I113: =SUMIFS('Bill Wise'!I:I,'Bill Wise'!C:C,B113,'Bill Wise'!H:H,"31-60 Days") -> 416074.92 | J113: =SUMIFS('Bill Wise'!I:I,'Bill Wise'!C:C,B113,'Bill Wise'!H:H,"61-90 Days") -> 0 | K113: =SUMIFS('Bill Wise'!I:I,'Bill Wise'!C:C,B113,'Bill Wise'!H:H,"91-120 Days") -> 0 | L113: =SUMIFS('Bill Wise'!I:I,'Bill Wise'!C:C,B113,'Bill Wise'!H:H,"121-150 Days") -> 0 | M113: =SUMIFS('Bill Wise'!I:I,'Bill Wise'!C:C,B113,'Bill Wise'!H:H,"151-180 Days") -> 0 | N113: =SUMIFS('Bill Wise'!I:I,'Bill Wise'!C:C,B113,'Bill Wise'!H:H,"181-365 Days") -> 0 | O113: =SUMIFS('Bill Wise'!I:I,'Bill Wise'!C:C,B113,'Bill Wise'!H:H,"Above 365 Days") -> 0 | P113: =SUM(H113:O113) -> 416074.92 | Q113: =G113-P113 -> 0
A114: 109 | B114: BN TRADING AND TRANSPORT COMPANY-CR | C114: Gujarat | D114: Transportation | E114: Transport | G114: =IFERROR(SUMIFS(TB!C:C,TB!A:A,B114)-SUMIFS(TB!B:B,TB!A:A,B114),0) -> 417743.16 | H114: =SUMIFS('Bill Wise'!I:I,'Bill Wise'!C:C,B114,'Bill Wise'!H:H,"0-30 Days") -> 417743.16 | I114: =SUMIFS('Bill Wise'!I:I,'Bill Wise'!C:C,B114,'Bill Wise'!H:H,"31-60 Days") -> 0 | J114: =SUMIFS('Bill Wise'!I:I,'Bill Wise'!C:C,B114,'Bill Wise'!H:H,"61-90 Days") -> 0 | K114: =SUMIFS('Bill Wise'!I:I,'Bill Wise'!C:C,B114,'Bill Wise'!H:H,"91-120 Days") -> 0 | L114: =SUMIFS('Bill Wise'!I:I,'Bill Wise'!C:C,B114,'Bill Wise'!H:H,"121-150 Days") -> 0 | M114: =SUMIFS('Bill Wise'!I:I,'Bill Wise'!C:C,B114,'Bill Wise'!H:H,"151-180 Days") -> 0 | N114: =SUMIFS('Bill Wise'!I:I,'Bill Wise'!C:C,B114,'Bill Wise'!H:H,"181-365 Days") -> 0 | O114: =SUMIFS('Bill Wise'!I:I,'Bill Wise'!C:C,B114,'Bill Wise'!H:H,"Above 365 Days") -> 0 | P114: =SUM(H114:O114) -> 417743.16 | Q114: =G114-P114 -> 0
A115: 110 | B115: SIS LIMITED-CRS | C115: Howrah | D115: Expenses | E115: Security charges | G115: =IFERROR(SUMIFS(TB!C:C,TB!A:A,B115)-SUMIFS(TB!B:B,TB!A:A,B115),0) -> 425184.61 | H115: =SUMIFS('Bill Wise'!I:I,'Bill Wise'!C:C,B115,'Bill Wise'!H:H,"0-30 Days") -> 0 | I115: =SUMIFS('Bill Wise'!I:I,'Bill Wise'!C:C,B115,'Bill Wise'!H:H,"31-60 Days") -> 0 | J115: =SUMIFS('Bill Wise'!I:I,'Bill Wise'!C:C,B115,'Bill Wise'!H:H,"61-90 Days") -> 0 | K115: =SUMIFS('Bill Wise'!I:I,'Bill Wise'!C:C,B115,'Bill Wise'!H:H,"91-120 Days") -> 0 | L115: =SUMIFS('Bill Wise'!I:I,'Bill Wise'!C:C,B115,'Bill Wise'!H:H,"121-150 Days") -> 0 | M115: =SUMIFS('Bill Wise'!I:I,'Bill Wise'!C:C,B115,'Bill Wise'!H:H,"151-180 Days") -> 0 | N115: =SUMIFS('Bill Wise'!I:I,'Bill Wise'!C:C,B115,'Bill Wise'!H:H,"181-365 Days") -> 425184.61 | O115: =SUMIFS('Bill Wise'!I:I,'Bill Wise'!C:C,B115,'Bill Wise'!H:H,"Above 365 Days") -> 0 | P115: =SUM(H115:O115) -> 425184.61 | Q115: =G115-P115 -> 0
A116: 111 | B116: R. G. Brothers Engineering Works - Crs | C116: wada | D116: Capex | E116: Capex | G116: =IFERROR(SUMIFS(TB!C:C,TB!A:A,B116)-SUMIFS(TB!B:B,TB!A:A,B116),0) -> 425594.04 | H116: =SUMIFS('Bill Wise'!I:I,'Bill Wise'!C:C,B116,'Bill Wise'!H:H,"0-30 Days") -> 425594.04 | I116: =SUMIFS('Bill Wise'!I:I,'Bill Wise'!C:C,B116,'Bill Wise'!H:H,"31-60 Days") -> 0 | J116: =SUMIFS('Bill Wise'!I:I,'Bill Wise'!C:C,B116,'Bill Wise'!H:H,"61-90 Days") -> 0 | K116: =SUMIFS('Bill Wise'!I:I,'Bill Wise'!C:C,B116,'Bill Wise'!H:H,"91-120 Days") -> 0 | L116: =SUMIFS('Bill Wise'!I:I,'Bill Wise'!C:C,B116,'Bill Wise'!H:H,"121-150 Days") -> 0 | M116: =SUMIFS('Bill Wise'!I:I,'Bill Wise'!C:C,B116,'Bill Wise'!H:H,"151-180 Days") -> 0 | N116: =SUMIFS('Bill Wise'!I:I,'Bill Wise'!C:C,B116,'Bill Wise'!H:H,"181-365 Days") -> 0 | O116: =SUMIFS('Bill Wise'!I:I,'Bill Wise'!C:C,B116,'Bill Wise'!H:H,"Above 365 Days") -> 0 | P116: =SUM(H116:O116) -> 425594.04 | Q116: =G116-P116 -> 0
A117: 112 | B117: M/s Jadav Enterprise - Crs | C117: Aggregate | D117: Raw Material | E117: 0 | G117: =IFERROR(SUMIFS(TB!C:C,TB!A:A,B117)-SUMIFS(TB!B:B,TB!A:A,B117),0) -> 426399.18 | H117: =SUMIFS('Bill Wise'!I:I,'Bill Wise'!C:C,B117,'Bill Wise'!H:H,"0-30 Days") -> 354525.18 | I117: =SUMIFS('Bill Wise'!I:I,'Bill Wise'!C:C,B117,'Bill Wise'!H:H,"31-60 Days") -> 71874 | J117: =SUMIFS('Bill Wise'!I:I,'Bill Wise'!C:C,B117,'Bill Wise'!H:H,"61-90 Days") -> 0 | K117: =SUMIFS('Bill Wise'!I:I,'Bill Wise'!C:C,B117,'Bill Wise'!H:H,"91-120 Days") -> 0 | L117: =SUMIFS('Bill Wise'!I:I,'Bill Wise'!C:C,B117,'Bill Wise'!H:H,"121-150 Days") -> 0 | M117: =SUMIFS('Bill Wise'!I:I,'Bill Wise'!C:C,B117,'Bill Wise'!H:H,"151-180 Days") -> 0 | N117: =SUMIFS('Bill Wise'!I:I,'Bill Wise'!C:C,B117,'Bill Wise'!H:H,"181-365 Days") -> 0 | O117: =SUMIFS('Bill Wise'!I:I,'Bill Wise'!C:C,B117,'Bill Wise'!H:H,"Above 365 Days") -> 0 | P117: =SUM(H117:O117) -> 426399.18 | Q117: =G117-P117 -> 0
A118: 113 | B118: Paras Sales Corporation -Crs | C118: Gujarat | D118: Expenses | E118: Repair & Maintenance | G118: =IFERROR(SUMIFS(TB!C:C,TB!A:A,B118)-SUMIFS(TB!B:B,TB!A:A,B118),0) -> 428544.42 | H118: =SUMIFS('Bill Wise'!I:I,'Bill Wise'!C:C,B118,'Bill Wise'!H:H,"0-30 Days") -> 428544.42 | I118: =SUMIFS('Bill Wise'!I:I,'Bill Wise'!C:C,B118,'Bill Wise'!H:H,"31-60 Days") -> 0 | J118: =SUMIFS('Bill Wise'!I:I,'Bill Wise'!C:C,B118,'Bill Wise'!H:H,"61-90 Days") -> 0 | K118: =SUMIFS('Bill Wise'!I:I,'Bill Wise'!C:C,B118,'Bill Wise'!H:H,"91-120 Days") -> 0 | L118: =SUMIFS('Bill Wise'!I:I,'Bill Wise'!C:C,B118,'Bill Wise'!H:H,"121-150 Days") -> 0 | M118: =SUMIFS('Bill Wise'!I:I,'Bill Wise'!C:C,B118,'Bill Wise'!H:H,"151-180 Days") -> 0 | N118: =SUMIFS('Bill Wise'!I:I,'Bill Wise'!C:C,B118,'Bill Wise'!H:H,"181-365 Days") -> 0 | O118: =SUMIFS('Bill Wise'!I:I,'Bill Wise'!C:C,B118,'Bill Wise'!H:H,"Above 365 Days") -> 0 | P118: =SUM(H118:O118) -> 428544.42 | Q118: =G118-P118 -> 0
A119: 114 | B119: WBSEDCL-CRS | C119: Aggregate | D119: Expenses | E119: Electricity | G119: =IFERROR(SUMIFS(TB!C:C,TB!A:A,B119)-SUMIFS(TB!B:B,TB!A:A,B119),0) -> 450130.89 | H119: =SUMIFS('Bill Wise'!I:I,'Bill Wise'!C:C,B119,'Bill Wise'!H:H,"0-30 Days") -> 450130.89 | I119: =SUMIFS('Bill Wise'!I:I,'Bill Wise'!C:C,B119,'Bill Wise'!H:H,"31-60 Days") -> 0 | J119: =SUMIFS('Bill Wise'!I:I,'Bill Wise'!C:C,B119,'Bill Wise'!H:H,"61-90 Days") -> 0 | K119: =SUMIFS('Bill Wise'!I:I,'Bill Wise'!C:C,B119,'Bill Wise'!H:H,"91-120 Days") -> 0 | L119: =SUMIFS('Bill Wise'!I:I,'Bill Wise'!C:C,B119,'Bill Wise'!H:H,"121-150 Days") -> 0 | M119: =SUMIFS('Bill Wise'!I:I,'Bill Wise'!C:C,B119,'Bill Wise'!H:H,"151-180 Days") -> 0 | N119: =SUMIFS('Bill Wise'!I:I,'Bill Wise'!C:C,B119,'Bill Wise'!H:H,"181-365 Days") -> 0 | O119: =SUMIFS('Bill Wise'!I:I,'Bill Wise'!C:C,B119,'Bill Wise'!H:H,"Above 365 Days") -> 0 | P119: =SUM(H119:O119) -> 450130.89 | Q119: =G119-P119 -> 0
A120: 115 | B120: Harish Ludhani - Employee | C120: Head Office | D120: Employee | E120: Consultancy Fees | G120: =IFERROR(SUMIFS(TB!C:C,TB!A:A,B120)-SUMIFS(TB!B:B,TB!A:A,B120),0) -> 459993.6 | H120: =SUMIFS('Bill Wise'!I:I,'Bill Wise'!C:C,B120,'Bill Wise'!H:H,"0-30 Days") -> 459993.6 | I120: =SUMIFS('Bill Wise'!I:I,'Bill Wise'!C:C,B120,'Bill Wise'!H:H,"31-60 Days") -> 0 | J120: =SUMIFS('Bill Wise'!I:I,'Bill Wise'!C:C,B120,'Bill Wise'!H:H,"61-90 Days") -> 0 | K120: =SUMIFS('Bill Wise'!I:I,'Bill Wise'!C:C,B120,'Bill Wise'!H:H,"91-120 Days") -> 0 | L120: =SUMIFS('Bill Wise'!I:I,'Bill Wise'!C:C,B120,'Bill Wise'!H:H,"121-150 Days") -> 0 | M120: =SUMIFS('Bill Wise'!I:I,'Bill Wise'!C:C,B120,'Bill Wise'!H:H,"151-180 Days") -> 0 | N120: =SUMIFS('Bill Wise'!I:I,'Bill Wise'!C:C,B120,'Bill Wise'!H:H,"181-365 Days") -> 0 | O120: =SUMIFS('Bill Wise'!I:I,'Bill Wise'!C:C,B120,'Bill Wise'!H:H,"Above 365 Days") -> 0 | P120: =SUM(H120:O120) -> 459993.6 | Q120: =G120-P120 -> 0
A121: 116 | B121: Bhamra Transport - Crs | C121: flyash | D121: Expenses | E121: Transport | G121: =IFERROR(SUMIFS(TB!C:C,TB!A:A,B121)-SUMIFS(TB!B:B,TB!A:A,B121),0) -> 464872.27 | H121: =SUMIFS('Bill Wise'!I:I,'Bill Wise'!C:C,B121,'Bill Wise'!H:H,"0-30 Days") -> 464872.27 | I121: =SUMIFS('Bill Wise'!I:I,'Bill Wise'!C:C,B121,'Bill Wise'!H:H,"31-60 Days") -> 0 | J121: =SUMIFS('Bill Wise'!I:I,'Bill Wise'!C:C,B121,'Bill Wise'!H:H,"61-90 Days") -> 0 | K121: =SUMIFS('Bill Wise'!I:I,'Bill Wise'!C:C,B121,'Bill Wise'!H:H,"91-120 Days") -> 0 | L121: =SUMIFS('Bill Wise'!I:I,'Bill Wise'!C:C,B121,'Bill Wise'!H:H,"121-150 Days") -> 0 | M121: =SUMIFS('Bill Wise'!I:I,'Bill Wise'!C:C,B121,'Bill Wise'!H:H,"151-180 Days") -> 0 | N121: =SUMIFS('Bill Wise'!I:I,'Bill Wise'!C:C,B121,'Bill Wise'!H:H,"181-365 Days") -> 0 | O121: =SUMIFS('Bill Wise'!I:I,'Bill Wise'!C:C,B121,'Bill Wise'!H:H,"Above 365 Days") -> 0 | P121: =SUM(H121:O121) -> 464872.27 | Q121: =G121-P121 -> 0
A122: 117 | B122: Rushika Enterprise - Crs | C122: flyash | D122: Transportation | E122: Transport | G122: =IFERROR(SUMIFS(TB!C:C,TB!A:A,B122)-SUMIFS(TB!B:B,TB!A:A,B122),0) -> 471144.46 | H122: =SUMIFS('Bill Wise'!I:I,'Bill Wise'!C:C,B122,'Bill Wise'!H:H,"0-30 Days") -> 471144.46 | I122: =SUMIFS('Bill Wise'!I:I,'Bill Wise'!C:C,B122,'Bill Wise'!H:H,"31-60 Days") -> 0 | J122: =SUMIFS('Bill Wise'!I:I,'Bill Wise'!C:C,B122,'Bill Wise'!H:H,"61-90 Days") -> 0 | K122: =SUMIFS('Bill Wise'!I:I,'Bill Wise'!C:C,B122,'Bill Wise'!H:H,"91-120 Days") -> 0 | L122: =SUMIFS('Bill Wise'!I:I,'Bill Wise'!C:C,B122,'Bill Wise'!H:H,"121-150 Days") -> 0 | M122: =SUMIFS('Bill Wise'!I:I,'Bill Wise'!C:C,B122,'Bill Wise'!H:H,"151-180 Days") -> 0 | N122: =SUMIFS('Bill Wise'!I:I,'Bill Wise'!C:C,B122,'Bill Wise'!H:H,"181-365 Days") -> 0 | O122: =SUMIFS('Bill Wise'!I:I,'Bill Wise'!C:C,B122,'Bill Wise'!H:H,"Above 365 Days") -> 0 | P122: =SUM(H122:O122) -> 471144.46 | Q122: =G122-P122 -> 0
A123: 118 | B123: Shree Mahalaxmi Traders-Crs | C123: Gujarat | D123: Transportation | E123: Transport | G123: =IFERROR(SUMIFS(TB!C:C,TB!A:A,B123)-SUMIFS(TB!B:B,TB!A:A,B123),0) -> 494112 | H123: =SUMIFS('Bill Wise'!I:I,'Bill Wise'!C:C,B123,'Bill Wise'!H:H,"0-30 Days") -> 0 | I123: =SUMIFS('Bill Wise'!I:I,'Bill Wise'!C:C,B123,'Bill Wise'!H:H,"31-60 Days") -> 214820 | J123: =SUMIFS('Bill Wise'!I:I,'Bill Wise'!C:C,B123,'Bill Wise'!H:H,"61-90 Days") -> 279292 | K123: =SUMIFS('Bill Wise'!I:I,'Bill Wise'!C:C,B123,'Bill Wise'!H:H,"91-120 Days") -> 0 | L123: =SUMIFS('Bill Wise'!I:I,'Bill Wise'!C:C,B123,'Bill Wise'!H:H,"121-150 Days") -> 0 | M123: =SUMIFS('Bill Wise'!I:I,'Bill Wise'!C:C,B123,'Bill Wise'!H:H,"151-180 Days") -> 0 | N123: =SUMIFS('Bill Wise'!I:I,'Bill Wise'!C:C,B123,'Bill Wise'!H:H,"181-365 Days") -> 0 | O123: =SUMIFS('Bill Wise'!I:I,'Bill Wise'!C:C,B123,'Bill Wise'!H:H,"Above 365 Days") -> 0 | P123: =SUM(H123:O123) -> 494112 | Q123: =G123-P123 -> 0
A124: 119 | B124: PUNAGHAR MATA TOOL CENTER - Crs | C124: Goa | D124: Expenses | E124: Repair & Maintenance | G124: =IFERROR(SUMIFS(TB!C:C,TB!A:A,B124)-SUMIFS(TB!B:B,TB!A:A,B124),0) -> 502551.78 | H124: =SUMIFS('Bill Wise'!I:I,'Bill Wise'!C:C,B124,'Bill Wise'!H:H,"0-30 Days") -> 31860 | I124: =SUMIFS('Bill Wise'!I:I,'Bill Wise'!C:C,B124,'Bill Wise'!H:H,"31-60 Days") -> 89859 | J124: =SUMIFS('Bill Wise'!I:I,'Bill Wise'!C:C,B124,'Bill Wise'!H:H,"61-90 Days") -> 380832.78 | K124: =SUMIFS('Bill Wise'!I:I,'Bill Wise'!C:C,B124,'Bill Wise'!H:H,"91-120 Days") -> 0 | L124: =SUMIFS('Bill Wise'!I:I,'Bill Wise'!C:C,B124,'Bill Wise'!H:H,"121-150 Days") -> 0 | M124: =SUMIFS('Bill Wise'!I:I,'Bill Wise'!C:C,B124,'Bill Wise'!H:H,"151-180 Days") -> 0 | N124: =SUMIFS('Bill Wise'!I:I,'Bill Wise'!C:C,B124,'Bill Wise'!H:H,"181-365 Days") -> 0 | O124: =SUMIFS('Bill Wise'!I:I,'Bill Wise'!C:C,B124,'Bill Wise'!H:H,"Above 365 Days") -> 0 | P124: =SUM(H124:O124) -> 502551.78 | Q124: =G124-P124 -> 0
A125: 120 | B125: Siddhi Vinayak Corporation-Crs | C125: Gujarat | D125: Expenses | E125: 0 | G125: =IFERROR(SUMIFS(TB!C:C,TB!A:A,B125)-SUMIFS(TB!B:B,TB!A:A,B125),0) -> 521234 | H125: =SUMIFS('Bill Wise'!I:I,'Bill Wise'!C:C,B125,'Bill Wise'!H:H,"0-30 Days") -> 521234 | I125: =SUMIFS('Bill Wise'!I:I,'Bill Wise'!C:C,B125,'Bill Wise'!H:H,"31-60 Days") -> 0 | J125: =SUMIFS('Bill Wise'!I:I,'Bill Wise'!C:C,B125,'Bill Wise'!H:H,"61-90 Days") -> 0 | K125: =SUMIFS('Bill Wise'!I:I,'Bill Wise'!C:C,B125,'Bill Wise'!H:H,"91-120 Days") -> 0 | L125: =SUMIFS('Bill Wise'!I:I,'Bill Wise'!C:C,B125,'Bill Wise'!H:H,"121-150 Days") -> 0 | M125: =SUMIFS('Bill Wise'!I:I,'Bill Wise'!C:C,B125,'Bill Wise'!H:H,"151-180 Days") -> 0 | N125: =SUMIFS('Bill Wise'!I:I,'Bill Wise'!C:C,B125,'Bill Wise'!H:H,"181-365 Days") -> 0 | O125: =SUMIFS('Bill Wise'!I:I,'Bill Wise'!C:C,B125,'Bill Wise'!H:H,"Above 365 Days") -> 0 | P125: =SUM(H125:O125) -> 521234 | Q125: =G125-P125 -> 0
A126: 121 | B126: MSJ Movers - CRS | C126: Nagpur | D126: Raw Material | E126: Flyash | G126: =IFERROR(SUMIFS(TB!C:C,TB!A:A,B126)-SUMIFS(TB!B:B,TB!A:A,B126),0) -> 536224.83 | H126: =SUMIFS('Bill Wise'!I:I,'Bill Wise'!C:C,B126,'Bill Wise'!H:H,"0-30 Days") -> 536224.83 | I126: =SUMIFS('Bill Wise'!I:I,'Bill Wise'!C:C,B126,'Bill Wise'!H:H,"31-60 Days") -> 0 | J126: =SUMIFS('Bill Wise'!I:I,'Bill Wise'!C:C,B126,'Bill Wise'!H:H,"61-90 Days") -> 0 | K126: =SUMIFS('Bill Wise'!I:I,'Bill Wise'!C:C,B126,'Bill Wise'!H:H,"91-120 Days") -> 0 | L126: =SUMIFS('Bill Wise'!I:I,'Bill Wise'!C:C,B126,'Bill Wise'!H:H,"121-150 Days") -> 0 | M126: =SUMIFS('Bill Wise'!I:I,'Bill Wise'!C:C,B126,'Bill Wise'!H:H,"151-180 Days") -> 0 | N126: =SUMIFS('Bill Wise'!I:I,'Bill Wise'!C:C,B126,'Bill Wise'!H:H,"181-365 Days") -> 0 | O126: =SUMIFS('Bill Wise'!I:I,'Bill Wise'!C:C,B126,'Bill Wise'!H:H,"Above 365 Days") -> 0 | P126: =SUM(H126:O126) -> 536224.83 | Q126: =G126-P126 -> 0
A127: 122 | B127: Rehaman Transport - Crs | C127: Vizag | D127: Transportation | E127: Transport | G127: =IFERROR(SUMIFS(TB!C:C,TB!A:A,B127)-SUMIFS(TB!B:B,TB!A:A,B127),0) -> 536674 | H127: =SUMIFS('Bill Wise'!I:I,'Bill Wise'!C:C,B127,'Bill Wise'!H:H,"0-30 Days") -> 536674 | I127: =SUMIFS('Bill Wise'!I:I,'Bill Wise'!C:C,B127,'Bill Wise'!H:H,"31-60 Days") -> 0 | J127: =SUMIFS('Bill Wise'!I:I,'Bill Wise'!C:C,B127,'Bill Wise'!H:H,"61-90 Days") -> 0 | K127: =SUMIFS('Bill Wise'!I:I,'Bill Wise'!C:C,B127,'Bill Wise'!H:H,"91-120 Days") -> 0 | L127: =SUMIFS('Bill Wise'!I:I,'Bill Wise'!C:C,B127,'Bill Wise'!H:H,"121-150 Days") -> 0 | M127: =SUMIFS('Bill Wise'!I:I,'Bill Wise'!C:C,B127,'Bill Wise'!H:H,"151-180 Days") -> 0 | N127: =SUMIFS('Bill Wise'!I:I,'Bill Wise'!C:C,B127,'Bill Wise'!H:H,"181-365 Days") -> 0 | O127: =SUMIFS('Bill Wise'!I:I,'Bill Wise'!C:C,B127,'Bill Wise'!H:H,"Above 365 Days") -> 0 | P127: =SUM(H127:O127) -> 536674 | Q127: =G127-P127 -> 0
A128: 123 | B128: FAITH INFRA-CRS | C128: Aggregate | D128: Expenses | E128: Repair & Maintenance | G128: =IFERROR(SUMIFS(TB!C:C,TB!A:A,B128)-SUMIFS(TB!B:B,TB!A:A,B128),0) -> 542308.24 | H128: =SUMIFS('Bill Wise'!I:I,'Bill Wise'!C:C,B128,'Bill Wise'!H:H,"0-30 Days") -> 446028.24 | I128: =SUMIFS('Bill Wise'!I:I,'Bill Wise'!C:C,B128,'Bill Wise'!H:H,"31-60 Days") -> 0 | J128: =SUMIFS('Bill Wise'!I:I,'Bill Wise'!C:C,B128,'Bill Wise'!H:H,"61-90 Days") -> 96280 | K128: =SUMIFS('Bill Wise'!I:I,'Bill Wise'!C:C,B128,'Bill Wise'!H:H,"91-120 Days") -> 0 | L128: =SUMIFS('Bill Wise'!I:I,'Bill Wise'!C:C,B128,'Bill Wise'!H:H,"121-150 Days") -> 0 | M128: =SUMIFS('Bill Wise'!I:I,'Bill Wise'!C:C,B128,'Bill Wise'!H:H,"151-180 Days") -> 0 | N128: =SUMIFS('Bill Wise'!I:I,'Bill Wise'!C:C,B128,'Bill Wise'!H:H,"181-365 Days") -> 0 | O128: =SUMIFS('Bill Wise'!I:I,'Bill Wise'!C:C,B128,'Bill Wise'!H:H,"Above 365 Days") -> 0 | P128: =SUM(H128:O128) -> 542308.24 | Q128: =G128-P128 -> 0
A129: 124 | B129: Shri Veereshwar Transport | C129: Bangalore | D129: Transportation | E129: Transport | G129: =IFERROR(SUMIFS(TB!C:C,TB!A:A,B129)-SUMIFS(TB!B:B,TB!A:A,B129),0) -> 567697 | H129: =SUMIFS('Bill Wise'!I:I,'Bill Wise'!C:C,B129,'Bill Wise'!H:H,"0-30 Days") -> 567697 | I129: =SUMIFS('Bill Wise'!I:I,'Bill Wise'!C:C,B129,'Bill Wise'!H:H,"31-60 Days") -> 0 | J129: =SUMIFS('Bill Wise'!I:I,'Bill Wise'!C:C,B129,'Bill Wise'!H:H,"61-90 Days") -> 0 | K129: =SUMIFS('Bill Wise'!I:I,'Bill Wise'!C:C,B129,'Bill Wise'!H:H,"91-120 Days") -> 0 | L129: =SUMIFS('Bill Wise'!I:I,'Bill Wise'!C:C,B129,'Bill Wise'!H:H,"121-150 Days") -> 0 | M129: =SUMIFS('Bill Wise'!I:I,'Bill Wise'!C:C,B129,'Bill Wise'!H:H,"151-180 Days") -> 0 | N129: =SUMIFS('Bill Wise'!I:I,'Bill Wise'!C:C,B129,'Bill Wise'!H:H,"181-365 Days") -> 0 | O129: =SUMIFS('Bill Wise'!I:I,'Bill Wise'!C:C,B129,'Bill Wise'!H:H,"Above 365 Days") -> 0 | P129: =SUM(H129:O129) -> 567697 | Q129: =G129-P129 -> 0
A130: 125 | B130: Asia Minerals and Machinery Company - Crs | C130: Wada | D130: Expenses | E130: Store and spare | G130: =IFERROR(SUMIFS(TB!C:C,TB!A:A,B130)-SUMIFS(TB!B:B,TB!A:A,B130),0) -> 603502 | H130: =SUMIFS('Bill Wise'!I:I,'Bill Wise'!C:C,B130,'Bill Wise'!H:H,"0-30 Days") -> 0 | I130: =SUMIFS('Bill Wise'!I:I,'Bill Wise'!C:C,B130,'Bill Wise'!H:H,"31-60 Days") -> 0 | J130: =SUMIFS('Bill Wise'!I:I,'Bill Wise'!C:C,B130,'Bill Wise'!H:H,"61-90 Days") -> 603502 | K130: =SUMIFS('Bill Wise'!I:I,'Bill Wise'!C:C,B130,'Bill Wise'!H:H,"91-120 Days") -> 0 | L130: =SUMIFS('Bill Wise'!I:I,'Bill Wise'!C:C,B130,'Bill Wise'!H:H,"121-150 Days") -> 0 | M130: =SUMIFS('Bill Wise'!I:I,'Bill Wise'!C:C,B130,'Bill Wise'!H:H,"151-180 Days") -> 0 | N130: =SUMIFS('Bill Wise'!I:I,'Bill Wise'!C:C,B130,'Bill Wise'!H:H,"181-365 Days") -> 0 | O130: =SUMIFS('Bill Wise'!I:I,'Bill Wise'!C:C,B130,'Bill Wise'!H:H,"Above 365 Days") -> 0 | P130: =SUM(H130:O130) -> 603502 | Q130: =G130-P130 -> 0
A131: 126 | B131: Mollick Tube- Crs | C131: Aggregate | D131: Trading | E131: Aggregate | G131: =IFERROR(SUMIFS(TB!C:C,TB!A:A,B131)-SUMIFS(TB!B:B,TB!A:A,B131),0) -> 623635.12 | H131: =SUMIFS('Bill Wise'!I:I,'Bill Wise'!C:C,B131,'Bill Wise'!H:H,"0-30 Days") -> 0 | I131: =SUMIFS('Bill Wise'!I:I,'Bill Wise'!C:C,B131,'Bill Wise'!H:H,"31-60 Days") -> 0 | J131: =SUMIFS('Bill Wise'!I:I,'Bill Wise'!C:C,B131,'Bill Wise'!H:H,"61-90 Days") -> 0 | K131: =SUMIFS('Bill Wise'!I:I,'Bill Wise'!C:C,B131,'Bill Wise'!H:H,"91-120 Days") -> 0 | L131: =SUMIFS('Bill Wise'!I:I,'Bill Wise'!C:C,B131,'Bill Wise'!H:H,"121-150 Days") -> 437373.82 | M131: =SUMIFS('Bill Wise'!I:I,'Bill Wise'!C:C,B131,'Bill Wise'!H:H,"151-180 Days") -> 186261.3 | N131: =SUMIFS('Bill Wise'!I:I,'Bill Wise'!C:C,B131,'Bill Wise'!H:H,"181-365 Days") -> 0 | O131: =SUMIFS('Bill Wise'!I:I,'Bill Wise'!C:C,B131,'Bill Wise'!H:H,"Above 365 Days") -> 0 | P131: =SUM(H131:O131) -> 623635.12 | Q131: =G131-P131 -> 0
A132: 127 | B132: Luk Enterprises - Crs | C132: Gujarat | D132: Capex | E132: Capex | G132: =IFERROR(SUMIFS(TB!C:C,TB!A:A,B132)-SUMIFS(TB!B:B,TB!A:A,B132),0) -> 627771.51 | H132: =SUMIFS('Bill Wise'!I:I,'Bill Wise'!C:C,B132,'Bill Wise'!H:H,"0-30 Days") -> 0 | I132: =SUMIFS('Bill Wise'!I:I,'Bill Wise'!C:C,B132,'Bill Wise'!H:H,"31-60 Days") -> 0 | J132: =SUMIFS('Bill Wise'!I:I,'Bill Wise'!C:C,B132,'Bill Wise'!H:H,"61-90 Days") -> 0 | K132: =SUMIFS('Bill Wise'!I:I,'Bill Wise'!C:C,B132,'Bill Wise'!H:H,"91-120 Days") -> 0 | L132: =SUMIFS('Bill Wise'!I:I,'Bill Wise'!C:C,B132,'Bill Wise'!H:H,"121-150 Days") -> 0 | M132: =SUMIFS('Bill Wise'!I:I,'Bill Wise'!C:C,B132,'Bill Wise'!H:H,"151-180 Days") -> 0 | N132: =SUMIFS('Bill Wise'!I:I,'Bill Wise'!C:C,B132,'Bill Wise'!H:H,"181-365 Days") -> 627771.51 | O132: =SUMIFS('Bill Wise'!I:I,'Bill Wise'!C:C,B132,'Bill Wise'!H:H,"Above 365 Days") -> 0 | P132: =SUM(H132:O132) -> 627771.51 | Q132: =G132-P132 -> 0
A133: 128 | B133: JFC Logistics - Crs | C133: Goa | D133: Transportation | E133: Transport | G133: =IFERROR(SUMIFS(TB!C:C,TB!A:A,B133)-SUMIFS(TB!B:B,TB!A:A,B133),0) -> 646998.8 | H133: =SUMIFS('Bill Wise'!I:I,'Bill Wise'!C:C,B133,'Bill Wise'!H:H,"0-30 Days") -> 632732.9 | I133: =SUMIFS('Bill Wise'!I:I,'Bill Wise'!C:C,B133,'Bill Wise'!H:H,"31-60 Days") -> 0 | J133: =SUMIFS('Bill Wise'!I:I,'Bill Wise'!C:C,B133,'Bill Wise'!H:H,"61-90 Days") -> 0 | K133: =SUMIFS('Bill Wise'!I:I,'Bill Wise'!C:C,B133,'Bill Wise'!H:H,"91-120 Days") -> 0 | L133: =SUMIFS('Bill Wise'!I:I,'Bill Wise'!C:C,B133,'Bill Wise'!H:H,"121-150 Days") -> 0 | M133: =SUMIFS('Bill Wise'!I:I,'Bill Wise'!C:C,B133,'Bill Wise'!H:H,"151-180 Days") -> 0 | N133: =SUMIFS('Bill Wise'!I:I,'Bill Wise'!C:C,B133,'Bill Wise'!H:H,"181-365 Days") -> 14265.9 | O133: =SUMIFS('Bill Wise'!I:I,'Bill Wise'!C:C,B133,'Bill Wise'!H:H,"Above 365 Days") -> 0 | P133: =SUM(H133:O133) -> 646998.8 | Q133: =G133-P133 -> 0
A134: 129 | B134: ADVITA POLYCRAFT LLP - Crs | C134: Wada | D134: Expenses | E134: Store and spare | G134: =IFERROR(SUMIFS(TB!C:C,TB!A:A,B134)-SUMIFS(TB!B:B,TB!A:A,B134),0) -> 655797.08 | H134: =SUMIFS('Bill Wise'!I:I,'Bill Wise'!C:C,B134,'Bill Wise'!H:H,"0-30 Days") -> 454244.93 | I134: =SUMIFS('Bill Wise'!I:I,'Bill Wise'!C:C,B134,'Bill Wise'!H:H,"31-60 Days") -> 190932.15 | J134: =SUMIFS('Bill Wise'!I:I,'Bill Wise'!C:C,B134,'Bill Wise'!H:H,"61-90 Days") -> 0 | K134: =SUMIFS('Bill Wise'!I:I,'Bill Wise'!C:C,B134,'Bill Wise'!H:H,"91-120 Days") -> 10620 | L134: =SUMIFS('Bill Wise'!I:I,'Bill Wise'!C:C,B134,'Bill Wise'!H:H,"121-150 Days") -> 0 | M134: =SUMIFS('Bill Wise'!I:I,'Bill Wise'!C:C,B134,'Bill Wise'!H:H,"151-180 Days") -> 0 | N134: =SUMIFS('Bill Wise'!I:I,'Bill Wise'!C:C,B134,'Bill Wise'!H:H,"181-365 Days") -> 0 | O134: =SUMIFS('Bill Wise'!I:I,'Bill Wise'!C:C,B134,'Bill Wise'!H:H,"Above 365 Days") -> 0 | P134: =SUM(H134:O134) -> 655797.08 | Q134: =G134-P134 -> 0
A135: 130 | B135: SULTAN ENTERPRISES-CRS | C135: flyash | D135: Expenses | E135: Contract Labour | G135: =IFERROR(SUMIFS(TB!C:C,TB!A:A,B135)-SUMIFS(TB!B:B,TB!A:A,B135),0) -> 666028.64 | H135: =SUMIFS('Bill Wise'!I:I,'Bill Wise'!C:C,B135,'Bill Wise'!H:H,"0-30 Days") -> 0 | I135: =SUMIFS('Bill Wise'!I:I,'Bill Wise'!C:C,B135,'Bill Wise'!H:H,"31-60 Days") -> 0 | J135: =SUMIFS('Bill Wise'!I:I,'Bill Wise'!C:C,B135,'Bill Wise'!H:H,"61-90 Days") -> 0 | K135: =SUMIFS('Bill Wise'!I:I,'Bill Wise'!C:C,B135,'Bill Wise'!H:H,"91-120 Days") -> 0 | L135: =SUMIFS('Bill Wise'!I:I,'Bill Wise'!C:C,B135,'Bill Wise'!H:H,"121-150 Days") -> 114935.62 | M135: =SUMIFS('Bill Wise'!I:I,'Bill Wise'!C:C,B135,'Bill Wise'!H:H,"151-180 Days") -> 0 | N135: =SUMIFS('Bill Wise'!I:I,'Bill Wise'!C:C,B135,'Bill Wise'!H:H,"181-365 Days") -> 125155.8 | O135: =SUMIFS('Bill Wise'!I:I,'Bill Wise'!C:C,B135,'Bill Wise'!H:H,"Above 365 Days") -> 425937.22 | P135: =SUM(H135:O135) -> 666028.64 | Q135: =G135-P135 -> 0
A136: 131 | B136: MSEDCL - CRS | C136: Nagpur | D136: Expenses | E136: Electricity | G136: =IFERROR(SUMIFS(TB!C:C,TB!A:A,B136)-SUMIFS(TB!B:B,TB!A:A,B136),0) -> 669710 | H136: =SUMIFS('Bill Wise'!I:I,'Bill Wise'!C:C,B136,'Bill Wise'!H:H,"0-30 Days") -> 669710 | I136: =SUMIFS('Bill Wise'!I:I,'Bill Wise'!C:C,B136,'Bill Wise'!H:H,"31-60 Days") -> 0 | J136: =SUMIFS('Bill Wise'!I:I,'Bill Wise'!C:C,B136,'Bill Wise'!H:H,"61-90 Days") -> 0 | K136: =SUMIFS('Bill Wise'!I:I,'Bill Wise'!C:C,B136,'Bill Wise'!H:H,"91-120 Days") -> 0 | L136: =SUMIFS('Bill Wise'!I:I,'Bill Wise'!C:C,B136,'Bill Wise'!H:H,"121-150 Days") -> 0 | M136: =SUMIFS('Bill Wise'!I:I,'Bill Wise'!C:C,B136,'Bill Wise'!H:H,"151-180 Days") -> 0 | N136: =SUMIFS('Bill Wise'!I:I,'Bill Wise'!C:C,B136,'Bill Wise'!H:H,"181-365 Days") -> 0 | O136: =SUMIFS('Bill Wise'!I:I,'Bill Wise'!C:C,B136,'Bill Wise'!H:H,"Above 365 Days") -> 0 | P136: =SUM(H136:O136) -> 669710 | Q136: =G136-P136 -> 0
A137: 132 | B137: Sumit Goods Carrier(Arabinda Kumar Das) - CRS | C137: haryana | D137: Expenses | E137: Repair & Maintenance | G137: =IFERROR(SUMIFS(TB!C:C,TB!A:A,B137)-SUMIFS(TB!B:B,TB!A:A,B137),0) -> 678850 | H137: =SUMIFS('Bill Wise'!I:I,'Bill Wise'!C:C,B137,'Bill Wise'!H:H,"0-30 Days") -> 678850 | I137: =SUMIFS('Bill Wise'!I:I,'Bill Wise'!C:C,B137,'Bill Wise'!H:H,"31-60 Days") -> 0 | J137: =SUMIFS('Bill Wise'!I:I,'Bill Wise'!C:C,B137,'Bill Wise'!H:H,"61-90 Days") -> 0 | K137: =SUMIFS('Bill Wise'!I:I,'Bill Wise'!C:C,B137,'Bill Wise'!H:H,"91-120 Days") -> 0 | L137: =SUMIFS('Bill Wise'!I:I,'Bill Wise'!C:C,B137,'Bill Wise'!H:H,"121-150 Days") -> 0 | M137: =SUMIFS('Bill Wise'!I:I,'Bill Wise'!C:C,B137,'Bill Wise'!H:H,"151-180 Days") -> 0 | N137: =SUMIFS('Bill Wise'!I:I,'Bill Wise'!C:C,B137,'Bill Wise'!H:H,"181-365 Days") -> 0 | O137: =SUMIFS('Bill Wise'!I:I,'Bill Wise'!C:C,B137,'Bill Wise'!H:H,"Above 365 Days") -> 0 | P137: =SUM(H137:O137) -> 678850 | Q137: =G137-P137 -> 0
... A146: 141 | B146: Devanand B. Singh - Employee | C146: Head Office | D146: Employee | E146: Employee | G146: =IFERROR(SUMIFS(TB!C:C,TB!A:A,B146)-SUMIFS(TB!B:B,TB!A:A,B146),0) -> 827999.28 | H146: =SUMIFS('Bill Wise'!I:I,'Bill Wise'!C:C,B146,'Bill Wise'!H:H,"0-30 Days") -> 827999.28 | I146: =SUMIFS('Bill Wise'!I:I,'Bill Wise'!C:C,B146,'Bill Wise'!H:H,"31-60 Days") -> 0 | J146: =SUMIFS('Bill Wise'!I:I,'Bill Wise'!C:C,B146,'Bill Wise'!H:H,"61-90 Days") -> 0 | K146: =SUMIFS('Bill Wise'!I:I,'Bill Wise'!C:C,B146,'Bill Wise'!H:H,"91-120 Days") -> 0 | L146: =SUMIFS('Bill Wise'!I:I,'Bill Wise'!C:C,B146,'Bill Wise'!H:H,"121-150 Days") -> 0 | M146: =SUMIFS('Bill Wise'!I:I,'Bill Wise'!C:C,B146,'Bill Wise'!H:H,"151-180 Days") -> 0 | N146: =SUMIFS('Bill Wise'!I:I,'Bill Wise'!C:C,B146,'Bill Wise'!H:H,"181-365 Days") -> 0 | O146: =SUMIFS('Bill Wise'!I:I,'Bill Wise'!C:C,B146,'Bill Wise'!H:H,"Above 365 Days") -> 0 | P146: =SUM(H146:O146) -> 827999.28 | Q146: =G146-P146 -> 0
A147: 142 | B147: Shri Raghavendra Enterprises - Crs | C147: Bangalore | D147: Trading | E147: 0 | G147: =IFERROR(SUMIFS(TB!C:C,TB!A:A,B147)-SUMIFS(TB!B:B,TB!A:A,B147),0) -> 835462.18 | H147: =SUMIFS('Bill Wise'!I:I,'Bill Wise'!C:C,B147,'Bill Wise'!H:H,"0-30 Days") -> 835462.18 | I147: =SUMIFS('Bill Wise'!I:I,'Bill Wise'!C:C,B147,'Bill Wise'!H:H,"31-60 Days") -> 0 | J147: =SUMIFS('Bill Wise'!I:I,'Bill Wise'!C:C,B147,'Bill Wise'!H:H,"61-90 Days") -> 0 | K147: =SUMIFS('Bill Wise'!I:I,'Bill Wise'!C:C,B147,'Bill Wise'!H:H,"91-120 Days") -> 0 | L147: =SUMIFS('Bill Wise'!I:I,'Bill Wise'!C:C,B147,'Bill Wise'!H:H,"121-150 Days") -> 0 | M147: =SUMIFS('Bill Wise'!I:I,'Bill Wise'!C:C,B147,'Bill Wise'!H:H,"151-180 Days") -> 0 | N147: =SUMIFS('Bill Wise'!I:I,'Bill Wise'!C:C,B147,'Bill Wise'!H:H,"181-365 Days") -> 0 | O147: =SUMIFS('Bill Wise'!I:I,'Bill Wise'!C:C,B147,'Bill Wise'!H:H,"Above 365 Days") -> 0 | P147: =SUM(H147:O147) -> 835462.18 | Q147: =G147-P147 -> 0
A148: 143 | B148: ARKAY LOGISTICS-Crs | C148: flyash | D148: Trading | E148: Flyash | G148: =IFERROR(SUMIFS(TB!C:C,TB!A:A,B148)-SUMIFS(TB!B:B,TB!A:A,B148),0) -> 848978.08 | H148: =SUMIFS('Bill Wise'!I:I,'Bill Wise'!C:C,B148,'Bill Wise'!H:H,"0-30 Days") -> 848978.08 | I148: =SUMIFS('Bill Wise'!I:I,'Bill Wise'!C:C,B148,'Bill Wise'!H:H,"31-60 Days") -> 0 | J148: =SUMIFS('Bill Wise'!I:I,'Bill Wise'!C:C,B148,'Bill Wise'!H:H,"61-90 Days") -> 0 | K148: =SUMIFS('Bill Wise'!I:I,'Bill Wise'!C:C,B148,'Bill Wise'!H:H,"91-120 Days") -> 0 | L148: =SUMIFS('Bill Wise'!I:I,'Bill Wise'!C:C,B148,'Bill Wise'!H:H,"121-150 Days") -> 0 | M148: =SUMIFS('Bill Wise'!I:I,'Bill Wise'!C:C,B148,'Bill Wise'!H:H,"151-180 Days") -> 0 | N148: =SUMIFS('Bill Wise'!I:I,'Bill Wise'!C:C,B148,'Bill Wise'!H:H,"181-365 Days") -> 0 | O148: =SUMIFS('Bill Wise'!I:I,'Bill Wise'!C:C,B148,'Bill Wise'!H:H,"Above 365 Days") -> 0 | P148: =SUM(H148:O148) -> 848978.08 | Q148: =G148-P148 -> 0
A149: 144 | B149: Neofines Solution-CRS | C149: Raipur | D149: Trading | E149: Microsilica | G149: =IFERROR(SUMIFS(TB!C:C,TB!A:A,B149)-SUMIFS(TB!B:B,TB!A:A,B149),0) -> 866710 | H149: =SUMIFS('Bill Wise'!I:I,'Bill Wise'!C:C,B149,'Bill Wise'!H:H,"0-30 Days") -> 406510 | I149: =SUMIFS('Bill Wise'!I:I,'Bill Wise'!C:C,B149,'Bill Wise'!H:H,"31-60 Days") -> 0 | J149: =SUMIFS('Bill Wise'!I:I,'Bill Wise'!C:C,B149,'Bill Wise'!H:H,"61-90 Days") -> 460200 | K149: =SUMIFS('Bill Wise'!I:I,'Bill Wise'!C:C,B149,'Bill Wise'!H:H,"91-120 Days") -> 0 | L149: =SUMIFS('Bill Wise'!I:I,'Bill Wise'!C:C,B149,'Bill Wise'!H:H,"121-150 Days") -> 0 | M149: =SUMIFS('Bill Wise'!I:I,'Bill Wise'!C:C,B149,'Bill Wise'!H:H,"151-180 Days") -> 0 | N149: =SUMIFS('Bill Wise'!I:I,'Bill Wise'!C:C,B149,'Bill Wise'!H:H,"181-365 Days") -> 0 | O149: =SUMIFS('Bill Wise'!I:I,'Bill Wise'!C:C,B149,'Bill Wise'!H:H,"Above 365 Days") -> 0 | P149: =SUM(H149:O149) -> 866710 | Q149: =G149-P149 -> 0
A150: 145 | B150: Kamakhya Enterprises - Crs | C150: Aggregate | D150: Expenses | E150: Transport | G150: =IFERROR(SUMIFS(TB!C:C,TB!A:A,B150)-SUMIFS(TB!B:B,TB!A:A,B150),0) -> 899181 | H150: =SUMIFS('Bill Wise'!I:I,'Bill Wise'!C:C,B150,'Bill Wise'!H:H,"0-30 Days") -> 899181 | I150: =SUMIFS('Bill Wise'!I:I,'Bill Wise'!C:C,B150,'Bill Wise'!H:H,"31-60 Days") -> 0 | J150: =SUMIFS('Bill Wise'!I:I,'Bill Wise'!C:C,B150,'Bill Wise'!H:H,"61-90 Days") -> 0 | K150: =SUMIFS('Bill Wise'!I:I,'Bill Wise'!C:C,B150,'Bill Wise'!H:H,"91-120 Days") -> 0 | L150: =SUMIFS('Bill Wise'!I:I,'Bill Wise'!C:C,B150,'Bill Wise'!H:H,"121-150 Days") -> 0 | M150: =SUMIFS('Bill Wise'!I:I,'Bill Wise'!C:C,B150,'Bill Wise'!H:H,"151-180 Days") -> 0 | N150: =SUMIFS('Bill Wise'!I:I,'Bill Wise'!C:C,B150,'Bill Wise'!H:H,"181-365 Days") -> 0 | O150: =SUMIFS('Bill Wise'!I:I,'Bill Wise'!C:C,B150,'Bill Wise'!H:H,"Above 365 Days") -> 0 | P150: =SUM(H150:O150) -> 899181 | Q150: =G150-P150 -> 0
A151: 146 | B151: Premier Roadlines Ltd - Crs | C151: Gujarat | D151: Capex | E151: Capex | G151: =IFERROR(SUMIFS(TB!C:C,TB!A:A,B151)-SUMIFS(TB!B:B,TB!A:A,B151),0) -> 913160 | H151: =SUMIFS('Bill Wise'!I:I,'Bill Wise'!C:C,B151,'Bill Wise'!H:H,"0-30 Days") -> 0 | I151: =SUMIFS('Bill Wise'!I:I,'Bill Wise'!C:C,B151,'Bill Wise'!H:H,"31-60 Days") -> 0 | J151: =SUMIFS('Bill Wise'!I:I,'Bill Wise'!C:C,B151,'Bill Wise'!H:H,"61-90 Days") -> 0 | K151: =SUMIFS('Bill Wise'!I:I,'Bill Wise'!C:C,B151,'Bill Wise'!H:H,"91-120 Days") -> 0 | L151: =SUMIFS('Bill Wise'!I:I,'Bill Wise'!C:C,B151,'Bill Wise'!H:H,"121-150 Days") -> 0 | M151: =SUMIFS('Bill Wise'!I:I,'Bill Wise'!C:C,B151,'Bill Wise'!H:H,"151-180 Days") -> 0 | N151: =SUMIFS('Bill Wise'!I:I,'Bill Wise'!C:C,B151,'Bill Wise'!H:H,"181-365 Days") -> 0 | O151: =SUMIFS('Bill Wise'!I:I,'Bill Wise'!C:C,B151,'Bill Wise'!H:H,"Above 365 Days") -> 913160 | P151: =SUM(H151:O151) -> 913160 | Q151: =G151-P151 -> 0
A152: 147 | B152: BGR Constructions - Crs | C152: Nellore | D152: Transportation | E152: Transport | G152: =IFERROR(SUMIFS(TB!C:C,TB!A:A,B152)-SUMIFS(TB!B:B,TB!A:A,B152),0) -> 968310 | H152: =SUMIFS('Bill Wise'!I:I,'Bill Wise'!C:C,B152,'Bill Wise'!H:H,"0-30 Days") -> 558250 | I152: =SUMIFS('Bill Wise'!I:I,'Bill Wise'!C:C,B152,'Bill Wise'!H:H,"31-60 Days") -> 410060 | J152: =SUMIFS('Bill Wise'!I:I,'Bill Wise'!C:C,B152,'Bill Wise'!H:H,"61-90 Days") -> 0 | K152: =SUMIFS('Bill Wise'!I:I,'Bill Wise'!C:C,B152,'Bill Wise'!H:H,"91-120 Days") -> 0 | L152: =SUMIFS('Bill Wise'!I:I,'Bill Wise'!C:C,B152,'Bill Wise'!H:H,"121-150 Days") -> 0 | M152: =SUMIFS('Bill Wise'!I:I,'Bill Wise'!C:C,B152,'Bill Wise'!H:H,"151-180 Days") -> 0 | N152: =SUMIFS('Bill Wise'!I:I,'Bill Wise'!C:C,B152,'Bill Wise'!H:H,"181-365 Days") -> 0 | O152: =SUMIFS('Bill Wise'!I:I,'Bill Wise'!C:C,B152,'Bill Wise'!H:H,"Above 365 Days") -> 0 | P152: =SUM(H152:O152) -> 968310 | Q152: =G152-P152 -> 0
A153: 148 | B153: ROYAL ENGINEERING WORKS - Crs | C153: Howrah | D153: Capex | E153: Capex | G153: =IFERROR(SUMIFS(TB!C:C,TB!A:A,B153)-SUMIFS(TB!B:B,TB!A:A,B153),0) -> 979541.18 | H153: =SUMIFS('Bill Wise'!I:I,'Bill Wise'!C:C,B153,'Bill Wise'!H:H,"0-30 Days") -> 0 | I153: =SUMIFS('Bill Wise'!I:I,'Bill Wise'!C:C,B153,'Bill Wise'!H:H,"31-60 Days") -> 0 | J153: =SUMIFS('Bill Wise'!I:I,'Bill Wise'!C:C,B153,'Bill Wise'!H:H,"61-90 Days") -> 0 | K153: =SUMIFS('Bill Wise'!I:I,'Bill Wise'!C:C,B153,'Bill Wise'!H:H,"91-120 Days") -> 55639.03 | L153: =SUMIFS('Bill Wise'!I:I,'Bill Wise'!C:C,B153,'Bill Wise'!H:H,"121-150 Days") -> 923902.15 | M153: =SUMIFS('Bill Wise'!I:I,'Bill Wise'!C:C,B153,'Bill Wise'!H:H,"151-180 Days") -> 0 | N153: =SUMIFS('Bill Wise'!I:I,'Bill Wise'!C:C,B153,'Bill Wise'!H:H,"181-365 Days") -> 0 | O153: =SUMIFS('Bill Wise'!I:I,'Bill Wise'!C:C,B153,'Bill Wise'!H:H,"Above 365 Days") -> 0 | P153: =SUM(H153:O153) -> 979541.18 | Q153: =G153-P153 -> 0
A154: 149 | B154: SRL Group and Company - Crs | C154: Wada | D154: Expenses | E154: Transport | G154: =IFERROR(SUMIFS(TB!C:C,TB!A:A,B154)-SUMIFS(TB!B:B,TB!A:A,B154),0) -> 1013907.5 | H154: =SUMIFS('Bill Wise'!I:I,'Bill Wise'!C:C,B154,'Bill Wise'!H:H,"0-30 Days") -> 1013907.5 | I154: =SUMIFS('Bill Wise'!I:I,'Bill Wise'!C:C,B154,'Bill Wise'!H:H,"31-60 Days") -> 0 | J154: =SUMIFS('Bill Wise'!I:I,'Bill Wise'!C:C,B154,'Bill Wise'!H:H,"61-90 Days") -> 0 | K154: =SUMIFS('Bill Wise'!I:I,'Bill Wise'!C:C,B154,'Bill Wise'!H:H,"91-120 Days") -> 0 | L154: =SUMIFS('Bill Wise'!I:I,'Bill Wise'!C:C,B154,'Bill Wise'!H:H,"121-150 Days") -> 0 | M154: =SUMIFS('Bill Wise'!I:I,'Bill Wise'!C:C,B154,'Bill Wise'!H:H,"151-180 Days") -> 0 | N154: =SUMIFS('Bill Wise'!I:I,'Bill Wise'!C:C,B154,'Bill Wise'!H:H,"181-365 Days") -> 0 | O154: =SUMIFS('Bill Wise'!I:I,'Bill Wise'!C:C,B154,'Bill Wise'!H:H,"Above 365 Days") -> 0 | P154: =SUM(H154:O154) -> 1013907.5 | Q154: =G154-P154 -> 0
A155: 150 | B155: Vaishnavi Aggregates - Crs | C155: Telangana | D155: Expenses | E155: Sales promotion | G155: =IFERROR(SUMIFS(TB!C:C,TB!A:A,B155)-SUMIFS(TB!B:B,TB!A:A,B155),0) -> 1021155.3 | H155: =SUMIFS('Bill Wise'!I:I,'Bill Wise'!C:C,B155,'Bill Wise'!H:H,"0-30 Days") -> 0 | I155: =SUMIFS('Bill Wise'!I:I,'Bill Wise'!C:C,B155,'Bill Wise'!H:H,"31-60 Days") -> 1021155.3 | J155: =SUMIFS('Bill Wise'!I:I,'Bill Wise'!C:C,B155,'Bill Wise'!H:H,"61-90 Days") -> 0 | K155: =SUMIFS('Bill Wise'!I:I,'Bill Wise'!C:C,B155,'Bill Wise'!H:H,"91-120 Days") -> 0 | L155: =SUMIFS('Bill Wise'!I:I,'Bill Wise'!C:C,B155,'Bill Wise'!H:H,"121-150 Days") -> 0 | M155: =SUMIFS('Bill Wise'!I:I,'Bill Wise'!C:C,B155,'Bill Wise'!H:H,"151-180 Days") -> 0 | N155: =SUMIFS('Bill Wise'!I:I,'Bill Wise'!C:C,B155,'Bill Wise'!H:H,"181-365 Days") -> 0 | O155: =SUMIFS('Bill Wise'!I:I,'Bill Wise'!C:C,B155,'Bill Wise'!H:H,"Above 365 Days") -> 0 | P155: =SUM(H155:O155) -> 1021155.3 | Q155: =G155-P155 -> 0
A156: 151 | B156: INDIA INTERNATIONAL COMPANY - Crs | C156: Nagpur | D156: Expenses | E156: Store and spare | G156: =IFERROR(SUMIFS(TB!C:C,TB!A:A,B156)-SUMIFS(TB!B:B,TB!A:A,B156),0) -> 1035872 | H156: =SUMIFS('Bill Wise'!I:I,'Bill Wise'!C:C,B156,'Bill Wise'!H:H,"0-30 Days") -> 1035872 | I156: =SUMIFS('Bill Wise'!I:I,'Bill Wise'!C:C,B156,'Bill Wise'!H:H,"31-60 Days") -> 0 | J156: =SUMIFS('Bill Wise'!I:I,'Bill Wise'!C:C,B156,'Bill Wise'!H:H,"61-90 Days") -> 0 | K156: =SUMIFS('Bill Wise'!I:I,'Bill Wise'!C:C,B156,'Bill Wise'!H:H,"91-120 Days") -> 0 | L156: =SUMIFS('Bill Wise'!I:I,'Bill Wise'!C:C,B156,'Bill Wise'!H:H,"121-150 Days") -> 0 | M156: =SUMIFS('Bill Wise'!I:I,'Bill Wise'!C:C,B156,'Bill Wise'!H:H,"151-180 Days") -> 0 | N156: =SUMIFS('Bill Wise'!I:I,'Bill Wise'!C:C,B156,'Bill Wise'!H:H,"181-365 Days") -> 0 | O156: =SUMIFS('Bill Wise'!I:I,'Bill Wise'!C:C,B156,'Bill Wise'!H:H,"Above 365 Days") -> 0 | P156: =SUM(H156:O156) -> 1035872 | Q156: =G156-P156 -> 0
...

Sheet Advances
A1: Ultrafine Mineral & Admixtures Pvt. Ltd.
A2: Creditors – Advance Payments (Debit Balances) | As at 30-June-2026
B3: SUBTOTAL | G3: =SUBTOTAL(9,G5:G60) -> -44503459 | H3: =SUBTOTAL(9,H5:H60) -> -10773370 | I3: =SUBTOTAL(9,I5:I60) -> -257950.4 | J3: =SUBTOTAL(9,J5:J60) -> -1792541.6 | K3: =SUBTOTAL(9,K5:K60) -> -45000 | L3: =SUBTOTAL(9,L5:L60) -> -432782.7 | M3: =SUBTOTAL(9,M5:M60) -> -187920 | N3: =SUBTOTAL(9,N5:N60) -> -25658410 | ... Q3: =SUBTOTAL(9,Q5:Q60) -> 0
A4: # | B4: Vendor Name | C4: Location | D4: Vendor Type | E4: Vendor Sub Type | G4: TB Balance (Cr) | H4: 0-30 Days | I4: 31-60 Days | J4: 61-90 Days | K4: 91-120 Days | L4: 121-150 Days | M4: 151-180 Days | N4: 181-365 Days | O4: Above 365 Days | P4: BW Total | Q4: Diff (TB-BW)
H5: =SUMIFS('Bill Wise'!I:I,'Bill Wise'!C:C,B5,'Bill Wise'!H:H,"0-30 Days") -> 0 | I5: =SUMIFS('Bill Wise'!I:I,'Bill Wise'!C:C,B5,'Bill Wise'!H:H,"31-60 Days") -> 0 | J5: =SUMIFS('Bill Wise'!I:I,'Bill Wise'!C:C,B5,'Bill Wise'!H:H,"61-90 Days") -> 0 | K5: =SUMIFS('Bill Wise'!I:I,'Bill Wise'!C:C,B5,'Bill Wise'!H:H,"91-120 Days") -> 0 | L5: =SUMIFS('Bill Wise'!I:I,'Bill Wise'!C:C,B5,'Bill Wise'!H:H,"121-150 Days") -> 0 | M5: =SUMIFS('Bill Wise'!I:I,'Bill Wise'!C:C,B5,'Bill Wise'!H:H,"151-180 Days") -> 0 | N5: =SUMIFS('Bill Wise'!I:I,'Bill Wise'!C:C,B5,'Bill Wise'!H:H,"181-365 Days") -> 0 | O5: =SUMIFS('Bill Wise'!I:I,'Bill Wise'!C:C,B5,'Bill Wise'!H:H,"Above 365 Days") -> 0
A6: 1 | B6: Desai Cement Company Pvt Ltd-Crs | C6: Goa | D6: Expenses | E6: BG Incashed | G6: =IFERROR(SUMIFS(TB!C:C,TB!A:A,B6)-SUMIFS(TB!B:B,TB!A:A,B6),0) -> -13962953 | H6: =SUMIFS('Bill Wise'!I:I,'Bill Wise'!C:C,B6,'Bill Wise'!H:H,"0-30 Days") -> 0 | I6: =SUMIFS('Bill Wise'!I:I,'Bill Wise'!C:C,B6,'Bill Wise'!H:H,"31-60 Days") -> 0 | J6: =SUMIFS('Bill Wise'!I:I,'Bill Wise'!C:C,B6,'Bill Wise'!H:H,"61-90 Days") -> 0 | K6: =SUMIFS('Bill Wise'!I:I,'Bill Wise'!C:C,B6,'Bill Wise'!H:H,"91-120 Days") -> 0 | L6: =SUMIFS('Bill Wise'!I:I,'Bill Wise'!C:C,B6,'Bill Wise'!H:H,"121-150 Days") -> 0 | M6: =SUMIFS('Bill Wise'!I:I,'Bill Wise'!C:C,B6,'Bill Wise'!H:H,"151-180 Days") -> 0 | N6: =SUMIFS('Bill Wise'!I:I,'Bill Wise'!C:C,B6,'Bill Wise'!H:H,"181-365 Days") -> -13962953 | O6: =SUMIFS('Bill Wise'!I:I,'Bill Wise'!C:C,B6,'Bill Wise'!H:H,"Above 365 Days") -> 0 | P6: =SUM(H6:O6) -> -13962953 | Q6: =G6-P6 -> 0
A7: 2 | B7: Vedanta Limited (Goa) - Crs | C7: Goa | D7: Raw Material | E7: BG Issue | G7: =IFERROR(SUMIFS(TB!C:C,TB!A:A,B7)-SUMIFS(TB!B:B,TB!A:A,B7),0) -> -9481609.8 | H7: =SUMIFS('Bill Wise'!I:I,'Bill Wise'!C:C,B7,'Bill Wise'!H:H,"0-30 Days") -> 0 | I7: =SUMIFS('Bill Wise'!I:I,'Bill Wise'!C:C,B7,'Bill Wise'!H:H,"31-60 Days") -> 0 | J7: =SUMIFS('Bill Wise'!I:I,'Bill Wise'!C:C,B7,'Bill Wise'!H:H,"61-90 Days") -> 0 | K7: =SUMIFS('Bill Wise'!I:I,'Bill Wise'!C:C,B7,'Bill Wise'!H:H,"91-120 Days") -> 0 | L7: =SUMIFS('Bill Wise'!I:I,'Bill Wise'!C:C,B7,'Bill Wise'!H:H,"121-150 Days") -> 0 | M7: =SUMIFS('Bill Wise'!I:I,'Bill Wise'!C:C,B7,'Bill Wise'!H:H,"151-180 Days") -> 0 | N7: =SUMIFS('Bill Wise'!I:I,'Bill Wise'!C:C,B7,'Bill Wise'!H:H,"181-365 Days") -> -9481609.8 | O7: =SUMIFS('Bill Wise'!I:I,'Bill Wise'!C:C,B7,'Bill Wise'!H:H,"Above 365 Days") -> 0 | P7: =SUM(H7:O7) -> -9481609.8 | Q7: =G7-P7 -> 0
A8: 3 | B8: JAI Energy Giant Engineering and consultancy - Crs | C8: Nagpur | D8: Capex | E8: Capex Advance | G8: =IFERROR(SUMIFS(TB!C:C,TB!A:A,B8)-SUMIFS(TB!B:B,TB!A:A,B8),0) -> -4692357 | H8: =SUMIFS('Bill Wise'!I:I,'Bill Wise'!C:C,B8,'Bill Wise'!H:H,"0-30 Days") -> 0 | I8: =SUMIFS('Bill Wise'!I:I,'Bill Wise'!C:C,B8,'Bill Wise'!H:H,"31-60 Days") -> 0 | J8: =SUMIFS('Bill Wise'!I:I,'Bill Wise'!C:C,B8,'Bill Wise'!H:H,"61-90 Days") -> 0 | K8: =SUMIFS('Bill Wise'!I:I,'Bill Wise'!C:C,B8,'Bill Wise'!H:H,"91-120 Days") -> 0 | L8: =SUMIFS('Bill Wise'!I:I,'Bill Wise'!C:C,B8,'Bill Wise'!H:H,"121-150 Days") -> 0 | M8: =SUMIFS('Bill Wise'!I:I,'Bill Wise'!C:C,B8,'Bill Wise'!H:H,"151-180 Days") -> 0 | N8: =SUMIFS('Bill Wise'!I:I,'Bill Wise'!C:C,B8,'Bill Wise'!H:H,"181-365 Days") -> 0 | O8: =SUMIFS('Bill Wise'!I:I,'Bill Wise'!C:C,B8,'Bill Wise'!H:H,"Above 365 Days") -> -4692357 | P8: =SUM(H8:O8) -> -4692357 | Q8: =G8-P8 -> 0
A9: 4 | B9: Exalt Druk Enviroklens Pvt Ltd - Crs | C9: Haryana | D9: Trading | E9: Bhutan Vendor | G9: =IFERROR(SUMIFS(TB!C:C,TB!A:A,B9)-SUMIFS(TB!B:B,TB!A:A,B9),0) -> -2387615 | H9: =SUMIFS('Bill Wise'!I:I,'Bill Wise'!C:C,B9,'Bill Wise'!H:H,"0-30 Days") -> -2387615 | I9: =SUMIFS('Bill Wise'!I:I,'Bill Wise'!C:C,B9,'Bill Wise'!H:H,"31-60 Days") -> 0 | J9: =SUMIFS('Bill Wise'!I:I,'Bill Wise'!C:C,B9,'Bill Wise'!H:H,"61-90 Days") -> 0 | K9: =SUMIFS('Bill Wise'!I:I,'Bill Wise'!C:C,B9,'Bill Wise'!H:H,"91-120 Days") -> 0 | L9: =SUMIFS('Bill Wise'!I:I,'Bill Wise'!C:C,B9,'Bill Wise'!H:H,"121-150 Days") -> 0 | M9: =SUMIFS('Bill Wise'!I:I,'Bill Wise'!C:C,B9,'Bill Wise'!H:H,"151-180 Days") -> 0 | N9: =SUMIFS('Bill Wise'!I:I,'Bill Wise'!C:C,B9,'Bill Wise'!H:H,"181-365 Days") -> 0 | O9: =SUMIFS('Bill Wise'!I:I,'Bill Wise'!C:C,B9,'Bill Wise'!H:H,"Above 365 Days") -> 0 | P9: =SUM(H9:O9) -> -2387615 | Q9: =G9-P9 -> 0
A10: 5 | B10: Kinshar Metals - Crs | C10: Haryana | D10: Trading | E10: Bhutan Vendor | G10: =IFERROR(SUMIFS(TB!C:C,TB!A:A,B10)-SUMIFS(TB!B:B,TB!A:A,B10),0) -> -2374700 | H10: =SUMIFS('Bill Wise'!I:I,'Bill Wise'!C:C,B10,'Bill Wise'!H:H,"0-30 Days") -> -2374700 | I10: =SUMIFS('Bill Wise'!I:I,'Bill Wise'!C:C,B10,'Bill Wise'!H:H,"31-60 Days") -> 0 | J10: =SUMIFS('Bill Wise'!I:I,'Bill Wise'!C:C,B10,'Bill Wise'!H:H,"61-90 Days") -> 0 | K10: =SUMIFS('Bill Wise'!I:I,'Bill Wise'!C:C,B10,'Bill Wise'!H:H,"91-120 Days") -> 0 | L10: =SUMIFS('Bill Wise'!I:I,'Bill Wise'!C:C,B10,'Bill Wise'!H:H,"121-150 Days") -> 0 | M10: =SUMIFS('Bill Wise'!I:I,'Bill Wise'!C:C,B10,'Bill Wise'!H:H,"151-180 Days") -> 0 | N10: =SUMIFS('Bill Wise'!I:I,'Bill Wise'!C:C,B10,'Bill Wise'!H:H,"181-365 Days") -> 0 | O10: =SUMIFS('Bill Wise'!I:I,'Bill Wise'!C:C,B10,'Bill Wise'!H:H,"Above 365 Days") -> 0 | P10: =SUM(H10:O10) -> -2374700 | Q10: =G10-P10 -> 0
A11: 6 | B11: DOED JUNG KUEN PHEN TRADING HOUSE-CRS | C11: Haryana | D11: Trading | E11: Bhutan Vendor | G11: =IFERROR(SUMIFS(TB!C:C,TB!A:A,B11)-SUMIFS(TB!B:B,TB!A:A,B11),0) -> -1949646.5 | H11: =SUMIFS('Bill Wise'!I:I,'Bill Wise'!C:C,B11,'Bill Wise'!H:H,"0-30 Days") -> -1949646.5 | I11: =SUMIFS('Bill Wise'!I:I,'Bill Wise'!C:C,B11,'Bill Wise'!H:H,"31-60 Days") -> 0 | J11: =SUMIFS('Bill Wise'!I:I,'Bill Wise'!C:C,B11,'Bill Wise'!H:H,"61-90 Days") -> 0 | K11: =SUMIFS('Bill Wise'!I:I,'Bill Wise'!C:C,B11,'Bill Wise'!H:H,"91-120 Days") -> 0 | L11: =SUMIFS('Bill Wise'!I:I,'Bill Wise'!C:C,B11,'Bill Wise'!H:H,"121-150 Days") -> 0 | M11: =SUMIFS('Bill Wise'!I:I,'Bill Wise'!C:C,B11,'Bill Wise'!H:H,"151-180 Days") -> 0 | N11: =SUMIFS('Bill Wise'!I:I,'Bill Wise'!C:C,B11,'Bill Wise'!H:H,"181-365 Days") -> 0 | O11: =SUMIFS('Bill Wise'!I:I,'Bill Wise'!C:C,B11,'Bill Wise'!H:H,"Above 365 Days") -> 0 | P11: =SUM(H11:O11) -> -1949646.5 | Q11: =G11-P11 -> 0
A12: 7 | B12: Fourteckh Enviro India Pvt Ltd - Crs | C12: Gujarat | D12: Capex | E12: Capex Advance | G12: =IFERROR(SUMIFS(TB!C:C,TB!A:A,B12)-SUMIFS(TB!B:B,TB!A:A,B12),0) -> -1228000 | H12: =SUMIFS('Bill Wise'!I:I,'Bill Wise'!C:C,B12,'Bill Wise'!H:H,"0-30 Days") -> -1228000 | I12: =SUMIFS('Bill Wise'!I:I,'Bill Wise'!C:C,B12,'Bill Wise'!H:H,"31-60 Days") -> 0 | J12: =SUMIFS('Bill Wise'!I:I,'Bill Wise'!C:C,B12,'Bill Wise'!H:H,"61-90 Days") -> 0 | K12: =SUMIFS('Bill Wise'!I:I,'Bill Wise'!C:C,B12,'Bill Wise'!H:H,"91-120 Days") -> 0 | L12: =SUMIFS('Bill Wise'!I:I,'Bill Wise'!C:C,B12,'Bill Wise'!H:H,"121-150 Days") -> 0 | M12: =SUMIFS('Bill Wise'!I:I,'Bill Wise'!C:C,B12,'Bill Wise'!H:H,"151-180 Days") -> 0 | N12: =SUMIFS('Bill Wise'!I:I,'Bill Wise'!C:C,B12,'Bill Wise'!H:H,"181-365 Days") -> 0 | O12: =SUMIFS('Bill Wise'!I:I,'Bill Wise'!C:C,B12,'Bill Wise'!H:H,"Above 365 Days") -> 0 | P12: =SUM(H12:O12) -> -1228000 | Q12: =G12-P12 -> 0
A13: 8 | B13: M/s Macro Engineers-Crs | C13: Gujarat | D13: Expenses | E13: Stores and Spares | G13: =IFERROR(SUMIFS(TB!C:C,TB!A:A,B13)-SUMIFS(TB!B:B,TB!A:A,B13),0) -> -955800 | H13: =SUMIFS('Bill Wise'!I:I,'Bill Wise'!C:C,B13,'Bill Wise'!H:H,"0-30 Days") -> 0 | I13: =SUMIFS('Bill Wise'!I:I,'Bill Wise'!C:C,B13,'Bill Wise'!H:H,"31-60 Days") -> 0 | J13: =SUMIFS('Bill Wise'!I:I,'Bill Wise'!C:C,B13,'Bill Wise'!H:H,"61-90 Days") -> -955800 | K13: =SUMIFS('Bill Wise'!I:I,'Bill Wise'!C:C,B13,'Bill Wise'!H:H,"91-120 Days") -> 0 | L13: =SUMIFS('Bill Wise'!I:I,'Bill Wise'!C:C,B13,'Bill Wise'!H:H,"121-150 Days") -> 0 | M13: =SUMIFS('Bill Wise'!I:I,'Bill Wise'!C:C,B13,'Bill Wise'!H:H,"151-180 Days") -> 0 | N13: =SUMIFS('Bill Wise'!I:I,'Bill Wise'!C:C,B13,'Bill Wise'!H:H,"181-365 Days") -> 0 | O13: =SUMIFS('Bill Wise'!I:I,'Bill Wise'!C:C,B13,'Bill Wise'!H:H,"Above 365 Days") -> 0 | P13: =SUM(H13:O13) -> -955800 | Q13: =G13-P13 -> 0
A14: 9 | B14: Eurocem Additives Private Limited-Crs | C14: Head Office | D14: Capex | E14: Interest | G14: =IFERROR(SUMIFS(TB!C:C,TB!A:A,B14)-SUMIFS(TB!B:B,TB!A:A,B14),0) -> -714140 | H14: =SUMIFS('Bill Wise'!I:I,'Bill Wise'!C:C,B14,'Bill Wise'!H:H,"0-30 Days") -> 0 | I14: =SUMIFS('Bill Wise'!I:I,'Bill Wise'!C:C,B14,'Bill Wise'!H:H,"31-60 Days") -> 0 | J14: =SUMIFS('Bill Wise'!I:I,'Bill Wise'!C:C,B14,'Bill Wise'!H:H,"61-90 Days") -> -714140 | K14: =SUMIFS('Bill Wise'!I:I,'Bill Wise'!C:C,B14,'Bill Wise'!H:H,"91-120 Days") -> 0 | L14: =SUMIFS('Bill Wise'!I:I,'Bill Wise'!C:C,B14,'Bill Wise'!H:H,"121-150 Days") -> 0 | M14: =SUMIFS('Bill Wise'!I:I,'Bill Wise'!C:C,B14,'Bill Wise'!H:H,"151-180 Days") -> 0 | N14: =SUMIFS('Bill Wise'!I:I,'Bill Wise'!C:C,B14,'Bill Wise'!H:H,"181-365 Days") -> 0 | O14: =SUMIFS('Bill Wise'!I:I,'Bill Wise'!C:C,B14,'Bill Wise'!H:H,"Above 365 Days") -> 0 | P14: =SUM(H14:O14) -> -714140 | Q14: =G14-P14 -> 0
A15: 10 | B15: JASSPER SHIPPING INDIA LIMITED- CRS | C15: Goa | D15: Transportation | E15: GST Claim | G15: =IFERROR(SUMIFS(TB!C:C,TB!A:A,B15)-SUMIFS(TB!B:B,TB!A:A,B15),0) -> -653396 | H15: =SUMIFS('Bill Wise'!I:I,'Bill Wise'!C:C,B15,'Bill Wise'!H:H,"0-30 Days") -> 0 | I15: =SUMIFS('Bill Wise'!I:I,'Bill Wise'!C:C,B15,'Bill Wise'!H:H,"31-60 Days") -> 0 | J15: =SUMIFS('Bill Wise'!I:I,'Bill Wise'!C:C,B15,'Bill Wise'!H:H,"61-90 Days") -> 0 | K15: =SUMIFS('Bill Wise'!I:I,'Bill Wise'!C:C,B15,'Bill Wise'!H:H,"91-120 Days") -> 0 | L15: =SUMIFS('Bill Wise'!I:I,'Bill Wise'!C:C,B15,'Bill Wise'!H:H,"121-150 Days") -> 0 | M15: =SUMIFS('Bill Wise'!I:I,'Bill Wise'!C:C,B15,'Bill Wise'!H:H,"151-180 Days") -> 0 | N15: =SUMIFS('Bill Wise'!I:I,'Bill Wise'!C:C,B15,'Bill Wise'!H:H,"181-365 Days") -> -653396 | O15: =SUMIFS('Bill Wise'!I:I,'Bill Wise'!C:C,B15,'Bill Wise'!H:H,"Above 365 Days") -> 0 | P15: =SUM(H15:O15) -> -653396 | Q15: =G15-P15 -> 0
A16: 11 | B16: Steel & Power-CR (CAP) - Crs | C16: Gujarat | D16: Capex | E16: Capex Advance | G16: =IFERROR(SUMIFS(TB!C:C,TB!A:A,B16)-SUMIFS(TB!B:B,TB!A:A,B16),0) -> -650000 | H16: =SUMIFS('Bill Wise'!I:I,'Bill Wise'!C:C,B16,'Bill Wise'!H:H,"0-30 Days") -> 0 | I16: =SUMIFS('Bill Wise'!I:I,'Bill Wise'!C:C,B16,'Bill Wise'!H:H,"31-60 Days") -> 0 | J16: =SUMIFS('Bill Wise'!I:I,'Bill Wise'!C:C,B16,'Bill Wise'!H:H,"61-90 Days") -> 0 | K16: =SUMIFS('Bill Wise'!I:I,'Bill Wise'!C:C,B16,'Bill Wise'!H:H,"91-120 Days") -> 0 | L16: =SUMIFS('Bill Wise'!I:I,'Bill Wise'!C:C,B16,'Bill Wise'!H:H,"121-150 Days") -> 0 | M16: =SUMIFS('Bill Wise'!I:I,'Bill Wise'!C:C,B16,'Bill Wise'!H:H,"151-180 Days") -> 0 | N16: =SUMIFS('Bill Wise'!I:I,'Bill Wise'!C:C,B16,'Bill Wise'!H:H,"181-365 Days") -> 0 | O16: =SUMIFS('Bill Wise'!I:I,'Bill Wise'!C:C,B16,'Bill Wise'!H:H,"Above 365 Days") -> -650000 | P16: =SUM(H16:O16) -> -650000 | Q16: =G16-P16 -> 0
A17: 12 | B17: SHIVSHAKTI ENTERPRISES - Crs | C17: flyash | D17: Raw Material | E17: Advance With Vendor Invoice or Refund Required | G17: =IFERROR(SUMIFS(TB!C:C,TB!A:A,B17)-SUMIFS(TB!B:B,TB!A:A,B17),0) -> -649762.84 | H17: =SUMIFS('Bill Wise'!I:I,'Bill Wise'!C:C,B17,'Bill Wise'!H:H,"0-30 Days") -> 0 | I17: =SUMIFS('Bill Wise'!I:I,'Bill Wise'!C:C,B17,'Bill Wise'!H:H,"31-60 Days") -> 0 | J17: =SUMIFS('Bill Wise'!I:I,'Bill Wise'!C:C,B17,'Bill Wise'!H:H,"61-90 Days") -> 0 | K17: =SUMIFS('Bill Wise'!I:I,'Bill Wise'!C:C,B17,'Bill Wise'!H:H,"91-120 Days") -> 0 | L17: =SUMIFS('Bill Wise'!I:I,'Bill Wise'!C:C,B17,'Bill Wise'!H:H,"121-150 Days") -> 0 | M17: =SUMIFS('Bill Wise'!I:I,'Bill Wise'!C:C,B17,'Bill Wise'!H:H,"151-180 Days") -> 0 | N17: =SUMIFS('Bill Wise'!I:I,'Bill Wise'!C:C,B17,'Bill Wise'!H:H,"181-365 Days") -> -649762.84 | O17: =SUMIFS('Bill Wise'!I:I,'Bill Wise'!C:C,B17,'Bill Wise'!H:H,"Above 365 Days") -> 0 | P17: =SUM(H17:O17) -> -649762.84 | Q17: =G17-P17 -> 0
... A59: 55 | B59: Vinayak Oil Industries - Crs | C59: Nagpur | D59: Expenses | E59: Repair & Maintenance | G59: =IFERROR(SUMIFS(TB!C:C,TB!A:A,B59)-SUMIFS(TB!B:B,TB!A:A,B59),0) -> -0.58 | H59: =SUMIFS('Bill Wise'!I:I,'Bill Wise'!C:C,B59,'Bill Wise'!H:H,"0-30 Days") -> 0 | I59: =SUMIFS('Bill Wise'!I:I,'Bill Wise'!C:C,B59,'Bill Wise'!H:H,"31-60 Days") -> 0 | J59: =SUMIFS('Bill Wise'!I:I,'Bill Wise'!C:C,B59,'Bill Wise'!H:H,"61-90 Days") -> -0.58 | K59: =SUMIFS('Bill Wise'!I:I,'Bill Wise'!C:C,B59,'Bill Wise'!H:H,"91-120 Days") -> 0 | L59: =SUMIFS('Bill Wise'!I:I,'Bill Wise'!C:C,B59,'Bill Wise'!H:H,"121-150 Days") -> 0 | M59: =SUMIFS('Bill Wise'!I:I,'Bill Wise'!C:C,B59,'Bill Wise'!H:H,"151-180 Days") -> 0 | N59: =SUMIFS('Bill Wise'!I:I,'Bill Wise'!C:C,B59,'Bill Wise'!H:H,"181-365 Days") -> 0 | O59: =SUMIFS('Bill Wise'!I:I,'Bill Wise'!C:C,B59,'Bill Wise'!H:H,"Above 365 Days") -> 0 | P59: =SUM(H59:O59) -> -0.58 | Q59: =G59-P59 -> 0
B61: Grand Total | G61: =SUM(G4:G60) -> -44503459 | H61: =SUM(H4:H60) -> -10773370 | I61: =SUM(I4:I60) -> -257950.4 | J61: =SUM(J4:J60) -> -1792541.6 | K61: =SUM(K4:K60) -> -45000 | L61: =SUM(L4:L60) -> -432782.7 | M61: =SUM(M4:M60) -> -187920 | N61: =SUM(N4:N60) -> -25658410 | ... Q61: =SUM(Q4:Q60) -> 0

Sheet Intercompany
A1: Ultrafine Mineral & Admixtures Pvt. Ltd.
A2: Creditors Ageing Report - Intercompany & Special | As at 30-Jun-2026
B3: SUBTOTAL | E3: =SUBTOTAL(9,E5:E24) -> 1.306018e+08 | F3: =SUBTOTAL(9,F5:F24) -> 24335937 | G3: =SUBTOTAL(9,G5:G24) -> 2729956.6 | H3: =SUBTOTAL(9,H5:H24) -> 3836467.5 | I3: =SUBTOTAL(9,I5:I24) -> 29521126 | J3: =SUBTOTAL(9,J5:J24) -> 11584568 | K3: =SUBTOTAL(9,K5:K24) -> 862289.56 | L3: =SUBTOTAL(9,L5:L24) -> 39612486 | ... O3: =SUBTOTAL(9,O5:O24) -> 0
A4: # | B4: Vendor Name | C4: Vendor Type | E4: TB Balance (Cr) | F4: 0-30 Days | G4: 31-60 Days | H4: 61-90 Days | I4: 91-120 Days | J4: 121-150 Days | K4: 151-180 Days | L4: 181-365 Days | M4: Above 365 Days | N4: BW Total | O4: Diff (TB-BW)
A6: 1 | B6: RDC Concrete India Pvt. Ltd. Punjab - Crs | C6: Intercompany | E6: =IFERROR(SUMIFS(TB!C:C,TB!A:A,B6)-SUMIFS(TB!B:B,TB!A:A,B6),0) -> 30680 | F6: =SUMIFS('Bill Wise'!I:I,'Bill Wise'!C:C,B6,'Bill Wise'!H:H,"0-30 Days") -> 0 | G6: =SUMIFS('Bill Wise'!I:I,'Bill Wise'!C:C,B6,'Bill Wise'!H:H,"31-60 Days") -> 0 | H6: =SUMIFS('Bill Wise'!I:I,'Bill Wise'!C:C,B6,'Bill Wise'!H:H,"61-90 Days") -> 0 | I6: =SUMIFS('Bill Wise'!I:I,'Bill Wise'!C:C,B6,'Bill Wise'!H:H,"91-120 Days") -> 0 | J6: =SUMIFS('Bill Wise'!I:I,'Bill Wise'!C:C,B6,'Bill Wise'!H:H,"121-150 Days") -> 0 | K6: =SUMIFS('Bill Wise'!I:I,'Bill Wise'!C:C,B6,'Bill Wise'!H:H,"151-180 Days") -> 0 | L6: =SUMIFS('Bill Wise'!I:I,'Bill Wise'!C:C,B6,'Bill Wise'!H:H,"181-365 Days") -> 30680 | M6: =SUMIFS('Bill Wise'!I:I,'Bill Wise'!C:C,B6,'Bill Wise'!H:H,"Above 365 Days") -> 0 | N6: =SUM(F6:M6) -> 30680 | O6: =E6-N6 -> 0
A7: 2 | B7: RDC Concrete (India) Pvt Ltd (Bangalore)-Crs | C7: Intercompany | E7: =IFERROR(SUMIFS(TB!C:C,TB!A:A,B7)-SUMIFS(TB!B:B,TB!A:A,B7),0) -> 215334 | F7: =SUMIFS('Bill Wise'!I:I,'Bill Wise'!C:C,B7,'Bill Wise'!H:H,"0-30 Days") -> 0 | G7: =SUMIFS('Bill Wise'!I:I,'Bill Wise'!C:C,B7,'Bill Wise'!H:H,"31-60 Days") -> 0 | H7: =SUMIFS('Bill Wise'!I:I,'Bill Wise'!C:C,B7,'Bill Wise'!H:H,"61-90 Days") -> 0 | I7: =SUMIFS('Bill Wise'!I:I,'Bill Wise'!C:C,B7,'Bill Wise'!H:H,"91-120 Days") -> 0 | J7: =SUMIFS('Bill Wise'!I:I,'Bill Wise'!C:C,B7,'Bill Wise'!H:H,"121-150 Days") -> 0 | K7: =SUMIFS('Bill Wise'!I:I,'Bill Wise'!C:C,B7,'Bill Wise'!H:H,"151-180 Days") -> 0 | L7: =SUMIFS('Bill Wise'!I:I,'Bill Wise'!C:C,B7,'Bill Wise'!H:H,"181-365 Days") -> 215334 | M7: =SUMIFS('Bill Wise'!I:I,'Bill Wise'!C:C,B7,'Bill Wise'!H:H,"Above 365 Days") -> 0 | N7: =SUM(F7:M7) -> 215334 | O7: =E7-N7 -> 0
A8: 3 | B8: RDC Concrete (India) Pvt Ltd (Haryana)-Crs | C8: Intercompany | E8: =IFERROR(SUMIFS(TB!C:C,TB!A:A,B8)-SUMIFS(TB!B:B,TB!A:A,B8),0) -> 332760 | F8: =SUMIFS('Bill Wise'!I:I,'Bill Wise'!C:C,B8,'Bill Wise'!H:H,"0-30 Days") -> 0 | G8: =SUMIFS('Bill Wise'!I:I,'Bill Wise'!C:C,B8,'Bill Wise'!H:H,"31-60 Days") -> 0 | H8: =SUMIFS('Bill Wise'!I:I,'Bill Wise'!C:C,B8,'Bill Wise'!H:H,"61-90 Days") -> 0 | I8: =SUMIFS('Bill Wise'!I:I,'Bill Wise'!C:C,B8,'Bill Wise'!H:H,"91-120 Days") -> 332760 | J8: =SUMIFS('Bill Wise'!I:I,'Bill Wise'!C:C,B8,'Bill Wise'!H:H,"121-150 Days") -> 0 | K8: =SUMIFS('Bill Wise'!I:I,'Bill Wise'!C:C,B8,'Bill Wise'!H:H,"151-180 Days") -> 0 | L8: =SUMIFS('Bill Wise'!I:I,'Bill Wise'!C:C,B8,'Bill Wise'!H:H,"181-365 Days") -> 0 | M8: =SUMIFS('Bill Wise'!I:I,'Bill Wise'!C:C,B8,'Bill Wise'!H:H,"Above 365 Days") -> 0 | N8: =SUM(F8:M8) -> 332760 | O8: =E8-N8 -> 0
A9: 4 | B9: RDC Concrete India Pvt Ltd (NCR)-Crs | C9: Intercompany | E9: =IFERROR(SUMIFS(TB!C:C,TB!A:A,B9)-SUMIFS(TB!B:B,TB!A:A,B9),0) -> 370425.6 | F9: =SUMIFS('Bill Wise'!I:I,'Bill Wise'!C:C,B9,'Bill Wise'!H:H,"0-30 Days") -> 0 | G9: =SUMIFS('Bill Wise'!I:I,'Bill Wise'!C:C,B9,'Bill Wise'!H:H,"31-60 Days") -> 0 | H9: =SUMIFS('Bill Wise'!I:I,'Bill Wise'!C:C,B9,'Bill Wise'!H:H,"61-90 Days") -> 0 | I9: =SUMIFS('Bill Wise'!I:I,'Bill Wise'!C:C,B9,'Bill Wise'!H:H,"91-120 Days") -> 0 | J9: =SUMIFS('Bill Wise'!I:I,'Bill Wise'!C:C,B9,'Bill Wise'!H:H,"121-150 Days") -> 0 | K9: =SUMIFS('Bill Wise'!I:I,'Bill Wise'!C:C,B9,'Bill Wise'!H:H,"151-180 Days") -> 0 | L9: =SUMIFS('Bill Wise'!I:I,'Bill Wise'!C:C,B9,'Bill Wise'!H:H,"181-365 Days") -> 370425.6 | M9: =SUMIFS('Bill Wise'!I:I,'Bill Wise'!C:C,B9,'Bill Wise'!H:H,"Above 365 Days") -> 0 | N9: =SUM(F9:M9) -> 370425.6 | O9: =E9-N9 -> 0
A10: 5 | B10: RDC Concrete (India) Pvt Ltd (Pune)- Crs | C10: Intercompany | E10: =IFERROR(SUMIFS(TB!C:C,TB!A:A,B10)-SUMIFS(TB!B:B,TB!A:A,B10),0) -> 488346 | F10: =SUMIFS('Bill Wise'!I:I,'Bill Wise'!C:C,B10,'Bill Wise'!H:H,"0-30 Days") -> 0 | G10: =SUMIFS('Bill Wise'!I:I,'Bill Wise'!C:C,B10,'Bill Wise'!H:H,"31-60 Days") -> 0 | H10: =SUMIFS('Bill Wise'!I:I,'Bill Wise'!C:C,B10,'Bill Wise'!H:H,"61-90 Days") -> 0 | I10: =SUMIFS('Bill Wise'!I:I,'Bill Wise'!C:C,B10,'Bill Wise'!H:H,"91-120 Days") -> 0 | J10: =SUMIFS('Bill Wise'!I:I,'Bill Wise'!C:C,B10,'Bill Wise'!H:H,"121-150 Days") -> 235800 | K10: =SUMIFS('Bill Wise'!I:I,'Bill Wise'!C:C,B10,'Bill Wise'!H:H,"151-180 Days") -> 0 | L10: =SUMIFS('Bill Wise'!I:I,'Bill Wise'!C:C,B10,'Bill Wise'!H:H,"181-365 Days") -> 252546 | M10: =SUMIFS('Bill Wise'!I:I,'Bill Wise'!C:C,B10,'Bill Wise'!H:H,"Above 365 Days") -> 0 | N10: =SUM(F10:M10) -> 488346 | O10: =E10-N10 -> 0
A11: 6 | B11: RDC Concrete (India) Pvt Ltd (chattisgarh) - Crs | C11: Intercompany | E11: =IFERROR(SUMIFS(TB!C:C,TB!A:A,B11)-SUMIFS(TB!B:B,TB!A:A,B11),0) -> 590000 | F11: =SUMIFS('Bill Wise'!I:I,'Bill Wise'!C:C,B11,'Bill Wise'!H:H,"0-30 Days") -> 0 | G11: =SUMIFS('Bill Wise'!I:I,'Bill Wise'!C:C,B11,'Bill Wise'!H:H,"31-60 Days") -> 0 | H11: =SUMIFS('Bill Wise'!I:I,'Bill Wise'!C:C,B11,'Bill Wise'!H:H,"61-90 Days") -> 0 | I11: =SUMIFS('Bill Wise'!I:I,'Bill Wise'!C:C,B11,'Bill Wise'!H:H,"91-120 Days") -> 0 | J11: =SUMIFS('Bill Wise'!I:I,'Bill Wise'!C:C,B11,'Bill Wise'!H:H,"121-150 Days") -> 0 | K11: =SUMIFS('Bill Wise'!I:I,'Bill Wise'!C:C,B11,'Bill Wise'!H:H,"151-180 Days") -> 0 | L11: =SUMIFS('Bill Wise'!I:I,'Bill Wise'!C:C,B11,'Bill Wise'!H:H,"181-365 Days") -> 590000 | M11: =SUMIFS('Bill Wise'!I:I,'Bill Wise'!C:C,B11,'Bill Wise'!H:H,"Above 365 Days") -> 0 | N11: =SUM(F11:M11) -> 590000 | O11: =E11-N11 -> 0
A12: 7 | B12: NEPTUNE READYMIX CONCRETE.PVT.LTD - MUPPATHADOM - Crs | C12: Intercompany | E12: =IFERROR(SUMIFS(TB!C:C,TB!A:A,B12)-SUMIFS(TB!B:B,TB!A:A,B12),0) -> 708759.9 | F12: =SUMIFS('Bill Wise'!I:I,'Bill Wise'!C:C,B12,'Bill Wise'!H:H,"0-30 Days") -> 0 | G12: =SUMIFS('Bill Wise'!I:I,'Bill Wise'!C:C,B12,'Bill Wise'!H:H,"31-60 Days") -> 0 | H12: =SUMIFS('Bill Wise'!I:I,'Bill Wise'!C:C,B12,'Bill Wise'!H:H,"61-90 Days") -> 0 | I12: =SUMIFS('Bill Wise'!I:I,'Bill Wise'!C:C,B12,'Bill Wise'!H:H,"91-120 Days") -> 0 | J12: =SUMIFS('Bill Wise'!I:I,'Bill Wise'!C:C,B12,'Bill Wise'!H:H,"121-150 Days") -> 0 | K12: =SUMIFS('Bill Wise'!I:I,'Bill Wise'!C:C,B12,'Bill Wise'!H:H,"151-180 Days") -> 0 | L12: =SUMIFS('Bill Wise'!I:I,'Bill Wise'!C:C,B12,'Bill Wise'!H:H,"181-365 Days") -> 0 | M12: =SUMIFS('Bill Wise'!I:I,'Bill Wise'!C:C,B12,'Bill Wise'!H:H,"Above 365 Days") -> 708759.9 | N12: =SUM(F12:M12) -> 708759.9 | O12: =E12-N12 -> 0
A13: 8 | B13: Neptune Readymix Concrete Pvt. Ltd.(Cochin)-Vendor - Crs | C13: Intercompany | E13: =IFERROR(SUMIFS(TB!C:C,TB!A:A,B13)-SUMIFS(TB!B:B,TB!A:A,B13),0) -> 731051 | F13: =SUMIFS('Bill Wise'!I:I,'Bill Wise'!C:C,B13,'Bill Wise'!H:H,"0-30 Days") -> 0 | G13: =SUMIFS('Bill Wise'!I:I,'Bill Wise'!C:C,B13,'Bill Wise'!H:H,"31-60 Days") -> 0 | H13: =SUMIFS('Bill Wise'!I:I,'Bill Wise'!C:C,B13,'Bill Wise'!H:H,"61-90 Days") -> 0 | I13: =SUMIFS('Bill Wise'!I:I,'Bill Wise'!C:C,B13,'Bill Wise'!H:H,"91-120 Days") -> 0 | J13: =SUMIFS('Bill Wise'!I:I,'Bill Wise'!C:C,B13,'Bill Wise'!H:H,"121-150 Days") -> 0 | K13: =SUMIFS('Bill Wise'!I:I,'Bill Wise'!C:C,B13,'Bill Wise'!H:H,"151-180 Days") -> 0 | L13: =SUMIFS('Bill Wise'!I:I,'Bill Wise'!C:C,B13,'Bill Wise'!H:H,"181-365 Days") -> 0 | M13: =SUMIFS('Bill Wise'!I:I,'Bill Wise'!C:C,B13,'Bill Wise'!H:H,"Above 365 Days") -> 731051 | N13: =SUM(F13:M13) -> 731051 | O13: =E13-N13 -> 0
A14: 9 | B14: RDC Concrete (India) Pvt Ltd (Chennai)-Crs | C14: Intercompany | E14: =IFERROR(SUMIFS(TB!C:C,TB!A:A,B14)-SUMIFS(TB!B:B,TB!A:A,B14),0) -> 1612470 | F14: =SUMIFS('Bill Wise'!I:I,'Bill Wise'!C:C,B14,'Bill Wise'!H:H,"0-30 Days") -> 0 | G14: =SUMIFS('Bill Wise'!I:I,'Bill Wise'!C:C,B14,'Bill Wise'!H:H,"31-60 Days") -> 0 | H14: =SUMIFS('Bill Wise'!I:I,'Bill Wise'!C:C,B14,'Bill Wise'!H:H,"61-90 Days") -> 212400 | I14: =SUMIFS('Bill Wise'!I:I,'Bill Wise'!C:C,B14,'Bill Wise'!H:H,"91-120 Days") -> 637200 | J14: =SUMIFS('Bill Wise'!I:I,'Bill Wise'!C:C,B14,'Bill Wise'!H:H,"121-150 Days") -> 366390 | K14: =SUMIFS('Bill Wise'!I:I,'Bill Wise'!C:C,B14,'Bill Wise'!H:H,"151-180 Days") -> 0 | L14: =SUMIFS('Bill Wise'!I:I,'Bill Wise'!C:C,B14,'Bill Wise'!H:H,"181-365 Days") -> 396480 | M14: =SUMIFS('Bill Wise'!I:I,'Bill Wise'!C:C,B14,'Bill Wise'!H:H,"Above 365 Days") -> 0 | N14: =SUM(F14:M14) -> 1612470 | O14: =E14-N14 -> 0
A15: 10 | B15: RDC Concrete (India) Pvt Ltd (Gujarat)-Crs | C15: Intercompany | E15: =IFERROR(SUMIFS(TB!C:C,TB!A:A,B15)-SUMIFS(TB!B:B,TB!A:A,B15),0) -> 1675373.1 | F15: =SUMIFS('Bill Wise'!I:I,'Bill Wise'!C:C,B15,'Bill Wise'!H:H,"0-30 Days") -> 52259.17 | G15: =SUMIFS('Bill Wise'!I:I,'Bill Wise'!C:C,B15,'Bill Wise'!H:H,"31-60 Days") -> 1545263.4 | H15: =SUMIFS('Bill Wise'!I:I,'Bill Wise'!C:C,B15,'Bill Wise'!H:H,"61-90 Days") -> 0 | I15: =SUMIFS('Bill Wise'!I:I,'Bill Wise'!C:C,B15,'Bill Wise'!H:H,"91-120 Days") -> 0 | J15: =SUMIFS('Bill Wise'!I:I,'Bill Wise'!C:C,B15,'Bill Wise'!H:H,"121-150 Days") -> 0 | K15: =SUMIFS('Bill Wise'!I:I,'Bill Wise'!C:C,B15,'Bill Wise'!H:H,"151-180 Days") -> 0 | L15: =SUMIFS('Bill Wise'!I:I,'Bill Wise'!C:C,B15,'Bill Wise'!H:H,"181-365 Days") -> 77850.5 | M15: =SUMIFS('Bill Wise'!I:I,'Bill Wise'!C:C,B15,'Bill Wise'!H:H,"Above 365 Days") -> 0 | N15: =SUM(F15:M15) -> 1675373 | O15: =E15-N15 -> 0
A16: 11 | B16: RDC Concrete (India) Pvt Ltd (Telangana)- Crs | C16: Intercompany | E16: =IFERROR(SUMIFS(TB!C:C,TB!A:A,B16)-SUMIFS(TB!B:B,TB!A:A,B16),0) -> 5970378.5 | F16: =SUMIFS('Bill Wise'!I:I,'Bill Wise'!C:C,B16,'Bill Wise'!H:H,"0-30 Days") -> 1259087.8 | G16: =SUMIFS('Bill Wise'!I:I,'Bill Wise'!C:C,B16,'Bill Wise'!H:H,"31-60 Days") -> 0 | H16: =SUMIFS('Bill Wise'!I:I,'Bill Wise'!C:C,B16,'Bill Wise'!H:H,"61-90 Days") -> 317874.38 | I16: =SUMIFS('Bill Wise'!I:I,'Bill Wise'!C:C,B16,'Bill Wise'!H:H,"91-120 Days") -> 542348.64 | J16: =SUMIFS('Bill Wise'!I:I,'Bill Wise'!C:C,B16,'Bill Wise'!H:H,"121-150 Days") -> 690690 | K16: =SUMIFS('Bill Wise'!I:I,'Bill Wise'!C:C,B16,'Bill Wise'!H:H,"151-180 Days") -> 486622.5 | L16: =SUMIFS('Bill Wise'!I:I,'Bill Wise'!C:C,B16,'Bill Wise'!H:H,"181-365 Days") -> 2673755.2 | M16: =SUMIFS('Bill Wise'!I:I,'Bill Wise'!C:C,B16,'Bill Wise'!H:H,"Above 365 Days") -> 0 | N16: =SUM(F16:M16) -> 5970378.5 | O16: =E16-N16 -> 0
A17: 12 | B17: SOCIAM EQUIPMENT SOLUTIONS PRIVATE LIMITED-CRS | C17: Intercompany | E17: =IFERROR(SUMIFS(TB!C:C,TB!A:A,B17)-SUMIFS(TB!B:B,TB!A:A,B17),0) -> 8743681.8 | F17: =SUMIFS('Bill Wise'!I:I,'Bill Wise'!C:C,B17,'Bill Wise'!H:H,"0-30 Days") -> 825920 | G17: =SUMIFS('Bill Wise'!I:I,'Bill Wise'!C:C,B17,'Bill Wise'!H:H,"31-60 Days") -> 0 | H17: =SUMIFS('Bill Wise'!I:I,'Bill Wise'!C:C,B17,'Bill Wise'!H:H,"61-90 Days") -> 412960 | I17: =SUMIFS('Bill Wise'!I:I,'Bill Wise'!C:C,B17,'Bill Wise'!H:H,"91-120 Days") -> 412960 | J17: =SUMIFS('Bill Wise'!I:I,'Bill Wise'!C:C,B17,'Bill Wise'!H:H,"121-150 Days") -> 825920 | K17: =SUMIFS('Bill Wise'!I:I,'Bill Wise'!C:C,B17,'Bill Wise'!H:H,"151-180 Days") -> 0 | L17: =SUMIFS('Bill Wise'!I:I,'Bill Wise'!C:C,B17,'Bill Wise'!H:H,"181-365 Days") -> 4736361.8 | M17: =SUMIFS('Bill Wise'!I:I,'Bill Wise'!C:C,B17,'Bill Wise'!H:H,"Above 365 Days") -> 1529560 | N17: =SUM(F17:M17) -> 8743681.8 | O17: =E17-N17 -> 0
... A22: 17 | B22: RDC Concrete (India) Pvt Ltd (Kolkata)-Crs | C22: Intercompany | E22: =IFERROR(SUMIFS(TB!C:C,TB!A:A,B22)-SUMIFS(TB!B:B,TB!A:A,B22),0) -> 35275916 | F22: =SUMIFS('Bill Wise'!I:I,'Bill Wise'!C:C,B22,'Bill Wise'!H:H,"0-30 Days") -> 3772858.3 | G22: =SUMIFS('Bill Wise'!I:I,'Bill Wise'!C:C,B22,'Bill Wise'!H:H,"31-60 Days") -> 1184693.2 | H22: =SUMIFS('Bill Wise'!I:I,'Bill Wise'!C:C,B22,'Bill Wise'!H:H,"61-90 Days") -> 492909.6 | I22: =SUMIFS('Bill Wise'!I:I,'Bill Wise'!C:C,B22,'Bill Wise'!H:H,"91-120 Days") -> 19935746 | J22: =SUMIFS('Bill Wise'!I:I,'Bill Wise'!C:C,B22,'Bill Wise'!H:H,"121-150 Days") -> 1410688.8 | K22: =SUMIFS('Bill Wise'!I:I,'Bill Wise'!C:C,B22,'Bill Wise'!H:H,"151-180 Days") -> 0 | L22: =SUMIFS('Bill Wise'!I:I,'Bill Wise'!C:C,B22,'Bill Wise'!H:H,"181-365 Days") -> 8479019.6 | M22: =SUMIFS('Bill Wise'!I:I,'Bill Wise'!C:C,B22,'Bill Wise'!H:H,"Above 365 Days") -> 0 | N22: =SUM(F22:M22) -> 35275916 | O22: =E22-N22 -> 0
B25: Grand Total | E25: =SUM(E4:E24) -> 1.306018e+08 | F25: =SUM(F4:F24) -> 24335937 | G25: =SUM(G4:G24) -> 2729956.6 | H25: =SUM(H4:H24) -> 3836467.5 | I25: =SUM(I4:I24) -> 29521126 | J25: =SUM(J4:J24) -> 11584568 | K25: =SUM(K4:K24) -> 862289.56 | L25: =SUM(L4:L24) -> 39612486 | ... O25: =SUM(O4:O24) -> 0
