Workbook

Sheet TB
A1: ULTRAFINE MINERAL & ADMIXTURES PVT LTD (HAY)
A2: 1516/907/2/1, RDC CONCRETE INDIA PRIVATE LIMITED,
A3: BEHRAMPUR ROAD, KHANDSA , GURGAON, Gurugram, Haryana
A4: UDYAM : UDYAM-MH-20-0007365 (Small/Mfgr)
A5: CIN: U24100MH2020PTC338575
A6: Contact : +91-
A7: Sundry Creditors
A8: Group Summary
A9: 1-Apr-26 to 31-Jul-26 | B9: =SUBTOTAL(9,B12:B255) -> 45031978 | C9: =SUBTOTAL(9,C12:C255) -> 2.7896965e+08
A10: PARTICULAR | B10: Closing Balance
B11: Debit | C11: Credit
A12: A. Abdul Hameed - Crs | C12: 225000
A13: Aadhya Shakti Enterprise-Crs | C13: 106912.12
A14: Abhay Dongare - Employee | B14: 7148
A15: Abhay Singh-Employee | B15: 4484
A16: ACE HIMALAYAN FERRO ALLOYS PRIVATE LIMITED - CRS | B16: 94000
A17: ADHUNIK TRASNPORT ORGANISATION LIMITED - Crs | C17: 104939.38
A18: ADVITA POLYCRAFT LLP - Crs | C18: 731548.93
A19: Agile Innotech - Crs | C19: 11328
A20: AI INDUSTRIAL SOLUTIONS-Crs | C20: 29854
A21: AIRMAX AUTOMATION - CRS | C21: 35913.4
A22: Akash Body Bildders-CRS | C22: 300000.02
A23: AMBUJA CEMENTS LIMITED -Crs | C23: 9642007.8
A24: Ankush Chavan- Employee | B24: 15000
A25: Arcelormittal Nippon Steel India Limited - Crs | B25: 531569.86
A26: ARKAY LOGISTICS-Crs | C26: 837826.02
A27: Arya CS - Crs | C27: 3000
A28: ASHCONNECT GLOBAL TRADING Pvt Ltd- Crs | C28: 8980658.6
A29: Ashish Kumar (Patna) - Employee | C29: 139597
A30: ASHOKA BUILDCON LIMITED-Crs | B30: 163127.04
A31: Ashvarya Kumar Verma-Employee | B31: 23510
A32: Asl Logistics Private Limited-Crs | C32: 9139346.2
A33: AVENGERS SECURITY SERVICES-CR | C33: 33434.68
A34: BAHUBALI CHEMICAL INDUSTRIES-CRS | C34: 6562298.2
A35: Balram Kumar Chakrawarti - Employee | C35: 413424
A36: Bandu Naik - Employee | B36: 187504
A37: Best Electro Mech-Crs | C37: 9762.76
A38: BGR Constructions - Crs | C38: 807940
A39: Bhamra Transport - Crs | C39: 311205.16
A40: Bhandari Automobiles Pvt Ltd - Crs | C40: 9150
A41: Bharat Engineering - Crs | C41: 503912
A42: Bharti Airtel Limited - Crs | C42: 64940.1
A43: BHARTIBEN SATISHBHAI PATEL-CR | C43: 8000
A44: BHUMAN ENTERPRISE-Crs | C44: 1331796.1
A45: Bhushan Deshpande - Employee | B45: 17998
A46: Bipin Jadhav Guest House - Crs | C46: 4500
A47: BISWAJIT RUI DAS - Crs | C47: 64334.88
A48: BN Trading and Transport Company-Cr | C48: 495364.28
A49: BOMMI SUNEEL KUMAR-Employee | B49: 25000
A50: B Stone Product - Crs | C50: 47027.5
A51: CB SURATWALA AND SONS-CRS | C51: 7167
A52: Chettinad Cement Corporation Private Limited - Crs | C52: 5614023.6
A53: Chukha Ferro Alloys Pvt Ltd- Crs | C53: 32191.76
A54: CJ DARCL Logistics Limited-Crs | C54: 3978034.4
A55: C K Paul Gas Agency - Crs | B55: 0.25
A56: Connect Residuary Pvt Ltd - Crs | C56: 3.48
A57: Csrl-Structwel Lab (Pune) Private Limited Crs | C57: 3933
A58: CtrlP Solutions Private Limited - Crs | C58: 700
A59: Dattakrupa Minerals - Crs | C59: 0.2
A60: DEEP ENTERPRISES-CRS | C60: 3000
A61: Desai Cement Company Pvt Ltd-Crs | B61: 13962953
A62: Devanand B. Singh - Employee | C62: 756000
A63: DEVENDRA CHAUHAN REFRACTORY WORKS -CRS | C63: 43200
A64: Dev Security Services- Crs | C64: 113558
A65: Dextrose Technologies Private Limited - Crs | C65: 4830.49
A66: Digambar A. Naik - Crs | B66: 29669.94
A67: D.K. SERVICES - Crs | C67: 45611.2
A68: Dmk Logistic - Crs | C68: 465366.71
A69: DOED JUNG KUEN PHEN TRADING HOUSE-CRS | C69: 220864.5
A70: Dokania Purushottam - Crs | C70: 0.5
A71: Dutta Auto Centre | C71: 36049.4
A72: Eon Infotech Ltd - Crs | C72: 74026.68
A73: ETC POOL - Crs | B73: 7000
A74: Eurocem Additives Private Limited-Crs | B74: 2714140
A75: Exalt Druk Enviroklens Pvt Ltd - Crs | B75: 2687615
A76: FAITH INFRA-CRS | C76: 601162.9
A77: FIRDOSH ERUCH ICHHAPORIA-Crs | C77: 20000
A78: First Choice Logistics-Crs | C78: 153802.5
A79: Fourteckh Enviro India Pvt Ltd - Crs | B79: 2884000
A80: Ganesh Trading & Industries LLP - Crs | C80: 1800000
A81: Gautam Trading Company -Crs | C81: 9801.08
A82: G D Packaging - Crs | C82: 137428
A83: Harish Ludhani - Employee | C83: 974095.2
A84: Harrier Security Services Private Limited-Crs | C84: 60336.57
A85: Harsh Raj - EMPLOYEE | B85: 4421
A86: HDFC IOCL CREDIT CARD | C86: 1699664
A87: Hella Infra Market Limited-Crs | C87: 13773300
A88: H R Industries - Crs | B88: 19032.8
A89: INDIA INTERNATIONAL COMPANY - Crs | C89: 2322864
A90: Indian Oil Corporation Limited - Crs | B90: 195874.65
A91: Info Tech Computers - Crs | C91: 924.16
A92: Jai Bhairunath | C92: 10856
A93: JAI Energy Giant Engineering and consultancy - Crs | B93: 4692357
A94: JANTA CEMENT INDUSTRIES-Crs | C94: 279918.46
A95: JASSPER SHIPPING INDIA LIMITED- CRS | B95: 653396
A96: JFC Logistics - Crs | C96: 1691845.6
A97: Jhuman Bagdi- Crs | C97: 6000
A98: JINDAL POWER LIMITED-Crs | C98: 249687
A99: JINENDRA AUTO PARTS-Crs | C99: 10091
A100: Joshi Dharmarajan Andezath - Employee | C100: 150000
...

Sheet Bill Wise
A1: Date | B1: Ref. No. | C1: Party's Name | D1: Cost Center/Location | E1: Ageing Bucket | F1: Pending (abs) | G1: Signed Amount
A2: 44357 | B2: CHN/2122/00447 | C2: Neptune Readymix Concrete Pvt. Ltd.(Cochin)-Vendor - Crs | D2: Bangalore | E2: Above 365 Days | F2: 85567 | G2: 85567
A3: 44361 | B3: CHN/2122/00452 | C3: Neptune Readymix Concrete Pvt. Ltd.(Cochin)-Vendor - Crs | D3: Bangalore | E3: Above 365 Days | F3: 62940 | G3: 62940
A4: 44383 | B4: CHN/2122/00448 | C4: Neptune Readymix Concrete Pvt. Ltd.(Cochin)-Vendor - Crs | D4: Bangalore | E4: Above 365 Days | F4: 78182 | G4: 78182
A5: 44400 | B5: CHN/2122/00453 | C5: Neptune Readymix Concrete Pvt. Ltd.(Cochin)-Vendor - Crs | D5: Bangalore | E5: Above 365 Days | F5: 73765 | G5: 73765
A6: 44456 | B6: CHN/2122/00543 | C6: Neptune Readymix Concrete Pvt. Ltd.(Cochin)-Vendor - Crs | D6: Bangalore | E6: Above 365 Days | F6: 74180 | G6: 74180
A7: 44473 | B7: CHN/2122/00547 | C7: Neptune Readymix Concrete Pvt. Ltd.(Cochin)-Vendor - Crs | D7: Bangalore | E7: Above 365 Days | F7: 92865 | G7: 92865
A8: 44488 | B8: CHN/2122/00548 | C8: Neptune Readymix Concrete Pvt. Ltd.(Cochin)-Vendor - Crs | D8: Bangalore | E8: Above 365 Days | F8: 71512 | G8: 71512
A9: 44493 | B9: CHN/2122/00560 | C9: Neptune Readymix Concrete Pvt. Ltd.(Cochin)-Vendor - Crs | D9: Bangalore | E9: Above 365 Days | F9: 15314 | G9: 15314
A10: 44500 | B10: CHN/2122/00562 | C10: Neptune Readymix Concrete Pvt. Ltd.(Cochin)-Vendor - Crs | D10: Bangalore | E10: Above 365 Days | F10: 81842 | G10: 81842
A11: 44535 | B11: CHN/2122/00579 | C11: Neptune Readymix Concrete Pvt. Ltd.(Cochin)-Vendor - Crs | D11: Bangalore | E11: Above 365 Days | F11: 19959 | G11: 19959
A12: 44545 | B12: CHN/21-22/00577 | C12: NEPTUNE READYMIX CONCRETE.PVT.LTD - MUPPATHADOM - Crs | D12: Bangalore | E12: Above 365 Days | F12: 72416 | G12: 72416
A13: 44546 | B13: CHN/21-22/00578 | C13: NEPTUNE READYMIX CONCRETE.PVT.LTD - MUPPATHADOM - Crs | D13: Bangalore | E13: Above 365 Days | F13: 56484 | G13: 56484
... A75: 45594 | B75: LSPL/24-25/400 | C75: Lub Solutions Pvt Ltd - Crs | D75: Goa | E75: Above 365 Days | F75: 786935 | G75: 786935
A76: 45692 | B76: 509 | C76: ASHOKA BUILDCON LIMITED-Crs | E76: Above 365 Days | F76: 13127.04 | G76: -13127.04
A77: 45722 | B77: 1750246755 | C77: SOCIAM EQUIPMENT SOLUTIONS PRIVATE LIMITED-CRS | D77: Gujarat | E77: Above 365 Days | F77: 819787.64 | G77: 819787.64
A78: 45747 | B78: WEET/RDC/024 | C78: Well Erectors Of Engineering Technology Private Limited - Crs | E78: Above 365 Days | F78: 819292.57 | G78: 819292.57
A79: 45777 | B79: JV/HO/2526/0009 | C79: RDC Concrete (India) Pvt Ltd (Head Office) - Crs | D79: Head Office | E79: Above 365 Days | F79: 1736215 | G79: 1736215
A80: 45798 | B80: 20KGRL/2025-26 | C80: KGR Logistics - Crs | D80: wada | E80: Above 365 Days | F80: 0.7 | G80: 0.7
A81: 45806 | B81: 038 | C81: SREERAMA INDUSTRIES PRIVATE LIMITED-Crs | D81: Vizag | E81: Above 365 Days | F81: 172046 | G81: 172046
A82: 45808 | B82: JV/HO/2526/0024 | C82: RDC Concrete (India) Pvt Ltd (Head Office) - Crs | D82: Head Office | E82: Above 365 Days | F82: 834281.26 | G82: 834281.26
A83: 45811 | B83: 027 | C83: Dattakrupa Minerals - Crs | D83: Goa | E83: Above 365 Days | F83: 0.2 | G83: 0.2
A84: 45812 | B84: PV/GUJ/2526/0123 | C84: Steel & Power-CR (CAP) - Crs | E84: Above 365 Days | F84: 300000 | G84: -300000
A85: 45813 | B85: 190 | C85: SULTAN ENTERPRISES-CRS | E85: Above 365 Days | F85: 110487.82 | G85: 110487.82
A86: 45814 | B86: 189 | C86: SULTAN ENTERPRISES-CRS | E86: Above 365 Days | F86: 100716 | G86: 100716
A87: 45818 | B87: 191 | C87: SULTAN ENTERPRISES-CRS | E87: Above 365 Days | F87: 106677.9 | G87: 106677.9
A88: 45825 | B88: 192 | C88: SULTAN ENTERPRISES-CRS | E88: Above 365 Days | F88: 108055.5 | G88: 108055.5
A89: 45826 | B89: Ash/12 | C89: ASHCONNECT GLOBAL TRADING Pvt Ltd- Crs | D89: flyash | E89: Above 365 Days | F89: 64759.02 | G89: 64759.02
A90: 45838 | B90: ASH/13 | C90: ASHCONNECT GLOBAL TRADING Pvt Ltd- Crs | E90: Above 365 Days | F90: 246403.27 | G90: 246403.27
A91: 45838 | B91: 2KL25ARMN10 | C91: RDC Concrete (India) Pvt Ltd (Kolkata)-Crs | D91: Panagarh (Aggregate) WB | E91: Above 365 Days | F91: 2972863.7 | G91: 2972863.7
A92: 45838 | B92: 2KL25ARMN12 | C92: RDC Concrete (India) Pvt Ltd (Kolkata)-Crs | D92: Gujarat | E92: Above 365 Days | F92: 1276850.8 | G92: 1276850.8
A93: 45839 | B93: JV/HO/2526/0073 | C93: RDC Concrete (India) Pvt Ltd (Head Office) - Crs | E93: Above 365 Days | F93: 740750 | G93: 740750
A94: 45839 | B94: JV/GUJ/2526/0038 | C94: SHIVSHAKTI ENTERPRISES - Crs | E94: Above 365 Days | F94: 649762.84 | G94: -649762.84
A95: 45858 | B95: Ash/15 | C95: ASHCONNECT GLOBAL TRADING Pvt Ltd- Crs | E95: Above 365 Days | F95: 99570 | G95: 99570
A96: 45863 | B96: Ash/16 | C96: ASHCONNECT GLOBAL TRADING Pvt Ltd- Crs | D96: flyash | E96: Above 365 Days | F96: 150479 | G96: 150479
A97: 45869 | B97: HM27/2526/069328 | C97: Hella Infra Market Limited-Crs | E97: 181-365 Days | F97: 1214662.7 | G97: 1214662.7
A98: 45869 | B98: JV/HO/2526/0070 | C98: RDC Concrete (India) Pvt Ltd (Head Office) - Crs | E98: 181-365 Days | F98: 821726.7 | G98: 821726.7
A99: 45869 | B99: 2KL25ARMN18 | C99: RDC Concrete (India) Pvt Ltd (Kolkata)-Crs | E99: 181-365 Days | F99: 540132.83 | G99: 540132.83
A100: 45869 | B100: 13HY25ARMN18 | C100: RDC Concrete (India) Pvt Ltd (Telangana)- Crs | E100: 181-365 Days | F100: 78487.5 | G100: 78487.5
A101: 45869 | B101: SRLGOA013/25-26 | C101: SRL Group and Company - Crs | D101: wada | E101: 181-365 Days | F101: 200928.42 | G101: 200928.42
A102: 45874 | B102: 1CH25ARMN126 | C102: RDC Concrete (India) Pvt Ltd (Chennai)-Crs | E102: 181-365 Days | F102: 23600 | G102: 23600
A103: 45889 | B103: SE/27/2526/00182 | C103: SOCIAM EQUIPMENT SOLUTIONS PRIVATE LIMITED-CRS | E103: 181-365 Days | F103: 297042 | G103: 297042
A104: 45891 | B104: Ash/21 | C104: ASHCONNECT GLOBAL TRADING Pvt Ltd- Crs | E104: 181-365 Days | F104: 148183.88 | G104: 148183.88
A105: 45900 | B105: Ash/22 | C105: ASHCONNECT GLOBAL TRADING Pvt Ltd- Crs | E105: 181-365 Days | F105: 315051.48 | G105: 315051.48
A106: 45900 | B106: JV/HO/2526/0085 | C106: RDC Concrete (India) Pvt Ltd (Head Office) - Crs | E106: 181-365 Days | F106: 836447.59 | G106: 836447.59
A107: 45900 | B107: 2KL25ARMN56 | C107: RDC Concrete (India) Pvt Ltd (Kolkata)-Crs | E107: 181-365 Days | F107: 470229.2 | G107: 470229.2
A108: 45900 | B108: 3KL25ARMN17 | C108: RDC Concrete (India) Pvt Ltd (Kolkata)-Crs | E108: 181-365 Days | F108: 371831.28 | G108: 371831.28
A109: 45900 | B109: 13HY25ARMN19 | C109: RDC Concrete (India) Pvt Ltd (Telangana)- Crs | E109: 181-365 Days | F109: 39243.75 | G109: 39243.75
A110: 45900 | B110: WEET/RDC/026 | C110: Well Erectors Of Engineering Technology Private Limited - Crs | E110: 181-365 Days | F110: 474690.06 | G110: 474690.06
A111: 45901 | B111: SKA/ULT/0625/001 | C111: SOCIAM EQUIPMENT SOLUTIONS PRIVATE LIMITED-CRS | E111: 181-365 Days | F111: 516200 | G111: 516200
A112: 45902 | B112: SKA/ULT/0625/002 | C112: SOCIAM EQUIPMENT SOLUTIONS PRIVATE LIMITED-CRS | E112: 181-365 Days | F112: 1032400 | G112: 1032400
A113: 45903 | B113: 92 | C113: BAHUBALI CHEMICAL INDUSTRIES-CRS | D113: Gujarat | E113: 181-365 Days | F113: 359676 | G113: 359676
A114: 45904 | B114: SE/29/2526/00146 | C114: SOCIAM EQUIPMENT SOLUTIONS PRIVATE LIMITED-CRS | E114: 181-365 Days | F114: 516200 | G114: 516200
A115: 45905 | B115: SE/29/2526/00181 | C115: SOCIAM EQUIPMENT SOLUTIONS PRIVATE LIMITED-CRS | E115: 181-365 Days | F115: 516199.76 | G115: 516199.76
A116: 45906 | B116: 95 | C116: BAHUBALI CHEMICAL INDUSTRIES-CRS | E116: 181-365 Days | F116: 333716 | G116: 333716
A117: 45909 | B117: 99 | C117: BAHUBALI CHEMICAL INDUSTRIES-CRS | E117: 181-365 Days | F117: 353965 | G117: 353965
A118: 45919 | B118: PV/WBA/2526/0170 | C118: ASHOKA BUILDCON LIMITED-Crs | E118: 181-365 Days | F118: 150000 | G118: -150000
A119: 45919 | B119: PV/WBA/2526/0156 | C119: M/s Manuwar Shaikh (Crusher)- Crs | E119: 181-365 Days | F119: 600000 | G119: -600000
A120: 45929 | B120: 13HY25ARMN23 | C120: RDC Concrete (India) Pvt Ltd (Telangana)- Crs | E120: 181-365 Days | F120: 78487.5 | G120: 78487.5
A121: 45930 | B121: 6CH25ARMN109 | C121: RDC Concrete (India) Pvt Ltd (Chennai)-Crs | E121: 181-365 Days | F121: 63720 | G121: 63720
A122: 45930 | B122: JV/HO/2526/0099 | C122: RDC Concrete (India) Pvt Ltd (Head Office) - Crs | E122: 181-365 Days | F122: 927486 | G122: 927486
A123: 45930 | B123: 3KL25ARMN26 | C123: RDC Concrete (India) Pvt Ltd (Kolkata)-Crs | E123: 181-365 Days | F123: 311495.64 | G123: 311495.64
A124: 45930 | B124: 2KL25ARMN86 | C124: RDC Concrete (India) Pvt Ltd (Kolkata)-Crs | E124: 181-365 Days | F124: 470229.6 | G124: 470229.6
A125: 45930 | B125: 13HY25ARMN22 | C125: RDC Concrete (India) Pvt Ltd (Telangana)- Crs | E125: 181-365 Days | F125: 180521.26 | G125: 180521.26
... A178: 45993 | B178: 132 | C178: BAHUBALI CHEMICAL INDUSTRIES-CRS | E178: 181-365 Days | F178: 322293 | G178: 322293
A179: 46000 | B179: 72_04.12.2025 | C179: P A Steel and Co - Crs | D179: Nagpur | E179: 181-365 Days | F179: 231733 | G179: 231733
A180: 46000 | B180: 13HY25ARMN36 | C180: RDC Concrete (India) Pvt Ltd (Telangana)- Crs | E180: 181-365 Days | F180: 78487.5 | G180: 78487.5
A181: 46002 | B181: 139 | C181: BAHUBALI CHEMICAL INDUSTRIES-CRS | E181: 181-365 Days | F181: 334624 | G181: 334624
A182: 46007 | B182: 13HY25ARMN39 | C182: RDC Concrete (India) Pvt Ltd (Telangana)- Crs | E182: 181-365 Days | F182: 78487.5 | G182: 78487.5
A183: 46009 | B183: 145 | C183: BAHUBALI CHEMICAL INDUSTRIES-CRS | D183: wada | E183: 181-365 Days | F183: 329432 | G183: 329432
A184: 46011 | B184: 13HY25ARMN40 | C184: RDC Concrete (India) Pvt Ltd (Telangana)- Crs | E184: 181-365 Days | F184: 47092.5 | G184: 47092.5
A185: 46020 | B185: A150 | C185: BAHUBALI CHEMICAL INDUSTRIES-CRS | E185: 181-365 Days | F185: 403418 | G185: 403418
A186: 46020 | B186: JV/MHN/2526/0111 | C186: RDC Concrete (India) Pvt Ltd (Head Office) - Crs | E186: 181-365 Days | F186: 5000000 | G186: 5000000
A187: 46020 | B187: 13HY25ARMN41 | C187: RDC Concrete (India) Pvt Ltd (Telangana)- Crs | E187: 181-365 Days | F187: 156975 | G187: 156975
A188: 46020 | B188: 13HY25ARMN42 | C188: RDC Concrete (India) Pvt Ltd (Telangana)- Crs | E188: 181-365 Days | F188: 78487.5 | G188: 78487.5
A189: 46022 | B189: Ash/29 | C189: ASHCONNECT GLOBAL TRADING Pvt Ltd- Crs | E189: 181-365 Days | F189: 413287.38 | G189: 413287.38
A190: 46022 | B190: Ash/28 | C190: ASHCONNECT GLOBAL TRADING Pvt Ltd- Crs | E190: 181-365 Days | F190: 258691.14 | G190: 258691.14
A191: 46022 | B191: 1CH25ARMN212 | C191: RDC Concrete (India) Pvt Ltd (Chennai)-Crs | E191: 181-365 Days | F191: 42480 | G191: 42480
A192: 46022 | B192: 1CH25ARMN227 | C192: RDC Concrete (India) Pvt Ltd (Chennai)-Crs | E192: 181-365 Days | F192: 42480 | G192: 42480
A193: 46022 | B193: 1CH25ARMN242 | C193: RDC Concrete (India) Pvt Ltd (Chennai)-Crs | E193: 181-365 Days | F193: 42480 | G193: 42480
A194: 46022 | B194: JV/HO/2526/0174 | C194: RDC Concrete (India) Pvt Ltd (Head Office) - Crs | E194: 181-365 Days | F194: 985730 | G194: 985730
A195: 46022 | B195: 3KL25ARMN46 | C195: RDC Concrete (India) Pvt Ltd (Kolkata)-Crs | E195: 181-365 Days | F195: 375991.9 | G195: 375991.9
... A221: 46026 | B221: 154 | C221: BAHUBALI CHEMICAL INDUSTRIES-CRS | E221: 181-365 Days | F221: 462607 | G221: 462607
A222: 46031 | B222: 156 | C222: BAHUBALI CHEMICAL INDUSTRIES-CRS | D222: Gujarat | E222: 181-365 Days | F222: 346566 | G222: 346566
A223: 46032 | B223: MT/042/25-26 | C223: Mollick Tube- Crs | D223: Panagarh (Aggregate) WB | E223: 181-365 Days | F223: 186261.3 | G223: 186261.3
A224: 46037 | B224: PV/GUJ/2526/0752 | C224: Bandu Naik - Employee | D224: Gujarat | E224: 181-365 Days | F224: 177504 | G224: -177504
A225: 46039 | B225: 13HY25ARMN46 | C225: RDC Concrete (India) Pvt Ltd (Telangana)- Crs | E225: 181-365 Days | F225: 486622.5 | G225: 486622.5
A226: 46053 | B226: Ash/32 | C226: ASHCONNECT GLOBAL TRADING Pvt Ltd- Crs | E226: 181-365 Days | F226: 165277.82 | G226: 165277.82
A227: 46053 | B227: Ash/31 | C227: ASHCONNECT GLOBAL TRADING Pvt Ltd- Crs | E227: 181-365 Days | F227: 109589.03 | G227: 109589.03
A228: 46053 | B228: Ash/30 | C228: ASHCONNECT GLOBAL TRADING Pvt Ltd- Crs | E228: 181-365 Days | F228: 157489.53 | G228: 157489.53
A229: 46053 | B229: Ash/33 | C229: ASHCONNECT GLOBAL TRADING Pvt Ltd- Crs | E229: 181-365 Days | F229: 103573 | G229: 103573
A230: 46053 | B230: SM/CON/25-26/7 | C230: M/S SHAKTI MACHINERY & MILL STORE-CRS | D230: Panagarh (Microsilica) WB | E230: 181-365 Days | F230: 944848.72 | G230: 944848.72
A231: 46053 | B231: 6CH25ARMN147 | C231: RDC Concrete (India) Pvt Ltd (Chennai)-Crs | E231: 181-365 Days | F231: 42480 | G231: 42480
A232: 46053 | B232: JV/HO/2526/0196 | C232: RDC Concrete (India) Pvt Ltd (Head Office) - Crs | E232: 181-365 Days | F232: 1015478 | G232: 1015478
A233: 46053 | B233: 2KL25ARMN189 | C233: RDC Concrete (India) Pvt Ltd (Kolkata)-Crs | E233: 181-365 Days | F233: 470229.6 | G233: 470229.6
A234: 46053 | B234: 2KL25ARMN139 | C234: RDC Concrete (India) Pvt Ltd (Kolkata)-Crs | E234: 181-365 Days | F234: 470229.6 | G234: 470229.6
A235: 46053 | B235: 13HY25ARMN48 | C235: RDC Concrete (India) Pvt Ltd (Telangana)- Crs | E235: 181-365 Days | F235: 235462.5 | G235: 235462.5
A236: 46053 | B236: 13HY25ARMN49 | C236: RDC Concrete (India) Pvt Ltd (Telangana)- Crs | E236: 181-365 Days | F236: 62790 | G236: 62790
A237: 46053 | B237: SE/29/2526/00359 | C237: SOCIAM EQUIPMENT SOLUTIONS PRIVATE LIMITED-CRS | E237: 181-365 Days | F237: 412960 | G237: 412960
A238: 46053 | B238: 696 | C238: SULTAN ENTERPRISES-CRS | E238: 181-365 Days | F238: 114935.62 | G238: 114935.62
...

Sheet Only Creditors
A1: Ultrafine Mineral & Admixtures Pvt. Ltd.
A2: Creditors Ageing Report | As at 31-July-2026
B3: SUBTOTAL | F3: =SUM(F5:F181) -> 32848614 | G3: =SUM(G5:G181) -> 1.3927462e+08 | H3: =SUM(H5:H181) -> 18364455 | I3: =SUM(I5:I181) -> 1.5763908e+08 | J3: =SUM(J5:J181) -> 65610551 | K3: =SUM(K5:K181) -> 34399226 | L3: =SUM(L5:L181) -> 17886604 | M3: =SUM(M5:M181) -> 6813919.8 | ... S3: =SUM(S5:S181) -> 660.95
A4: # | B4: Vendor Name | C4: Location | D4: Vendor Type | E4: Vendor Sub Type | F4: above 120 days | G4: As of 10-08-2026 | H4: Paid in August | I4: TB Balance (Cr) | J4: 0-30 Days | K4: 31-60 Days | L4: 61-90 Days | M4: 91-120 Days | N4: 121-150 Days | O4: 151-180 Days | P4: 181-365 Days | Q4: Above 365 Days | R4: BW Total | S4: Diff (TB-BW)
A5: 1 | B5: A. Abdul Hameed - Crs | C5: Goa | D5: Expenses | E5: Professional Fees | F5: =SUM(N5:Q5) -> 0 | G5: =I5-H5 -> 0 | H5: =SUMIF(Payments!$D$4:$D$117,'Only Creditors'!B5,Payments!$E$4:$E$130) -> 225000 | I5: 225000 | J5: 225000 | K5: 0 | L5: 0 | M5: 0 | N5: 0 | O5: 0 | P5: 0 | Q5: 0 | R5: 225000 | S5: 0
A6: 2 | B6: ADHUNIK TRASNPORT ORGANISATION LIMITED - Crs | C6: Galsi | D6: Transportation | E6: Transport | F6: =SUM(N6:Q6) -> 0 | G6: =I6-H6 -> 104939.38 | H6: =SUMIF(Payments!$D$4:$D$117,'Only Creditors'!B6,Payments!$E$4:$E$130) -> 0 | I6: 104939.38 | J6: 24500 | K6: 0 | L6: 80439.38 | M6: 0 | N6: 0 | O6: 0 | P6: 0 | Q6: 0 | R6: 104939.38 | S6: 0
A7: 3 | B7: ADVITA POLYCRAFT LLP - Crs | C7: Wada | D7: Expenses | E7: Store and spare | F7: =SUM(N7:Q7) -> 0 | G7: =I7-H7 -> 731548.93 | H7: =SUMIF(Payments!$D$4:$D$117,'Only Creditors'!B7,Payments!$E$4:$E$130) -> 0 | I7: 731548.93 | J7: 277304 | K7: 454244.93 | L7: 0 | M7: 0 | N7: 0 | O7: 0 | P7: 0 | Q7: 0 | R7: 731548.93 | S7: 0
A8: 4 | B8: AI INDUSTRIAL SOLUTIONS-Crs | C8: Wada | D8: Expenses | E8: Store and spare | F8: =SUM(N8:Q8) -> 0 | G8: =I8-H8 -> 29854 | H8: =SUMIF(Payments!$D$4:$D$117,'Only Creditors'!B8,Payments!$E$4:$E$130) -> 0 | I8: 29854 | J8: 29854 | K8: 0 | L8: 0 | M8: 0 | N8: 0 | O8: 0 | P8: 0 | Q8: 0 | R8: 29854 | S8: 0
A9: 5 | B9: AIRMAX AUTOMATION - CRS | C9: Wada | D9: Expenses | E9: Store and spare | F9: To be paid | G9: =I9-H9 -> 35913.4 | H9: =SUMIF(Payments!$D$4:$D$117,'Only Creditors'!B9,Payments!$E$4:$E$130) -> 0 | I9: 35913.4 | J9: 0 | K9: 0 | L9: 35913.4 | M9: 0 | N9: 0 | O9: 0 | P9: 0 | Q9: 0 | R9: 35913.4 | S9: 0
A10: 6 | B10: AMBUJA CEMENTS LIMITED -Crs | C10: flyash | D10: Trading | E10: Flyash | F10: =SUM(N10:Q10) -> 0 | G10: =I10-H10 -> 8637609.4 | H10: =SUMIF(Payments!$D$4:$D$117,'Only Creditors'!B10,Payments!$E$4:$E$130) -> 1004398.3 | I10: 9642007.8 | J10: 5766835.1 | K10: 3875172.7 | L10: 0 | M10: 0 | N10: 0 | O10: 0 | P10: 0 | Q10: 0 | R10: 9642007.8 | S10: 0
A11: 7 | B11: ARKAY LOGISTICS-Crs | C11: flyash | D11: Trading | E11: Flyash | F11: =SUM(N11:Q11) -> 0 | G11: =I11-H11 -> 837826.02 | H11: =SUMIF(Payments!$D$4:$D$117,'Only Creditors'!B11,Payments!$E$4:$E$130) -> 0 | I11: 837826.02 | J11: 479696.2 | K11: 358129.82 | L11: 0 | M11: 0 | N11: 0 | O11: 0 | P11: 0 | Q11: 0 | R11: 837826.02 | S11: 0
A12: 8 | B12: ASHCONNECT GLOBAL TRADING Pvt Ltd- Crs | C12: flyash | D12: Trading | E12: Flyash | F12: =SUM(N12:Q12) -> 6960958 | G12: =I12-H12 -> 8419447.3 | H12: =SUMIF(Payments!$D$4:$D$117,'Only Creditors'!B12,Payments!$E$4:$E$130) -> 561211.29 | I12: 8980658.6 | J12: 340769.77 | K12: 697265.26 | L12: 529460.71 | M12: 452204.79 | N12: 1885930.5 | O12: 1621868.9 | P12: 2891947.3 | Q12: 561211.29 | R12: 8980658.6 | S12: 0
A13: 9 | B13: AVENGERS SECURITY SERVICES-CR | C13: Nellore | D13: Expenses | E13: Security charges | F13: =SUM(N13:Q13) -> 0 | G13: =I13-H13 -> 33434.68 | H13: =SUMIF(Payments!$D$4:$D$117,'Only Creditors'!B13,Payments!$E$4:$E$130) -> 0 | I13: 33434.68 | J13: 33434.68 | K13: 0 | L13: 0 | M13: 0 | N13: 0 | O13: 0 | P13: 0 | Q13: 0 | R13: 33434.68 | S13: 0
A14: 10 | B14: Aadhya Shakti Enterprise-Crs | C14: Gujarat | D14: Transportation | E14: Transport | F14: =SUM(N14:Q14) -> 0 | G14: =I14-H14 -> 106912.12 | H14: =SUMIF(Payments!$D$4:$D$117,'Only Creditors'!B14,Payments!$E$4:$E$130) -> 0 | I14: 106912.12 | J14: 106912.12 | K14: 0 | L14: 0 | M14: 0 | N14: 0 | O14: 0 | P14: 0 | Q14: 0 | R14: 106912.12 | S14: 0
A15: 11 | B15: Agile Innotech - Crs | C15: Aggregate | D15: Expenses | E15: Office Exps | F15: To be paid | G15: =I15-H15 -> 0 | H15: =SUMIF(Payments!$D$4:$D$117,'Only Creditors'!B15,Payments!$E$4:$E$130) -> 11328 | I15: 11328 | J15: 11328 | K15: 0 | L15: 0 | M15: 0 | N15: 0 | O15: 0 | P15: 0 | Q15: 0 | R15: 11328 | S15: 0
A16: 12 | B16: Akash Body Bildders-CRS | C16: Aggregate | D16: Transportation | E16: Transport | F16: =SUM(N16:Q16) -> 300000.02 | G16: =I16-H16 -> 300000.02 | H16: =SUMIF(Payments!$D$4:$D$117,'Only Creditors'!B16,Payments!$E$4:$E$130) -> 0 | I16: 300000.02 | J16: 0 | K16: 0 | L16: 0 | M16: 0 | N16: 0 | O16: 0 | P16: 300000.02 | Q16: 0 | R16: 300000.02 | S16: 0
A17: 13 | B17: Arya CS - Crs | C17: Nagpur | D17: Expenses | E17: Guest House Rent | F17: To be paid | G17: =I17-H17 -> 3000 | H17: =SUMIF(Payments!$D$4:$D$117,'Only Creditors'!B17,Payments!$E$4:$E$130) -> 0 | I17: 3000 | J17: 3000 | K17: 0 | L17: 0 | M17: 0 | N17: 0 | O17: 0 | P17: 0 | Q17: 0 | R17: 3000 | S17: 0
A18: 14 | B18: Ashish Kumar (Patna) - Employee | C18: Patna | D18: Employee | E18: Employee | F18: =SUM(N18:Q18) -> 0 | G18: =I18-H18 -> 139597 | H18: =SUMIF(Payments!$D$4:$D$117,'Only Creditors'!B18,Payments!$E$4:$E$130) -> 0 | I18: 139597 | J18: 139597 | K18: 0 | L18: 0 | M18: 0 | N18: 0 | O18: 0 | P18: 0 | Q18: 0 | R18: 139597 | S18: 0
A19: 15 | B19: Asl Logistics Private Limited-Crs | C19: Gujarat | D19: Transportation | E19: Transport | F19: =SUM(N19:Q19) -> 0 | G19: =I19-H19 -> 8364610.1 | H19: =SUMIF(Payments!$D$4:$D$117,'Only Creditors'!B19,Payments!$E$4:$E$130) -> 774736.17 | I19: 9139346.2 | J19: 2782951.5 | K19: 2726848.2 | L19: 2054810.2 | M19: 1574736.2 | N19: 0 | O19: 0 | P19: 0 | Q19: 0 | R19: 9139346.2 | S19: 0
A20: 16 | B20: B Stone Product - Crs | C20: Aggregate | D20: Raw Material | E20: Aggregate | F20: =SUM(N20:Q20) -> 0 | G20: =I20-H20 -> 47027.5 | H20: =SUMIF(Payments!$D$4:$D$117,'Only Creditors'!B20,Payments!$E$4:$E$130) -> 0 | I20: 47027.5 | J20: 47068 | K20: 0 | L20: -40.5 | M20: 0 | N20: 0 | O20: 0 | P20: 0 | Q20: 0 | R20: 47027.5 | S20: 0
A21: 17 | B21: BAHUBALI CHEMICAL INDUSTRIES-CRS | C21: Bangalore | D21: Trading | E21: Microsilica | F21: =SUM(N21:Q21) -> 6562298.2 | G21: =I21-H21 -> 6562298.2 | H21: =SUMIF(Payments!$D$4:$D$117,'Only Creditors'!B21,Payments!$E$4:$E$130) -> 0 | I21: 6562298.2 | J21: 0 | K21: 0 | L21: 0 | M21: 0 | N21: 0 | O21: 832278 | P21: 5730020.2 | Q21: 0 | R21: 6562298.2 | S21: 0
A22: 18 | B22: BGR Constructions - Crs | C22: Nellore | D22: Transportation | E22: Transport | F22: =SUM(N22:Q22) -> 0 | G22: =I22-H22 -> 807940 | H22: =SUMIF(Payments!$D$4:$D$117,'Only Creditors'!B22,Payments!$E$4:$E$130) -> 0 | I22: 807940 | J22: 249690 | K22: 558250 | L22: 0 | M22: 0 | N22: 0 | O22: 0 | P22: 0 | Q22: 0 | R22: 807940 | S22: 0
A23: 19 | B23: BHARTIBEN SATISHBHAI PATEL-CR | C23: Gujarat | D23: Expenses | E23: Guest House Rent | F23: =SUM(N23:Q23) -> 0 | G23: =I23-H23 -> 0 | H23: =SUMIF(Payments!$D$4:$D$117,'Only Creditors'!B23,Payments!$E$4:$E$130) -> 8000 | I23: 8000 | J23: 8000 | K23: 0 | L23: 0 | M23: 0 | N23: 0 | O23: 0 | P23: 0 | Q23: 0 | R23: 8000 | S23: 0
A24: 20 | B24: BHUMAN ENTERPRISE-Crs | C24: Microsilica | D24: Raw Material | E24: Aggregate | F24: =SUM(N24:Q24) -> 0 | G24: =I24-H24 -> 1331796.1 | H24: =SUMIF(Payments!$D$4:$D$117,'Only Creditors'!B24,Payments!$E$4:$E$130) -> 0 | I24: 1331796.1 | J24: 441449.15 | K24: 890347 | L24: 0 | M24: 0 | N24: 0 | O24: 0 | P24: 0 | Q24: 0 | R24: 1331796.1 | S24: 0
A25: 21 | B25: BISWAJIT RUI DAS - Crs | C25: Microsilica | D25: Expenses | E25: Transport | F25: To be paid | G25: =I25-H25 -> 28072 | H25: =SUMIF(Payments!$D$4:$D$117,'Only Creditors'!B25,Payments!$E$4:$E$130) -> 36262.88 | I25: 64334.88 | J25: 28072 | K25: 36262.88 | L25: 0 | M25: 0 | N25: 0 | O25: 0 | P25: 0 | Q25: 0 | R25: 64334.88 | S25: 0
A26: 22 | B26: BN Trading and Transport Company-Cr | C26: Gujarat | D26: Transportation | E26: Transport | F26: =SUM(N26:Q26) -> 0 | G26: =I26-H26 -> 495364.28 | H26: =SUMIF(Payments!$D$4:$D$117,'Only Creditors'!B26,Payments!$E$4:$E$130) -> 0 | I26: 495364.28 | J26: 152876.4 | K26: 342487.88 | L26: 0 | M26: 0 | N26: 0 | O26: 0 | P26: 0 | Q26: 0 | R26: 495364.28 | S26: 0
A27: 23 | B27: Balram Kumar Chakrawarti - Employee | C27: Vizag | D27: Employee | E27: Employee | F27: =SUM(N27:Q27) -> 0 | G27: =I27-H27 -> 0 | H27: =SUMIF(Payments!$D$4:$D$117,'Only Creditors'!B27,Payments!$E$4:$E$130) -> 413424 | I27: 413424 | J27: 413424 | K27: 0 | L27: 0 | M27: 0 | N27: 0 | O27: 0 | P27: 0 | Q27: 0 | R27: 413424 | S27: 0
A28: 24 | B28: Best Electro Mech-Crs | C28: Wada | D28: Expenses | E28: Store and spare | F28: =SUM(N28:Q28) -> 0 | G28: =I28-H28 -> 9762.76 | H28: =SUMIF(Payments!$D$4:$D$117,'Only Creditors'!B28,Payments!$E$4:$E$130) -> 0 | I28: 9762.76 | J28: 9762.76 | K28: 0 | L28: 0 | M28: 0 | N28: 0 | O28: 0 | P28: 0 | Q28: 0 | R28: 9762.76 | S28: 0
A29: 25 | B29: Bhamra Transport - Crs | C29: flyash | D29: Expenses | E29: Transport | F29: =SUM(N29:Q29) -> 0 | G29: =I29-H29 -> 311205.16 | H29: =SUMIF(Payments!$D$4:$D$117,'Only Creditors'!B29,Payments!$E$4:$E$130) -> 0 | I29: 311205.16 | J29: 311205.16 | K29: 0 | L29: 0 | M29: 0 | N29: 0 | O29: 0 | P29: 0 | Q29: 0 | R29: 311205.16 | S29: 0
A30: 26 | B30: Bhandari Automobiles Pvt Ltd - Crs | C30: Aggregate | D30: Expenses | E30: Vehicle Exps | F30: To be paid | G30: =I30-H30 -> 0 | H30: =SUMIF(Payments!$D$4:$D$117,'Only Creditors'!B30,Payments!$E$4:$E$130) -> 9150 | I30: 9150 | J30: 0 | K30: 9150 | L30: 0 | M30: 0 | N30: 0 | O30: 0 | P30: 0 | Q30: 0 | R30: 9150 | S30: 0
A31: 27 | B31: Bharat Engineering - Crs | C31: Gujarat | D31: Expenses | E31: Store and spare | F31: =SUM(N31:Q31) -> 0 | G31: =I31-H31 -> 503912 | H31: =SUMIF(Payments!$D$4:$D$117,'Only Creditors'!B31,Payments!$E$4:$E$130) -> 0 | I31: 503912 | J31: 541762 | K31: -37850 | L31: 0 | M31: 0 | N31: 0 | O31: 0 | P31: 0 | Q31: 0 | R31: 503912 | S31: 0
A32: 28 | B32: Bharti Airtel Limited - Crs | C32: Gujarat | D32: Expenses | E32: Office Exps | F32: To be paid | G32: =I32-H32 -> 64940.1 | H32: =SUMIF(Payments!$D$4:$D$117,'Only Creditors'!B32,Payments!$E$4:$E$130) -> 0 | I32: 64940.1 | J32: 64940.1 | K32: 0 | L32: 0 | M32: 0 | N32: 0 | O32: 0 | P32: 0 | Q32: 0 | R32: 64940.1 | S32: 0
A33: 29 | B33: Bipin Jadhav Guest House - Crs | C33: Nagpur | D33: Expenses | E33: Guest House Rent | F33: To be paid | G33: =I33-H33 -> 4500 | H33: =SUMIF(Payments!$D$4:$D$117,'Only Creditors'!B33,Payments!$E$4:$E$130) -> 0 | I33: 4500 | J33: 4500 | K33: 0 | L33: 0 | M33: 0 | N33: 0 | O33: 0 | P33: 0 | Q33: 0 | R33: 4500 | S33: 0
A34: 30 | B34: CB SURATWALA AND SONS-CRS | C34: Gujarat | D34: Expenses | E34: Professional Fees | F34: =SUM(N34:Q34) -> 0 | G34: =I34-H34 -> 7167 | H34: =SUMIF(Payments!$D$4:$D$117,'Only Creditors'!B34,Payments!$E$4:$E$130) -> 0 | I34: 7167 | J34: 7167 | K34: 0 | L34: 0 | M34: 0 | N34: 0 | O34: 0 | P34: 0 | Q34: 0 | R34: 7167 | S34: 0
A35: 31 | B35: CJ DARCL Logistics Limited-Crs | C35: Nellore | D35: Transportation | E35: Transport | F35: =SUM(N35:Q35) -> 2052620 | G35: =I35-H35 -> 3978034.4 | H35: =SUMIF(Payments!$D$4:$D$117,'Only Creditors'!B35,Payments!$E$4:$E$130) -> 0 | I35: 3978034.4 | J35: 409480 | K35: 617885.6 | L35: 781468.8 | M35: 116580 | N35: 646700 | O35: 1405920 | P35: 0 | Q35: 0 | R35: 3978034.4 | S35: 0
A36: 32 | B36: Chettinad Cement Corporation Private Limited - Crs | C36: Vizag | D36: Raw Material | E36: GGBS | F36: =SUM(N36:Q36) -> 0 | G36: =I36-H36 -> 5058891.6 | H36: =SUMIF(Payments!$D$4:$D$117,'Only Creditors'!B36,Payments!$E$4:$E$130) -> 555132 | I36: 5614023.6 | J36: 3105090.6 | K36: 2508933 | L36: 0 | M36: 0 | N36: 0 | O36: 0 | P36: 0 | Q36: 0 | R36: 5614023.6 | S36: 0
A37: 33 | B37: Chukha Ferro Alloys Pvt Ltd- Crs | C37: Haryana | D37: Trading | E37: Bhutan Vendor | F37: To be paid | G37: =I37-H37 -> 32191.76 | H37: =SUMIF(Payments!$D$4:$D$117,'Only Creditors'!B37,Payments!$E$4:$E$130) -> 0 | I37: 32191.76 | J37: 0 | K37: 32191.76 | L37: 0 | M37: 0 | N37: 0 | O37: 0 | P37: 0 | Q37: 0 | R37: 32191.76 | S37: 0
A38: 34 | B38: Connect Residuary Pvt Ltd - Crs | C38: Head Office | D38: Loan EMI | E38: Loan EMI | F38: To be paid | G38: =I38-H38 -> 3.48 | H38: =SUMIF(Payments!$D$4:$D$117,'Only Creditors'!B38,Payments!$E$4:$E$130) -> 0 | I38: 3.48 | J38: 0 | K38: 1.24 | L38: 0 | M38: 0 | N38: 2.24 | O38: 0 | P38: 0 | Q38: 0 | R38: 3.48 | S38: 0
A39: 35 | B39: Csrl-Structwel Lab (Pune) Private Limited Crs | C39: Nagpur | D39: Expenses | E39: Testing charges | F39: To be paid | G39: =I39-H39 -> 0 | H39: =SUMIF(Payments!$D$4:$D$117,'Only Creditors'!B39,Payments!$E$4:$E$130) -> 3933 | I39: 3933 | J39: 0 | K39: 0 | L39: 3933 | M39: 0 | N39: 0 | O39: 0 | P39: 0 | Q39: 0 | R39: 3933 | S39: 0
A40: 36 | B40: CtrlP Solutions Private Limited - Crs | C40: Head Office | D40: Expenses | E40: Office Exps | F40: To be paid | G40: =I40-H40 -> 0 | H40: =SUMIF(Payments!$D$4:$D$117,'Only Creditors'!B40,Payments!$E$4:$E$130) -> 700 | I40: 700 | J40: 0 | K40: 700 | L40: -660.95 | M40: 0 | N40: 0 | O40: 0 | P40: 0 | Q40: 0 | R40: 39.05 | S40: 660.95
A41: 37 | B41: D.K. SERVICES - Crs | C41: Nagpur | D41: Expenses | E41: Postage & Courrier | F41: To be paid | G41: =I41-H41 -> 0 | H41: =SUMIF(Payments!$D$4:$D$117,'Only Creditors'!B41,Payments!$E$4:$E$130) -> 45611.2 | I41: 45611.2 | J41: 45611.2 | K41: 0 | L41: 0 | M41: 0 | N41: 0 | O41: 0 | P41: 0 | Q41: 0 | R41: 45611.2 | S41: 0
A42: 38 | B42: DEEP ENTERPRISES-CRS | C42: Nagpur | D42: Expenses | E42: Office Exps | F42: To be paid | G42: =I42-H42 -> 0 | H42: =SUMIF(Payments!$D$4:$D$117,'Only Creditors'!B42,Payments!$E$4:$E$130) -> 3000 | I42: 3000 | J42: 0 | K42: 3000 | L42: 0 | M42: 0 | N42: 0 | O42: 0 | P42: 0 | Q42: 0 | R42: 3000 | S42: 0
A43: 39 | B43: DEVENDRA CHAUHAN REFRACTORY WORKS -CRS | C43: Gujarat | D43: Capex | E43: Capex | F43: =SUM(N43:Q43) -> 0 | G43: =I43-H43 -> 0 | H43: =SUMIF(Payments!$D$4:$D$117,'Only Creditors'!B43,Payments!$E$4:$E$130) -> 43200 | I43: 43200 | J43: 0 | K43: 0 | L43: 43200 | M43: 0 | N43: 0 | O43: 0 | P43: 0 | Q43: 0 | R43: 43200 | S43: 0
A44: 40 | B44: DOED JUNG KUEN PHEN TRADING HOUSE-CRS | C44: Haryana | D44: Trading | E44: Bhutan Vendor | F44: =SUM(N44:Q44) -> 0 | G44: =I44-H44 -> -1479135.5 | H44: =SUMIF(Payments!$D$4:$D$117,'Only Creditors'!B44,Payments!$E$4:$E$130) -> 1700000 | I44: 220864.5 | J44: 2170511 | K44: -1949646.5 | L44: 0 | M44: 0 | N44: 0 | O44: 0 | P44: 0 | Q44: 0 | R44: 220864.5 | S44: 0
A45: 41 | B45: Dattakrupa Minerals - Crs | C45: Goa | D45: Transportation | E45: Transport | F45: To be paid | G45: =I45-H45 -> 0.2 | H45: =SUMIF(Payments!$D$4:$D$117,'Only Creditors'!B45,Payments!$E$4:$E$130) -> 0 | I45: 0.2 | J45: 0 | K45: 0 | L45: 0 | M45: 0 | N45: 0 | O45: 0 | P45: 0 | Q45: 0.2 | R45: 0.2 | S45: 0
A46: 42 | B46: Dev Security Services- Crs | C46: Aggregate | D46: Expenses | E46: Security charges | F46: =SUM(N46:Q46) -> 0 | G46: =I46-H46 -> 113558 | H46: =SUMIF(Payments!$D$4:$D$117,'Only Creditors'!B46,Payments!$E$4:$E$130) -> 0 | I46: 113558 | J46: 113558 | K46: 0 | L46: 0 | M46: 0 | N46: 0 | O46: 0 | P46: 0 | Q46: 0 | R46: 113558 | S46: 0
A47: 43 | B47: Devanand B. Singh - Employee | C47: Head Office | D47: Employee | E47: Employee | F47: =SUM(N47:Q47) -> 0 | G47: =I47-H47 -> 0 | H47: =SUMIF(Payments!$D$4:$D$117,'Only Creditors'!B47,Payments!$E$4:$E$130) -> 756000 | I47: 756000 | J47: 756000 | K47: 0 | L47: 0 | M47: 0 | N47: 0 | O47: 0 | P47: 0 | Q47: 0 | R47: 756000 | S47: 0
A48: 44 | B48: Dextrose Technologies Private Limited - Crs | C48: Galsi | D48: Raw Material | E48: Advance With Vendor Invoice Required | F48: To be paid | G48: =I48-H48 -> 4830.49 | H48: =SUMIF(Payments!$D$4:$D$117,'Only Creditors'!B48,Payments!$E$4:$E$130) -> 0 | I48: 4830.49 | J48: 4830.49 | K48: 0 | L48: 0 | M48: 0 | N48: 0 | O48: 0 | P48: 0 | Q48: 0 | R48: 4830.49 | S48: 0
A49: 45 | B49: Dmk Logistic - Crs | C49: Bangalore | D49: Transportation | E49: Transport | F49: =SUM(N49:Q49) -> 0 | G49: =I49-H49 -> 0 | H49: =SUMIF(Payments!$D$4:$D$117,'Only Creditors'!B49,Payments!$E$4:$E$130) -> 465366.71 | I49: 465366.71 | J49: 465366.71 | K49: 0 | L49: 0 | M49: 0 | N49: 0 | O49: 0 | P49: 0 | Q49: 0 | R49: 465366.71 | S49: 0
A50: 46 | B50: Dokania Purushottam - Crs | C50: Gujarat | D50: Expenses | E50: Factory rent | F50: To be paid | G50: =I50-H50 -> 0.5 | H50: =SUMIF(Payments!$D$4:$D$117,'Only Creditors'!B50,Payments!$E$4:$E$130) -> 0 | I50: 0.5 | J50: 0.5 | K50: 0 | L50: 0 | M50: 0 | N50: 0 | O50: 0 | P50: 0 | Q50: 0 | R50: 0.5 | S50: 0
A51: 47 | B51: Dutta Auto Centre | C51: Microsilica | D51: Expenses | E51: Repair & Maintenance | F51: =SUM(N51:Q51) -> 0 | G51: =I51-H51 -> 0 | H51: =SUMIF(Payments!$D$4:$D$117,'Only Creditors'!B51,Payments!$E$4:$E$130) -> 36049.4 | I51: 36049.4 | J51: 0 | K51: 36049.4 | L51: 0 | M51: 0 | N51: 0 | O51: 0 | P51: 0 | Q51: 0 | R51: 36049.4 | S51: 0
A52: 48 | B52: Eon Infotech Ltd - Crs | C52: Wada | D52: Expenses | E52: Repair & Maintenance | F52: To be paid | G52: =I52-H52 -> 74026.68 | H52: =SUMIF(Payments!$D$4:$D$117,'Only Creditors'!B52,Payments!$E$4:$E$130) -> 0 | I52: 74026.68 | J52: 12056 | K52: 0 | L52: 61970.68 | M52: 0 | N52: 0 | O52: 0 | P52: 0 | Q52: 0 | R52: 74026.68 | S52: 0
A53: 49 | B53: FAITH INFRA-CRS | C53: Aggregate | D53: Expenses | E53: Repair & Maintenance | F53: =SUM(N53:Q53) -> 0 | G53: =I53-H53 -> 601162.9 | H53: =SUMIF(Payments!$D$4:$D$117,'Only Creditors'!B53,Payments!$E$4:$E$130) -> 0 | I53: 601162.9 | J53: 215686.66 | K53: 87361.92 | L53: 298114.32 | M53: 0 | N53: 0 | O53: 0 | P53: 0 | Q53: 0 | R53: 601162.9 | S53: 0
A54: 50 | B54: FIRDOSH ERUCH ICHHAPORIA-Crs | C54: Gujarat | D54: Expenses | E54: Guest House Rent | F54: To be paid | G54: =I54-H54 -> 0 | H54: =SUMIF(Payments!$D$4:$D$117,'Only Creditors'!B54,Payments!$E$4:$E$130) -> 20000 | I54: 20000 | J54: 20000 | K54: 0 | L54: 0 | M54: 0 | N54: 0 | O54: 0 | P54: 0 | Q54: 0 | R54: 20000 | S54: 0
A55: 51 | B55: First Choice Logistics-Crs | C55: Wada | D55: Transportation | E55: Transport | F55: =SUM(N55:Q55) -> 0 | G55: =I55-H55 -> 153802.5 | H55: =SUMIF(Payments!$D$4:$D$117,'Only Creditors'!B55,Payments!$E$4:$E$130) -> 0 | I55: 153802.5 | J55: 153802.5 | K55: 0 | L55: 0 | M55: 0 | N55: 0 | O55: 0 | P55: 0 | Q55: 0 | R55: 153802.5 | S55: 0
A56: 52 | B56: G D Packaging - Crs | C56: Vizag | D56: Expenses | E56: Store and spare | F56: =SUM(N56:Q56) -> 0 | G56: =I56-H56 -> 0 | H56: =SUMIF(Payments!$D$4:$D$117,'Only Creditors'!B56,Payments!$E$4:$E$130) -> 137428 | I56: 137428 | J56: 0 | K56: 137428 | L56: 0 | M56: 0 | N56: 0 | O56: 0 | P56: 0 | Q56: 0 | R56: 137428 | S56: 0
A57: 53 | B57: Ganesh Trading & Industries LLP - Crs | C57: Bangalore | D57: Expenses | E57: Security charges | F57: =SUM(N57:Q57) -> 1800000 | G57: =I57-H57 -> 1800000 | H57: =SUMIF(Payments!$D$4:$D$117,'Only Creditors'!B57,Payments!$E$4:$E$130) -> 0 | I57: 1800000 | J57: 0 | K57: 0 | L57: 0 | M57: 0 | N57: 0 | O57: 0 | P57: 0 | Q57: 1800000 | R57: 1800000 | S57: 0
A58: 54 | B58: Gautam Trading Company -Crs | C58: Wada | D58: Expenses | E58: Store and spare | F58: =SUM(N58:Q58) -> 0 | G58: =I58-H58 -> 9801.08 | H58: =SUMIF(Payments!$D$4:$D$117,'Only Creditors'!B58,Payments!$E$4:$E$130) -> 0 | I58: 9801.08 | J58: 0 | K58: 9801.08 | L58: 0 | M58: 0 | N58: 0 | O58: 0 | P58: 0 | Q58: 0 | R58: 9801.08 | S58: 0
A59: 55 | B59: HDFC IOCL CREDIT CARD | C59: Head Office | D59: Expenses | E59: Regular Recharge | F59: =SUM(N59:Q59) -> 0 | G59: =I59-H59 -> 1699664 | H59: =SUMIF(Payments!$D$4:$D$117,'Only Creditors'!B59,Payments!$E$4:$E$130) -> 0 | I59: 1699664 | J59: -26338 | K59: 1726002 | L59: 0 | M59: 0 | N59: 0 | O59: 0 | P59: 0 | Q59: 0 | R59: 1699664 | S59: 0
A60: 56 | B60: Harish Ludhani - Employee | C60: Head Office | D60: Employee | E60: Employee | F60: =SUM(N60:Q60) -> 0 | G60: =I60-H60 -> 0 | H60: =SUMIF(Payments!$D$4:$D$117,'Only Creditors'!B60,Payments!$E$4:$E$130) -> 974095.2 | I60: 974095.2 | J60: 974095.2 | K60: 0 | L60: 0 | M60: 0 | N60: 0 | O60: 0 | P60: 0 | Q60: 0 | R60: 974095.2 | S60: 0
A61: 57 | B61: Harrier Security Services Private Limited-Crs | C61: Wada | D61: Expenses | E61: Security charges | F61: To be paid | G61: =I61-H61 -> 60336.57 | H61: =SUMIF(Payments!$D$4:$D$117,'Only Creditors'!B61,Payments!$E$4:$E$130) -> 0 | I61: 60336.57 | J61: 60336.57 | K61: 0 | L61: 0 | M61: 0 | N61: 0 | O61: 0 | P61: 0 | Q61: 0 | R61: 60336.57 | S61: 0
A62: 58 | B62: INDIA INTERNATIONAL COMPANY - Crs | C62: Nagpur | D62: Expenses | E62: Store and spare | F62: =SUM(N62:Q62) -> 0 | G62: =I62-H62 -> 2322864 | H62: =SUMIF(Payments!$D$4:$D$117,'Only Creditors'!B62,Payments!$E$4:$E$130) -> 0 | I62: 2322864 | J62: 1786992 | K62: 0 | L62: 535872 | M62: 0 | N62: 0 | O62: 0 | P62: 0 | Q62: 0 | R62: 2322864 | S62: 0
A63: 59 | B63: Info Tech Computers - Crs | C63: Nagpur | D63: Expenses | E63: Office Exps | F63: To be paid | G63: =I63-H63 -> 924.16 | H63: =SUMIF(Payments!$D$4:$D$117,'Only Creditors'!B63,Payments!$E$4:$E$130) -> 0 | I63: 924.16 | J63: 924.16 | K63: 0 | L63: 0 | M63: 0 | N63: 0 | O63: 0 | P63: 0 | Q63: 0 | R63: 924.16 | S63: 0
A64: 60 | B64: JANTA CEMENT INDUSTRIES-Crs | C64: Nagpur | D64: Trading | E64: Flyash | F64: =SUM(N64:Q64) -> 0 | G64: =I64-H64 -> 279918.46 | H64: =SUMIF(Payments!$D$4:$D$117,'Only Creditors'!B64,Payments!$E$4:$E$130) -> 0 | I64: 279918.46 | J64: 279918.46 | K64: 0 | L64: 0 | M64: 0 | N64: 0 | O64: 0 | P64: 0 | Q64: 0 | R64: 279918.46 | S64: 0
A65: 61 | B65: JFC Logistics - Crs | C65: Goa | D65: Transportation | E65: Transport | F65: =SUM(N65:Q65) -> 0 | G65: =I65-H65 -> 1391845.6 | H65: =SUMIF(Payments!$D$4:$D$117,'Only Creditors'!B65,Payments!$E$4:$E$130) -> 300000 | I65: 1691845.6 | J65: 1218167.3 | K65: 473678.34 | L65: 0 | M65: 0 | N65: 0 | O65: 0 | P65: 0 | Q65: 0 | R65: 1691845.6 | S65: 0
A66: 62 | B66: JINDAL POWER LIMITED-Crs | C66: Nellore | D66: Flyash | E66: Flyash | F66: =SUM(N66:Q66) -> 0 | G66: =I66-H66 -> 249687 | H66: =SUMIF(Payments!$D$4:$D$117,'Only Creditors'!B66,Payments!$E$4:$E$130) -> 0 | I66: 249687 | J66: 0 | K66: 249687 | L66: 0 | M66: 0 | N66: 0 | O66: 0 | P66: 0 | Q66: 0 | R66: 249687 | S66: 0
A67: 63 | B67: JINENDRA AUTO PARTS-Crs | C67: Gujarat | D67: Expenses | E67: Store and spare | F67: To be paid | G67: =I67-H67 -> 10091 | H67: =SUMIF(Payments!$D$4:$D$117,'Only Creditors'!B67,Payments!$E$4:$E$130) -> 0 | I67: 10091 | J67: 10091 | K67: 0 | L67: 0 | M67: 0 | N67: 0 | O67: 0 | P67: 0 | Q67: 0 | R67: 10091 | S67: 0
A68: 64 | B68: Jai Bhairunath | C68: Aggregate | D68: Expenses | E68: Repair & Maintenance | F68: To be paid | G68: =I68-H68 -> 0 | H68: =SUMIF(Payments!$D$4:$D$117,'Only Creditors'!B68,Payments!$E$4:$E$130) -> 10856 | I68: 10856 | J68: 10856 | K68: 0 | L68: 0 | M68: 0 | N68: 0 | O68: 0 | P68: 0 | Q68: 0 | R68: 10856 | S68: 0
A69: 65 | B69: Jhuman Bagdi- Crs | C69: Galsi | D69: Expenses | E69: Staff Welfare | F69: To be paid | G69: =I69-H69 -> 6000 | H69: =SUMIF(Payments!$D$4:$D$117,'Only Creditors'!B69,Payments!$E$4:$E$130) -> 0 | I69: 6000 | J69: 6000 | K69: 0 | L69: 0 | M69: 0 | N69: 0 | O69: 0 | P69: 0 | Q69: 0 | R69: 6000 | S69: 0
A70: 66 | B70: Joshi Dharmarajan Andezath - Employee | C70: Head Office | D70: Employee | E70: Employee | F70: =SUM(N70:Q70) -> 0 | G70: =I70-H70 -> 0 | H70: =SUMIF(Payments!$D$4:$D$117,'Only Creditors'!B70,Payments!$E$4:$E$130) -> 150000 | I70: 150000 | J70: 150000 | K70: 0 | L70: 0 | M70: 0 | N70: 0 | O70: 0 | P70: 0 | Q70: 0 | R70: 150000 | S70: 0
A71: 67 | B71: K D Enterprises-Crs | C71: flyash | D71: Flyash | E71: Flyash | F71: =SUM(N71:Q71) -> 0 | G71: =I71-H71 -> 1329902.5 | H71: =SUMIF(Payments!$D$4:$D$117,'Only Creditors'!B71,Payments!$E$4:$E$130) -> 0 | I71: 1329902.5 | J71: 367353.78 | K71: 104204.86 | L71: 858343.9 | M71: 0 | N71: 0 | O71: 0 | P71: 0 | Q71: 0 | R71: 1329902.5 | S71: 0
A72: 68 | B72: KAMAL S PATIL - Crs | C72: Wada | D72: Expenses | E72: Guest House Rent | F72: =SUM(N72:Q72) -> 0 | G72: =I72-H72 -> 0 | H72: =SUMIF(Payments!$D$4:$D$117,'Only Creditors'!B72,Payments!$E$4:$E$130) -> 34630.2 | I72: 34630.2 | J72: 34630.2 | K72: 0 | L72: 0 | M72: 0 | N72: 0 | O72: 0 | P72: 0 | Q72: 0 | R72: 34630.2 | S72: 0
A73: 69 | B73: KAPIL THAKARE - Crs | C73: Wada | D73: Expenses | E73: Staff Welfare | F73: =SUM(N73:Q73) -> 0 | G73: =I73-H73 -> 5495 | H73: =SUMIF(Payments!$D$4:$D$117,'Only Creditors'!B73,Payments!$E$4:$E$130) -> 0 | I73: 5495 | J73: 5495 | K73: 0 | L73: 0 | M73: 0 | N73: 0 | O73: 0 | P73: 0 | Q73: 0 | R73: 5495 | S73: 0
A74: 70 | B74: KGR Logistics - Crs | C74: Goa | D74: Transportation | E74: Transport | F74: =SUM(N74:Q74) -> 0.7 | G74: =I74-H74 -> 0.7 | H74: =SUMIF(Payments!$D$4:$D$117,'Only Creditors'!B74,Payments!$E$4:$E$130) -> 0 | I74: 0.7 | J74: 0 | K74: 0 | L74: 0 | M74: 0 | N74: 0 | O74: 0 | P74: 0 | Q74: 0.7 | R74: 0.7 | S74: 0
A75: 71 | B75: KRISHNA ENTERPRISES- Crs | C75: flyash | D75: Flyash | E75: Flyash | F75: =SUM(N75:Q75) -> 0 | G75: =I75-H75 -> 251774.38 | H75: =SUMIF(Payments!$D$4:$D$117,'Only Creditors'!B75,Payments!$E$4:$E$130) -> 0 | I75: 251774.38 | J75: 128158.8 | K75: 0 | L75: 123615.58 | M75: 0 | N75: 0 | O75: 0 | P75: 0 | Q75: 0 | R75: 251774.38 | S75: 0
A76: 72 | B76: Kamakhya Enterprises - Crs | C76: Aggregate | D76: Expenses | E76: Transport | F76: =SUM(N76:Q76) -> 0 | G76: =I76-H76 -> 822181.93 | H76: =SUMIF(Payments!$D$4:$D$117,'Only Creditors'!B76,Payments!$E$4:$E$130) -> 988898.21 | I76: 1811080.1 | J76: 1811080.1 | K76: 0 | L76: 0 | M76: 0 | N76: 0 | O76: 0 | P76: 0 | Q76: 0 | R76: 1811080.1 | S76: 0
A77: 73 | B77: Kaneria Building Solutions Pvt Ltd - Crs | C77: Gujarat | D77: Trading | E77: Flyash | F77: =SUM(N77:Q77) -> 0 | G77: =I77-H77 -> 455798 | H77: =SUMIF(Payments!$D$4:$D$117,'Only Creditors'!B77,Payments!$E$4:$E$130) -> 0 | I77: 455798 | J77: 0 | K77: 455798 | L77: 0 | M77: 0 | N77: 0 | O77: 0 | P77: 0 | Q77: 0 | R77: 455798 | S77: 0
A78: 74 | B78: Kiran Rubber-Crs | C78: Gujarat | D78: Expenses | E78: Repair & Maintenance | F78: To be paid | G78: =I78-H78 -> 5850 | H78: =SUMIF(Payments!$D$4:$D$117,'Only Creditors'!B78,Payments!$E$4:$E$130) -> 0 | I78: 5850 | J78: 5850 | K78: 0 | L78: 0 | M78: 0 | N78: 0 | O78: 0 | P78: 0 | Q78: 0 | R78: 5850 | S78: 0
A79: 75 | B79: Krishna Enterprise(Guj)-Crs | C79: Gujarat | D79: Expenses | E79: Store and spare | F79: To be paid | G79: =I79-H79 -> 2478 | H79: =SUMIF(Payments!$D$4:$D$117,'Only Creditors'!B79,Payments!$E$4:$E$130) -> 0 | I79: 2478 | J79: 2478 | K79: 0 | L79: 0 | M79: 0 | N79: 0 | O79: 0 | P79: 0 | Q79: 0 | R79: 2478 | S79: 0
A80: 76 | B80: Krishna Konar - Crs | C80: Galsi | D80: Expenses | E80: Factory rent | F80: To be paid | G80: =I80-H80 -> 0 | H80: =SUMIF(Payments!$D$4:$D$117,'Only Creditors'!B80,Payments!$E$4:$E$130) -> 18000 | I80: 18000 | J80: 18000 | K80: 0 | L80: 0 | M80: 0 | N80: 0 | O80: 0 | P80: 0 | Q80: 0 | R80: 18000 | S80: 0
A81: 77 | B81: Krishnendu Konar CRS | C81: Galsi | D81: Expenses | E81: Factory rent | F81: To be paid | G81: =I81-H81 -> 0 | H81: =SUMIF(Payments!$D$4:$D$117,'Only Creditors'!B81,Payments!$E$4:$E$130) -> 37000 | I81: 37000 | J81: 37000 | K81: 0 | L81: 0 | M81: 0 | N81: 0 | O81: 0 | P81: 0 | Q81: 0 | R81: 37000 | S81: 0
A82: 78 | B82: Legacy Transport Private Limited-Crs | C82: Gujarat | D82: Transportation | E82: Transport | F82: =SUM(N82:Q82) -> 0 | G82: =I82-H82 -> 77420 | H82: =SUMIF(Payments!$D$4:$D$117,'Only Creditors'!B82,Payments!$E$4:$E$130) -> 197225 | I82: 274645 | J82: 274645 | K82: 0 | L82: 0 | M82: 0 | N82: 0 | O82: 0 | P82: 0 | Q82: 0 | R82: 274645 | S82: 0
A83: 79 | B83: Lub Solutions Pvt Ltd - Crs | C83: Goa | D83: Capex | E83: Capex | F83: =SUM(N83:Q83) -> 786935 | G83: =I83-H83 -> 786935 | H83: =SUMIF(Payments!$D$4:$D$117,'Only Creditors'!B83,Payments!$E$4:$E$130) -> 0 | I83: 786935 | J83: 0 | K83: 0 | L83: 0 | M83: 0 | N83: 0 | O83: 0 | P83: 0 | Q83: 786935 | R83: 786935 | S83: 0
A84: 80 | B84: Lubricating Centre Pvt Ltd | C84: Aggregate | D84: Expenses | E84: Repair & Maintenance | F84: =SUM(N84:Q84) -> 0 | G84: =I84-H84 -> 305400 | H84: =SUMIF(Payments!$D$4:$D$117,'Only Creditors'!B84,Payments!$E$4:$E$130) -> 0 | I84: 305400 | J84: 97000 | K84: 0 | L84: 208400 | M84: 0 | N84: 0 | O84: 0 | P84: 0 | Q84: 0 | R84: 305400 | S84: 0
A85: 81 | B85: M B ENTERPRISE- Crs | C85: Galsi | D85: Expenses | E85: Postage & Courrier | F85: To be paid | G85: =I85-H85 -> 81011.2 | H85: =SUMIF(Payments!$D$4:$D$117,'Only Creditors'!B85,Payments!$E$4:$E$130) -> 0 | I85: 81011.2 | J85: 81011.2 | K85: 0 | L85: 0 | M85: 0 | N85: 0 | O85: 0 | P85: 0 | Q85: 0 | R85: 81011.2 | S85: 0
A86: 82 | B86: M.B.S. Construction | C86: Aggregate | D86: Transportation | E86: Transport | F86: =SUM(N86:Q86) -> 0.3 | G86: =I86-H86 -> 5887338.8 | H86: =SUMIF(Payments!$D$4:$D$117,'Only Creditors'!B86,Payments!$E$4:$E$130) -> 0 | I86: 5887338.8 | J86: 2339857.2 | K86: 1800161.3 | L86: 1747319.5 | M86: 0.4 | N86: 0.3 | O86: 0 | P86: 0 | Q86: 0 | R86: 5887338.8 | S86: 0
A87: 83 | B87: M/S SHAKTI MACHINERY & MILL STORE-CRS | C87: Microsilica | D87: Expenses | E87: Repair & Maintenance | F87: =SUM(N87:Q87) -> 944848.72 | G87: =I87-H87 -> 1763177.7 | H87: =SUMIF(Payments!$D$4:$D$117,'Only Creditors'!B87,Payments!$E$4:$E$130) -> 0 | I87: 1763177.7 | J87: 0 | K87: 0 | L87: 0 | M87: 818328.96 | N87: 0 | O87: 0 | P87: 944848.72 | Q87: 0 | R87: 1763177.7 | S87: 0
A88: 84 | B88: M/s Jadav Enterprise - Crs | C88: Aggregate | D88: Raw Material | E88: Raw material | F88: =SUM(N88:Q88) -> 0 | G88: =I88-H88 -> 316522.28 | H88: =SUMIF(Payments!$D$4:$D$117,'Only Creditors'!B88,Payments!$E$4:$E$130) -> 988255 | I88: 1304777.3 | J88: 1304777.3 | K88: 0 | L88: 0 | M88: 0 | N88: 0 | O88: 0 | P88: 0 | Q88: 0 | R88: 1304777.3 | S88: 0
A89: 85 | B89: MSEDCL - CRS | C89: Nagpur | D89: Expenses | E89: Electricity | F89: =SUM(N89:Q89) -> 0 | G89: =I89-H89 -> 0 | H89: =SUMIF(Payments!$D$4:$D$117,'Only Creditors'!B89,Payments!$E$4:$E$130) -> 626430 | I89: 626430 | J89: 626430 | K89: 0 | L89: 0 | M89: 0 | N89: 0 | O89: 0 | P89: 0 | Q89: 0 | R89: 626430 | S89: 0
A90: 86 | B90: MSJ Movers - CRS | C90: Nagpur | D90: Raw Material | E90: Flyash | F90: =SUM(N90:Q90) -> 0 | G90: =I90-H90 -> 657030.24 | H90: =SUMIF(Payments!$D$4:$D$117,'Only Creditors'!B90,Payments!$E$4:$E$130) -> 0 | I90: 657030.24 | J90: 292813.11 | K90: 364217.13 | L90: 0 | M90: 0 | N90: 0 | O90: 0 | P90: 0 | Q90: 0 | R90: 657030.24 | S90: 0
A91: 87 | B91: Maa Jodh Roadways-Crs | C91: Gujarat | D91: Expenses | E91: Transport | F91: =SUM(N91:Q91) -> 0 | G91: =I91-H91 -> 857382.61 | H91: =SUMIF(Payments!$D$4:$D$117,'Only Creditors'!B91,Payments!$E$4:$E$130) -> 0 | I91: 857382.61 | J91: 119436.04 | K91: 737946.57 | L91: 0 | M91: 0 | N91: 0 | O91: 0 | P91: 0 | Q91: 0 | R91: 857382.61 | S91: 0
A92: 88 | B92: Mahalaxmi Industrial & Hardware Store - Crs | C92: Gujarat | D92: Expenses | E92: Store and spare | F92: =SUM(N92:Q92) -> 0 | G92: =I92-H92 -> 54516.76 | H92: =SUMIF(Payments!$D$4:$D$117,'Only Creditors'!B92,Payments!$E$4:$E$130) -> 0 | I92: 54516.76 | J92: 54516.76 | K92: 0 | L92: 0 | M92: 0 | N92: 0 | O92: 0 | P92: 0 | Q92: 0 | R92: 54516.76 | S92: 0
A93: 89 | B93: Mangal Packaging Industries - Crs | C93: Nagpur | D93: Expenses | E93: Store and spare | F93: =SUM(N93:Q93) -> 0 | G93: =I93-H93 -> 517000 | H93: =SUMIF(Payments!$D$4:$D$117,'Only Creditors'!B93,Payments!$E$4:$E$130) -> 0 | I93: 517000 | J93: 0 | K93: 274350 | L93: 242650 | M93: 0 | N93: 0 | O93: 0 | P93: 0 | Q93: 0 | R93: 517000 | S93: 0
A94: 90 | B94: Mbs Enterprise (Crusher) - Crs | C94: Aggregate | D94: Raw Material | E94: Aggregate | F94: =SUM(N94:Q94) -> 0 | G94: =I94-H94 -> 352640 | H94: =SUMIF(Payments!$D$4:$D$117,'Only Creditors'!B94,Payments!$E$4:$E$130) -> 0 | I94: 352640 | J94: 352640 | K94: 0 | L94: 0 | M94: 0 | N94: 0 | O94: 0 | P94: 0 | Q94: 0 | R94: 352640 | S94: 0
A95: 91 | B95: Mehar Engineering Works | C95: Nagpur | D95: Expenses | E95: Store and spare | F95: To be paid | G95: =I95-H95 -> 0 | H95: =SUMIF(Payments!$D$4:$D$117,'Only Creditors'!B95,Payments!$E$4:$E$130) -> 66080 | I95: 66080 | J95: 66080 | K95: 0 | L95: 0 | M95: 0 | N95: 0 | O95: 0 | P95: 0 | Q95: 0 | R95: 66080 | S95: 0
A96: 92 | B96: Miloni International - Crs | C96: Gujarat | D96: Capex | E96: Capex | F96: =SUM(N96:Q96) -> 0 | G96: =I96-H96 -> 730882.4 | H96: =SUMIF(Payments!$D$4:$D$117,'Only Creditors'!B96,Payments!$E$4:$E$130) -> 0 | I96: 730882.4 | J96: 0 | K96: 0 | L96: 730882.4 | M96: 0 | N96: 0 | O96: 0 | P96: 0 | Q96: 0 | R96: 730882.4 | S96: 0
A97: 93 | B97: Mollick Tube- Crs | C97: Aggregate | D97: Trading | E97: Aggregate | F97: =SUM(N97:Q97) -> 623635.12 | G97: =I97-H97 -> 623635.12 | H97: =SUMIF(Payments!$D$4:$D$117,'Only Creditors'!B97,Payments!$E$4:$E$130) -> 0 | I97: 623635.12 | J97: 0 | K97: 0 | L97: 0 | M97: 0 | N97: 0 | O97: 437373.82 | P97: 186261.3 | Q97: 0 | R97: 623635.12 | S97: 0
A98: 94 | B98: NAVEEN P REDDY - Crs | C98: Nellore | D98: Expenses | E98: Factory rent | F98: To be paid | G98: =I98-H98 -> 27225 | H98: =SUMIF(Payments!$D$4:$D$117,'Only Creditors'!B98,Payments!$E$4:$E$130) -> 0 | I98: 27225 | J98: 27225 | K98: 0 | L98: 0 | M98: 0 | N98: 0 | O98: 0 | P98: 0 | Q98: 0 | R98: 27225 | S98: 0
A99: 95 | B99: NIGAM CAR SERVICES | C99: Aggregate | D99: Expenses | E99: Repair & Maintenance | F99: To be paid | G99: =I99-H99 -> 0 | H99: =SUMIF(Payments!$D$4:$D$117,'Only Creditors'!B99,Payments!$E$4:$E$130) -> 20958 | I99: 20958 | J99: 0 | K99: 10958 | L99: 10000 | M99: 0 | N99: 0 | O99: 0 | P99: 0 | Q99: 0 | R99: 20958 | S99: 0
A100: 96 | B100: Neofines Solution-CRS | C100: Raipur | D100: Trading | E100: Microsilica | F100: =SUM(N100:Q100) -> 0 | G100: =I100-H100 -> 722437.3 | H100: =SUMIF(Payments!$D$4:$D$117,'Only Creditors'!B100,Payments!$E$4:$E$130) -> 0 | I100: 722437.3 | J100: 315927.3 | K100: 138060 | L100: 268450 | M100: 0 | N100: 0 | O100: 0 | P100: 0 | Q100: 0 | R100: 722437.3 | S100: 0
...

Sheet Advances
A1: Ultrafine Mineral & Admixtures Pvt. Ltd.
A2: Creditors - Advance Payments (Debit Balances) | As at 31-July-2026
B3: SUBTOTAL | H3: =SUBTOTAL(9,H5:H54) -> -45031978 | I3: =SUBTOTAL(9,I5:I54) -> -4141190 | J3: =SUBTOTAL(9,J5:J54) -> -8008796.6 | K3: =SUBTOTAL(9,K5:K54) -> -124791.9 | L3: =SUBTOTAL(9,L5:L54) -> -815688.58 | M3: =SUBTOTAL(9,M5:M54) -> -30000 | N3: =SUBTOTAL(9,N5:N54) -> -400000 | O3: =SUBTOTAL(9,O5:O54) -> -25207370 | ... R3: =SUBTOTAL(9,R5:R54) -> -298894
A4: # | B4: Vendor Name | C4: Location | D4: Vendor Type | E4: Vendor Sub Type | F4: Remarks | H4: TB Balance (Cr) | I4: 0-30 Days | J4: 31-60 Days | K4: 61-90 Days | L4: 91-120 Days | M4: 121-150 Days | N4: 151-180 Days | O4: 181-365 Days | P4: Above 365 Days | Q4: BW Total | R4: Diff (TB-BW)
A5: 1 | B5: ACE HIMALAYAN FERRO ALLOYS PRIVATE LIMITED - CRS | C5: Haryana | D5: Trading | E5: Bhutan Vendor | F5: Abhay | H5: -94000 | I5: 0 | J5: 0 | K5: -94000 | L5: 0 | M5: 0 | N5: 0 | O5: 0 | P5: 0 | Q5: -94000 | R5: 0
A6: 2 | B6: ASHOKA BUILDCON LIMITED-Crs | C6: Aggregate | D6: Vendor Advance | E6: Vendor Advance | H6: -163127.04 | I6: 0 | J6: 0 | K6: 0 | L6: 0 | M6: 0 | N6: 0 | O6: -150000 | P6: -13127.04 | Q6: -163127.04 | R6: 0
A7: 3 | B7: Abhay Dongare - Employee | C7: Head Office | D7: Employee | E7: Employee | H7: -7148 | I7: 0 | J7: 0 | K7: 0 | L7: -7148 | M7: 0 | N7: 0 | O7: 0 | P7: 0 | Q7: -7148 | R7: 0
A8: 4 | B8: Abhay Singh-Employee | C8: Head Office | D8: Employee | E8: Employee | H8: -4484 | I8: -4484 | J8: 0 | K8: 0 | L8: 0 | M8: 0 | N8: 0 | O8: 0 | P8: 0 | Q8: -4484 | R8: 0
A9: 5 | B9: Ankush Chavan- Employee | C9: Wada | D9: Employee | E9: Employee | H9: -15000 | I9: -15000 | J9: 0 | K9: 0 | L9: 0 | M9: 0 | N9: 0 | O9: 0 | P9: 0 | Q9: -15000 | R9: 0
A10: 6 | B10: Arcelormittal Nippon Steel India Limited - Crs | C10: Gujarat | D10: Vendor Advance | E10: Vendor Advance | H10: -531569.86 | I10: -531569.86 | J10: 0 | K10: 0 | L10: 0 | M10: 0 | N10: 0 | O10: 0 | P10: 0 | Q10: -531569.86 | R10: 0
A11: 7 | B11: Ashvarya Kumar Verma-Employee | C11: Head Office | D11: Employee | E11: Employee | H11: -23510 | I11: 0 | J11: 0 | K11: -10 | L11: -23500 | M11: 0 | N11: 0 | O11: 0 | P11: 0 | Q11: -23510 | R11: 0
A12: 8 | B12: BOMMI SUNEEL KUMAR-Employee | C12: Nellore | D12: Employee | E12: Employee | H12: -25000 | I12: 0 | J12: 0 | K12: 0 | L12: -25000 | M12: 0 | N12: 0 | O12: 0 | P12: 0 | Q12: -25000 | R12: 0
A13: 9 | B13: Bandu Naik - Employee | C13: Gujarat | D13: Employee | E13: Employee | F13: Rakesh Sir | H13: -187504 | I13: -10000 | J13: 0 | K13: 0 | L13: 0 | M13: 0 | N13: 0 | O13: -177504 | P13: 0 | Q13: -187504 | R13: 0
A14: 10 | B14: Bhushan Deshpande - Employee | C14: Head Office | D14: Employee | E14: Employee | F14: JV | H14: -17998 | I14: 0 | J14: -17998 | K14: 0 | L14: 0 | M14: 0 | N14: 0 | O14: 0 | P14: 0 | Q14: -17998 | R14: 0
A15: 11 | B15: C K Paul Gas Agency - Crs | C15: Galsi | D15: Expenses | E15: Repair & Maintenance | H15: -0.25 | I15: -0.25 | J15: 0 | K15: 0 | L15: 0 | M15: 0 | N15: 0 | O15: 0 | P15: 0 | Q15: -0.25 | R15: 0
A16: 12 | B16: Desai Cement Company Pvt Ltd-Crs | C16: Goa | D16: Expenses | E16: BG Incashed | H16: -13962953 | I16: 0 | J16: 0 | K16: 0 | L16: 0 | M16: 0 | N16: 0 | O16: -13962953 | P16: 0 | Q16: -13962953 | R16: 0
A17: 13 | B17: Digambar A. Naik - Crs | C17: Goa | D17: Expenses | E17: GST Claim | F17: Rakesh Sir | H17: -29669.94 | I17: 0 | J17: -29669.94 | K17: 0 | L17: 0 | M17: 0 | N17: 0 | O17: 0 | P17: 0 | Q17: -29669.94 | R17: 0
A18: 14 | B18: ETC POOL - Crs | C18: flyash | D18: Expenses | E18: Regular Advance | H18: -7000 | I18: 276000 | J18: -283000 | K18: 0 | L18: 0 | M18: 0 | N18: 0 | O18: 0 | P18: 0 | Q18: -7000 | R18: 0
A19: 15 | B19: Eurocem Additives Private Limited-Crs | C19: Head Office | D19: Capex | E19: Interest | H19: -2714140 | I19: -2000000 | J19: 0 | K19: 0 | L19: -714140 | M19: 0 | N19: 0 | O19: 0 | P19: 0 | Q19: -2714140 | R19: 0
A20: 16 | B20: Exalt Druk Enviroklens Pvt Ltd - Crs | C20: Haryana | D20: Trading | E20: Bhutan Vendor | F20: Abhay | H20: -2687615 | I20: -300000 | J20: -2387615 | K20: 0 | L20: 0 | M20: 0 | N20: 0 | O20: 0 | P20: 0 | Q20: -2687615 | R20: 0
A21: 17 | B21: Fourteckh Enviro India Pvt Ltd - Crs | C21: Gujarat | D21: Capex | E21: Capex Advance | H21: -2884000 | I21: -1656000 | J21: -1228000 | K21: 0 | L21: 0 | M21: 0 | N21: 0 | O21: 0 | P21: 0 | Q21: -2884000 | R21: 0
A22: 18 | B22: H R Industries - Crs | C22: Bangalore | D22: Trading | E22: GGBS | F22: Saif Sir | H22: -19032.8 | I22: 0 | J22: 0 | K22: 0 | L22: 0 | M22: 0 | N22: 0 | O22: -19032.8 | P22: 0 | Q22: -19032.8 | R22: 0
A23: 19 | B23: Harsh Raj - EMPLOYEE | C23: Head Office | D23: Employee | E23: Employee | H23: -4421 | I23: -4421 | J23: 0 | K23: 0 | L23: 0 | M23: 0 | N23: 0 | O23: 0 | P23: 0 | Q23: -4421 | R23: 0
A24: 20 | B24: Indian Oil Corporation Limited - Crs | C24: Wada | D24: Expenses | E24: Regular Advance | H24: -195874.65 | I24: 131705.39 | J24: -327580.04 | K24: 0 | L24: 0 | M24: 0 | N24: 0 | O24: 0 | P24: 0 | Q24: -195874.65 | R24: 0
A25: 21 | B25: JAI Energy Giant Engineering and consultancy - Crs | C25: Nagpur | D25: Capex | E25: Capex Advance | H25: -4692357 | I25: 0 | J25: 0 | K25: 0 | L25: 0 | M25: 0 | N25: 0 | O25: 0 | P25: -4692357 | Q25: -4692357 | R25: 0
A26: 22 | B26: JASSPER SHIPPING INDIA LIMITED- CRS | C26: Goa | D26: Transportation | E26: GST Claim | F26: legal mail | H26: -653396 | I26: 0 | J26: 0 | K26: 0 | L26: 0 | M26: 0 | N26: 0 | O26: -653396 | P26: 0 | Q26: -653396 | R26: 0
A27: 23 | B27: Jpgr Automobile Private Limited-Crs | C27: Wada | D27: Expenses | E27: Repair & Maintenance | H27: -0.68 | I27: -0.68 | J27: 0 | K27: 0 | L27: 0 | M27: 0 | N27: 0 | O27: 0 | P27: 0 | Q27: -0.68 | R27: 0
A28: 24 | B28: KFin Technologies Limited - Crs | C28: Howrah | D28: Expenses | E28: Professional Fees | H28: -5900 | I28: 0 | J28: 0 | K28: 0 | L28: -5900 | M28: 0 | N28: 0 | O28: 0 | P28: 0 | Q28: -5900 | R28: 0
A29: 25 | B29: Karim Shah - Employee | C29: Head Office | D29: Employee | E29: Employee | H29: -25507 | I29: -4493 | J29: 0 | K29: 0 | L29: 0 | M29: 0 | N29: 0 | O29: 0 | P29: 0 | Q29: -4493 | R29: -21014
A30: 26 | B30: Kinshar Metals - Crs | C30: Haryana | D30: Trading | E30: Bhutan Vendor | F30: Abhay | H30: -2874700 | I30: -222120 | J30: -2374700 | K30: 0 | L30: 0 | M30: 0 | N30: 0 | O30: 0 | P30: 0 | Q30: -2596820 | R30: -277880
A31: 27 | B31: LAXMI ENGINEERING INDUSTRIES - CRS | C31: Galsi | D31: Expenses | E31: Capex Advance | H31: -5781.9 | I31: 0 | J31: 0 | K31: -5781.9 | L31: 0 | M31: 0 | N31: 0 | O31: 0 | P31: 0 | Q31: -5781.9 | R31: 0
A32: 28 | B32: M/s Hms International-Crs | C32: Wada | D32: Expenses | E32: Sales Promotion Exps | F32: Cleared | H32: -179000 | I32: 0 | J32: -179000 | K32: 0 | L32: 0 | M32: 0 | N32: 0 | O32: 0 | P32: 0 | Q32: -179000 | R32: 0
A33: 29 | B33: M/s Manuwar Shaikh (Crusher)- Crs | C33: Microsilica | D33: Expenses | E33: Pending from Vendor | F33: ashutosh | H33: -600000 | I33: 0 | J33: 0 | K33: 0 | L33: 0 | M33: 0 | N33: 0 | O33: -600000 | P33: 0 | Q33: -600000 | R33: 0
A34: 30 | B34: MACPOWER ELECTRICALS-Crs (Cap) | C34: Galsi | D34: Capex | E34: Capex Advance | H34: -141300 | I34: 353700 | J34: -495000 | K34: 0 | L34: 0 | M34: 0 | N34: 0 | O34: 0 | P34: 0 | Q34: -141300 | R34: 0
A35: 31 | B35: MNG Automobiles Pvt Ltd - CRS | C35: Goa | D35: Expenses | E35: Vehicle Expenses | H35: -6891.58 | I35: 0 | J35: -6891.58 | K35: 0 | L35: 0 | M35: 0 | N35: 0 | O35: 0 | P35: 0 | Q35: -6891.58 | R35: 0
A36: 32 | B36: Narvekar Brothers - Crs | C36: Goa | D36: Expenses | E36: Stores and Spares | H36: -6048 | I36: 0 | J36: -6048 | K36: 0 | L36: 0 | M36: 0 | N36: 0 | O36: 0 | P36: 0 | Q36: -6048 | R36: 0
A37: 33 | B37: Rajeswar Polai - Employee | C37: Goa | D37: Employee | E37: Employee | H37: -25000 | I37: 0 | J37: 0 | K37: -25000 | L37: 0 | M37: 0 | N37: 0 | O37: 0 | P37: 0 | Q37: -25000 | R37: 0
A38: 34 | B38: Remi Sales and Engineering Ltd - Crs | C38: Goa | D38: Expenses | E38: Testing and Inspection | H38: -1852.02 | I38: 0 | J38: -1852.02 | K38: 0 | L38: 0 | M38: 0 | N38: 0 | O38: 0 | P38: 0 | Q38: -1852.02 | R38: 0
A39: 35 | B39: Rohit Prasad - Employee | C39: Gujarat | D39: Employee | E39: Employee | H39: -25000 | I39: 0 | J39: 0 | K39: 0 | L39: -25000 | M39: 0 | N39: 0 | O39: 0 | P39: 0 | Q39: -25000 | R39: 0
A40: 36 | B40: SGS Impex - Crs | C40: Gujarat | D40: Expenses | E40: Adjusted against Kinshar Metals | F40: Abhay 20 aug | H40: -400000 | I40: 0 | J40: 0 | K40: 0 | L40: 0 | M40: 0 | N40: -400000 | O40: 0 | P40: 0 | Q40: -400000 | R40: 0
A41: 37 | B41: SHIVSHAKTI ENTERPRISES - Crs | C41: flyash | D41: Raw Material | E41: Advance With Vendor Invoice or Refund Required | H41: -649762.84 | I41: 0 | J41: 0 | K41: 0 | L41: 0 | M41: 0 | N41: 0 | O41: 0 | P41: -649762.84 | Q41: -649762.84 | R41: 0
A42: 38 | B42: SOUTHERNPOWERDISTRIBUTIONCOMPANYOFANDHRA-Cr | C42: Nellore | D42: Expenses | E42: Electricity | H42: -108.85 | I42: -108.85 | J42: 0 | K42: 0 | L42: 0 | M42: 0 | N42: 0 | O42: 0 | P42: 0 | Q42: -108.85 | R42: 0
A43: 39 | B43: Saiprasad Naik & Associates - Crs | C43: Goa | D43: Raw Material | E43: Advance With Vendor Invoice or Refund Required | H43: -195838.66 | I43: 0 | J43: -54183.66 | K43: 0 | L43: 0 | M43: 0 | N43: 0 | O43: -141655 | P43: 0 | Q43: -195838.66 | R43: 0
A44: 40 | B44: Sandeep Singh - Employee | C44: Aggregate | D44: Employee | E44: Employee | H44: -30000 | I44: 0 | J44: 0 | K44: 0 | L44: 0 | M44: -30000 | N44: 0 | O44: 0 | P44: 0 | Q44: -30000 | R44: 0
A45: 41 | B45: Sanjay Ramgopal Sharma - Crs | C45: Goa | D45: Expenses | E45: Transport Exps | H45: -6400 | I45: -5200 | J45: -1200 | K45: 0 | L45: 0 | M45: 0 | N45: 0 | O45: 0 | P45: 0 | Q45: -6400 | R45: 0
A46: 42 | B46: Shahabaz Khan - Employee | C46: Head Office | D46: Employee | E46: Employee | H46: -12000 | I46: 3000 | J46: 0 | K46: 0 | L46: -15000 | M46: 0 | N46: 0 | O46: 0 | P46: 0 | Q46: -12000 | R46: 0
A47: 43 | B47: Steel & Power-CR (CAP) - Crs | C47: Gujarat | D47: Capex | E47: Capex Advance | F47: dev | H47: -650000 | I47: 0 | J47: 0 | K47: 0 | L47: 0 | M47: 0 | N47: 0 | O47: 0 | P47: -650000 | Q47: -650000 | R47: 0
A48: 44 | B48: Stsk Controls and Automation - Crs | C48: Gujarat | D48: Capex | E48: Capex Advance | F48: devanand sir | H48: -587994 | I48: 0 | J48: -587994 | K48: 0 | L48: 0 | M48: 0 | N48: 0 | O48: 0 | P48: 0 | Q48: -587994 | R48: 0
A49: 45 | B49: Vedant Roadways And Trading-Crs | C49: Nagpur | D49: Transportation | E49: Transport | F49: Diesel exp | H49: -146997.79 | I49: -146997.79 | J49: 0 | K49: 0 | L49: 0 | M49: 0 | N49: 0 | O49: 0 | P49: 0 | Q49: -146997.79 | R49: 0
A50: 46 | B50: Vedanta Limited (Goa) - Crs | C50: Goa | D50: Raw Material | E50: BG Issue | H50: -9481609.8 | I50: 0 | J50: 0 | K50: 0 | L50: 0 | M50: 0 | N50: 0 | O50: -9481609.8 | P50: 0 | Q50: -9481609.8 | R50: 0
A51: 47 | B51: Vikram Coal Carriers (P) Ltd - Crs | C51: Goa | D51: Transportation | E51: Debit note | H51: -5200 | I51: -5200 | J51: 0 | K51: 0 | L51: 0 | M51: 0 | N51: 0 | O51: 0 | P51: 0 | Q51: -5200 | R51: 0
A52: 48 | B52: Vinayak Minerals - Crs | C52: Wada | D52: Raw Material | E52: Regular Advance | F52: Rakesh Sir | G52: =28064.39+37033.5 -> 65097.89 | H52: -28064.39 | I52: 0 | J52: -28064.39 | K52: 0 | L52: 0 | M52: 0 | N52: 0 | O52: 0 | P52: 0 | Q52: -28064.39 | R52: 0
A53: 49 | B53: Vinayak Oil Industries - Crs | C53: Nagpur | D53: Expenses | E53: Repair & Maintenance | H53: -0.58 | I53: 0 | J53: 0 | K53: 0 | L53: -0.58 | M53: 0 | N53: 0 | O53: 0 | P53: 0 | Q53: -0.58 | R53: 0
A54: 50 | B54: Zippmat Private Limited - Crs | C54: Bangalore | D54: Raw Material | E54: Advance With Vendor Invoice or Refund Required | F54: Mail | H54: -21219.5 | I54: 0 | J54: 0 | K54: 0 | L54: 0 | M54: 0 | N54: 0 | O54: -21219.5 | P54: 0 | Q54: -21219.5 | R54: 0
B56: Grand Total | H56: =SUBTOTAL(9,H9:H55) -> -44763219 | I56: =SUM(I5:I54) -> -4141190 | J56: =SUM(J5:J54) -> -8008796.6 | K56: =SUM(K5:K54) -> -124791.9 | L56: =SUM(L5:L54) -> -815688.58 | M56: =SUM(M5:M54) -> -30000 | N56: =SUM(N5:N54) -> -400000 | O56: =SUM(O5:O54) -> -25207370 | P56: =SUM(P5:P54) -> -6005246.9 | ... R56: =SUM(R5:R54) -> -298894

Sheet Sheet1
B2: Vendor Name | C2: Location | D2: TB Balance (Cr) | E2: 0-30 Days | F2: 31-60 Days | G2: 61-90 Days | H2: 91-120 Days | I2: 121-150 Days | J2: 151-180 Days | K2: 181-365 Days | L2: Above 365 Days | M2: BW Total
B3: Kinshar Metals - Crs | C3: Haryana | D3: -2874700 | E3: -222120 | F3: -2374700 | G3: 0 | H3: 0 | I3: 0 | J3: 0 | K3: 0 | L3: 0 | M3: -2596820
B4: Exalt Druk Enviroklens Pvt Ltd - Crs | C4: Haryana | D4: -2687615 | E4: -300000 | F4: -2387615 | G4: 0 | H4: 0 | I4: 0 | J4: 0 | K4: 0 | L4: 0 | M4: -2687615
B5: SGS Impex - Crs | C5: Gujarat | D5: -400000 | E5: 0 | F5: 0 | G5: 0 | H5: 0 | I5: 0 | J5: -400000 | K5: 0 | L5: 0 | M5: -400000
B6: ACE HIMALAYAN FERRO ALLOYS PRIVATE LIMITED - CRS | C6: Haryana | D6: -94000 | E6: 0 | F6: 0 | G6: -94000 | H6: 0 | I6: 0 | J6: 0 | K6: 0 | L6: 0 | M6: -94000
D8: =SUM(D3:D7) -> -6056315 | E8: =SUM(E3:E7) -> -522120 | F8: =SUM(F3:F7) -> -4762315 | G8: =SUM(G3:G7) -> -94000 | H8: =SUM(H3:H7) -> 0 | I8: =SUM(I3:I7) -> 0 | J8: =SUM(J3:J7) -> -400000 | K8: =SUM(K3:K7) -> 0 | ... M8: =SUM(M3:M7) -> -5778435

Sheet Intercompany
A1: Ultrafine Mineral & Admixtures Pvt. Ltd.
A2: Creditors Ageing Report - Intercompany & Special | As at 31-July-2026
B3: SUBTOTAL | E3: =SUM(E5:E21) -> 1.2133057e+08 | F3: =SUM(F5:F21) -> 4133810.8 | G3: =SUM(G5:G21) -> 21034576 | H3: =SUM(H5:H21) -> 4849961.4 | I3: =SUM(I5:I21) -> 5021160.7 | J3: =SUM(J5:J21) -> 27744692 | K3: =SUM(K5:K21) -> 7489095.8 | L3: =SUM(L5:L21) -> 28657615 | ... O3: =SUM(O5:O21) -> 0
A4: # | B4: Vendor Name | C4: Vendor Type | E4: TB Balance (Cr) | F4: 0-30 Days | G4: 31-60 Days | H4: 61-90 Days | I4: 91-120 Days | J4: 121-150 Days | K4: 151-180 Days | L4: 181-365 Days | M4: Above 365 Days | N4: BW Total | O4: Diff (TB-BW)
A5: 1 | B5: RDC Concrete India Pvt. Ltd. Punjab - Crs | C5: Intercompany | E5: 30680 | F5: 0 | G5: 0 | H5: 0 | I5: 0 | J5: 0 | K5: 0 | L5: 30680 | M5: 0 | N5: 30680 | O5: 0
A6: 2 | B6: RDC Concrete (India) Pvt Ltd (Bangalore)-Crs | C6: Intercompany | E6: 215334 | F6: 0 | G6: 0 | H6: 0 | I6: 0 | J6: 0 | K6: 0 | L6: 215334 | M6: 0 | N6: 215334 | O6: 0
A7: 3 | B7: RDC Concrete (India) Pvt Ltd (Haryana)-Crs | C7: Intercompany | E7: 332760 | F7: 0 | G7: 0 | H7: 0 | I7: 0 | J7: 332760 | K7: 0 | L7: 0 | M7: 0 | N7: 332760 | O7: 0
A8: 4 | B8: RDC Concrete India Pvt Ltd (NCR)-Crs | C8: Intercompany | E8: 370425.6 | F8: 0 | G8: 0 | H8: 0 | I8: 0 | J8: 0 | K8: 0 | L8: 370425.6 | M8: 0 | N8: 370425.6 | O8: 0
A9: 5 | B9: RDC Concrete (India) Pvt Ltd (Pune)- Crs | C9: Intercompany | E9: 511161.75 | F9: 22815.75 | G9: 0 | H9: 0 | I9: 0 | J9: 0 | K9: 235800 | L9: 252546 | M9: 0 | N9: 511161.75 | O9: 0
A10: 6 | B10: RDC Concrete (India) Pvt Ltd (chattisgarh) - Crs | C10: Intercompany | E10: 590000 | F10: 0 | G10: 0 | H10: 0 | I10: 0 | J10: 0 | K10: 0 | L10: 590000 | M10: 0 | N10: 590000 | O10: 0
A11: 7 | B11: NEPTUNE READYMIX CONCRETE.PVT.LTD - MUPPATHADOM - Crs | C11: Intercompany | E11: 708759.9 | F11: 0 | G11: 0 | H11: 0 | I11: 0 | J11: 0 | K11: 0 | L11: 0 | M11: 708759.9 | N11: 708759.9 | O11: 0
A12: 8 | B12: Neptune Readymix Concrete Pvt. Ltd.(Cochin)-Vendor - Crs | C12: Intercompany | E12: 731051 | F12: 0 | G12: 0 | H12: 0 | I12: 0 | J12: 0 | K12: 0 | L12: 0 | M12: 731051 | N12: 731051 | O12: 0
A13: 9 | B13: RDC Concrete (India) Pvt Ltd (Chennai)-Crs | C13: Intercompany | E13: 1654914 | F13: 42444 | G13: 0 | H13: 0 | I13: 212400 | J13: 637200 | K13: 323910 | L13: 438960 | M13: 0 | N13: 1654914 | O13: 0
A14: 10 | B14: RDC Concrete (India) Pvt Ltd (Gujarat)-Crs | C14: Intercompany | E14: 1675373.1 | F14: 0 | G14: 52259.17 | H14: 1545263.4 | I14: 0 | J14: 0 | K14: 0 | L14: 77850.5 | M14: 0 | N14: 1675373.1 | O14: 0
A15: 11 | B15: RDC Concrete (India) Pvt Ltd (Telangana)- Crs | C15: Intercompany | E15: 6318122 | F15: 347743.5 | G15: 906231 | H15: 352856.76 | I15: 317874.38 | J15: 542348.64 | K15: 392437.5 | L15: 3458630.2 | M15: 0 | N15: 6318122 | O15: 0
A16: 12 | B16: SOCIAM EQUIPMENT SOLUTIONS PRIVATE LIMITED-CRS | C16: Intercompany | E16: 8446869.4 | F16: 412960 | G16: 412960 | H16: 412960 | I16: 412960 | J16: 412960 | K16: 412960 | L16: 5149321.8 | M16: 819787.64 | N16: 8446869.4 | O16: 0
... A21: 17 | B21: RDC Concrete (India) Pvt Ltd (Kolkata)-Crs | C21: Intercompany | E21: 38159903 | F21: 2933987.6 | G21: 3204745.7 | H21: 568112.6 | I21: 1677602.8 | J21: 19935746 | K21: 470229.6 | L21: 5119764.4 | M21: 4249714.4 | N21: 38159903 | O21: 0
B23: Grand Total | E23: =SUM(E5:E21) -> 1.2133057e+08 | F23: =SUM(F5:F21) -> 4133810.8 | G23: =SUM(G5:G21) -> 21034576 | H23: =SUM(H5:H21) -> 4849961.4 | I23: =SUM(I5:I21) -> 5021160.7 | J23: =SUM(J5:J21) -> 27744692 | K23: =SUM(K5:K21) -> 7489095.8 | L23: =SUM(L5:L21) -> 28657615 | ... O23: =SUM(O5:O21) -> 0

Sheet Review
A1: Review Items | Creditors Ageing as at 31-July-2026
A3: A. New vendors - classification required (25)
A4: Vendor Name | B4: Location (from cost centre) | C4: TB Balance | D4: Vendor Type | E4: Vendor Sub Type
A5: Aadhya Shakti Enterprise-Crs | B5: Gujarat | C5: 106912.12
A6: Arya CS - Crs | B6: Nagpur | C6: 3000
A7: Balram Kumar Chakrawarti - Employee | B7: Vizag | C7: 413424
A8: D.K. SERVICES - Crs | B8: Nagpur | C8: 45611.2
A9: Harish Ludhani - Employee | B9: Head Office | C9: 974095.2
A10: Jai Bhairunath | B10: Aggregate | C10: 10856
A11: KAMAL S PATIL - Crs | B11: Wada | C11: 34630.2
A12: KAPIL THAKARE - Crs | B12: Wada | C12: 5495
A13: Krishna Enterprise(Guj)-Crs | B13: Gujarat | C13: 2478
A14: Krishna Konar - Crs | B14: Galsi | C14: 18000
A15: Krishnendu Konar CRS | B15: Galsi | C15: 37000
A16: M B ENTERPRISE- Crs | B16: Galsi | C16: 81011.2
... A29: Tathoi Enterprise - Crs | B29: Galsi | C29: 700906.24
A31: B. New vendors - auto-classified, please confirm (23)
A32: Vendor Name | B32: Location | C32: TB Balance | D32: Vendor Type (suggested) | E32: Vendor Sub Type (suggested)
A33: AVENGERS SECURITY SERVICES-CR | B33: Nellore | C33: 33434.68 | D33: Expenses | E33: Security charges
A34: Agile Innotech - Crs | B34: Aggregate | C34: 11328 | D34: Expenses | E34: Office Exps
A35: Best Electro Mech-Crs | B35: Wada | C35: 9762.76 | D35: Expenses | E35: Store and spare
A36: Bharti Airtel Limited - Crs | B36: Gujarat | C36: 64940.1 | D36: Expenses | E36: Office Exps
A37: Bipin Jadhav Guest House - Crs | B37: Nagpur | C37: 4500 | D37: Expenses | E37: Guest House Rent
A38: CB SURATWALA AND SONS-CRS | B38: Gujarat | C38: 7167 | D38: Expenses | E38: Professional Fees
A39: Dev Security Services- Crs | B39: Aggregate | C39: 113558 | D39: Expenses | E39: Security charges
A40: First Choice Logistics-Crs | B40: Wada | C40: 153802.5 | D40: Transportation | E40: Transport
A41: Harrier Security Services Private Limited-Crs | B41: Wada | C41: 60336.57 | D41: Expenses | E41: Security charges
A42: Info Tech Computers - Crs | B42: Nagpur | C42: 924.16 | D42: Expenses | E42: Office Exps
A43: JANTA CEMENT INDUSTRIES-Crs | B43: Nagpur | C43: 279918.46 | D43: Trading | E43: Flyash
A44: JINENDRA AUTO PARTS-Crs | B44: Gujarat | C44: 10091 | D44: Expenses | E44: Store and spare
... A55: Yaa Baba Taj Restaurants - CRS | B55: Nagpur | C55: 4516 | D55: Expenses | E55: Staff Welfare
A57: C. TB vs Bill-Wise differences (3)
A58: Vendor Name | B58: Tab | C58: TB Balance | D58: BW Total | E58: Diff (TB-BW)
A59: CtrlP Solutions Private Limited - Crs | B59: Only Creditors | C59: 700 | D59: 39.05 | E59: 660.95
A60: Karim Shah - Employee | B60: Advances | C60: -25507 | D60: -4493 | E60: -21014
A61: Kinshar Metals - Crs | B61: Advances | C61: -2874700 | D61: -2596820 | E61: -277880
A63: D. Nil-balance vendors excluded (open bills net to zero in TB) (12)
A64: Vendor Name | B64: Bills | C64: Gross of bills | D64: Net after netting
A65: Anantha Vamshider Reddy - Employee | B65: 1 | C65: 20512 | D65: 20512
A66: MANNAT CONSTRUCTIONS - Crs | B66: 3 | C66: 216484 | D66: 0
A67: Powercraft Industries-Crs | B67: 1 | C67: 600 | D67: 600
A68: Premier Electricals-Crs | B68: 2 | C68: 270400 | D68: 0
A69: RANJAN MAHANANDA - Employee | B69: 2 | C69: 42812 | D69: 0
A70: RITHIK ELECTRICALS-Crs | B70: 1 | C70: 46135.36 | D70: 46135.36
A71: Rashmi Cement - Crs | B71: 2 | C71: 162750 | D71: 0
A72: SEN & RAY- CRS | B72: 2 | C72: 5400 | D72: 0
A73: Shree Ganesh Engineering Work - CRS | B73: 1 | C73: 5544 | D73: 5544
A74: Tata AIG General Insurance Co Ltd - Crs | B74: 2 | C74: 473416 | D74: 0
A75: Vaibhav Govind Ide- Crs | B75: 2 | C75: 35000 | D75: 0
A76: Xinda Group Cementious Material Co. Ltd - Crs | B76: 2 | C76: 211911 | D76: 0

Sheet Payments
C2: Total | E2: =SUBTOTAL(9,E4:E141) -> 34536948
B3: Date | C3: Description | D3: Name | E3: Amount | F3: UTR No | G3: Location | H3: CF Location
B4: 46235.174 | C4: AUTO INTEREST PAYMENT ON TERM LOAN AGAINST 5WSLN06240060003 | D4: Interest on Term Loan | E4: 352078 | F4: 5WSLN06240060003 | G4: Head Office | H4: Head Office
B5: 46235.296 | C5: Jadav Enterprise | D5: M/s Jadav Enterprise - Crs | E5: 730112 | F5: HDFCH01162147885 | G5: Aggregate | H5: Aggregate Panagarh Crusher
B6: 46235.296 | C6: P.S. Agency-CRS | D6: P.S. Agency-CRS | E6: 500000 | F6: HDFCH01162149041 | G6: Aggregate | H6: Aggregate pachami trading
B7: 46235.296 | C7: Kamakhya Enterprise | D7: Kamakhya Enterprises - Crs | E7: 492928.21 | F7: HDFCH01162149821 | G7: Aggregate | H7: Aggregate Panagarh Crusher
B8: 46235.572 | C8: Enet_ST CHG_ULTMIAN-CDT2621341895107 | D8: Bank Charges | E8: 590 | F8: CDT2621341895107 | G8: Head Office | H8: Main Operation
B9: 46235.635 | C9: ETC POOL | D9: ETC POOL - Crs | E9: 28000 | F9: HDFCH01163334322 | G9: Gujarat | H9: Main Operation
B10: 46235.635 | C10: ETC POOL | D10: ETC POOL - Crs | E10: 172000 | F10: HDFCH01163334322 | G10: Aggregate | H10: Aggregate Panagarh Crusher
B11: 46235.776 | C11: JFC Logistics | D11: JFC Logistics - Crs | E11: 300000 | F11: 608018651316 | G11: Goa | H11: Main Operation
B12: 46235.776 | C12: Sumit Goods Carrier | D12: Sumit Goods Carrier(Arabinda Kumar Das) - CRS | E12: 192200 | F12: 608018651325 | G12: Haryana | H12: Trading Business
B13: 46235.776 | C13: Devanand B Singh | D13: Devanand B. Singh - Employee | E13: 756000 | F13: HDFCH01164212484 | G13: Head Office | H13: Main Operation
B14: 46235.776 | C14: Shreeji Sales Corp | D14: Shreeji Sales Corporation-Crs | E14: 41480 | F14: HDFCH01164216054 | G14: Gujarat | H14: Main Operation
B15: 46235.777 | C15: THORON TURNKEY PVT | D15: THORON TURNKEY SOLUTIONS PRIVATE LIMITED-CRS | E15: 94814.01 | F15: HDFCH01164215435 | G15: Gujarat | H15: Main Operation
B16: 46235.777 | C16: STEP IN TECHNOLOGIE | D16: STEP IN TECHNOLOGIES-CRS | E16: 136560.6 | F16: HDFCH01164213377 | G16: TamilNadu | H16: Main Operation
B17: 46235.777 | C17: A Abdul Hameed | D17: A. Abdul Hameed - Crs | E17: 225000 | F17: HDFCH01164213978 | G17: Goa | H17: Main Operation
B18: 46235.777 | C18: G D Packaging | D18: G D Packaging - Crs | E18: 137428 | F18: HDFCH01164216833 | G18: Vizag | H18: Main Operation
B19: 46236.493 | C19: FT-IOCLXPP1002085506-IOCL | D19: Indian Oil Corporation Limited - Crs | E19: 58000 | F19: 607316199847 | G19: Gujarat | H19: Main Operation
B20: 46236.493 | C20: FT-IOCLXPP1002085506-IOCL | D20: Indian Oil Corporation Limited - Crs | E20: 42000 | F20: 607316199847 | G20: Flyash | H20: Flyash Business
B21: 46236.493 | C21: FT-IOCLXPP1002085506-IOCL | D21: Indian Oil Corporation Limited - Crs | E21: 100000 | F21: 607316199847 | G21: Aggregate | H21: Aggregate Panagarh Crusher
B22: 46236.493 | C22: FT-IOCLXPP1002085506-IOCL | D22: Indian Oil Corporation Limited - Crs | E22: 58000 | F22: 607316199845 | G22: Gujarat | H22: Main Operation
B23: 46236.493 | C23: FT-IOCLXPP1002085506-IOCL | D23: Indian Oil Corporation Limited - Crs | E23: 42000 | F23: 607316199845 | G23: Flyash | H23: Flyash Business
B24: 46236.493 | C24: FT-IOCLXPP1002085506-IOCL | D24: Indian Oil Corporation Limited - Crs | E24: 100000 | F24: 607316199845 | G24: Aggregate | H24: Aggregate Panagarh Crusher
B25: 46237.543 | C25: FT-CHETTINAD9214181-Chettinad Cement | D25: Chettinad Cement Corporation Private Limited - Crs | E25: 397403 | F25: 608038926716 | G25: Vizag | H25: Main Operation
B26: 46237.543 | C26: RMB KNOVATECH PVT LT | D26: RMB KNOVATECH PVT LTD. - Crs | E26: 199520 | F26: 608018651342 | G26: Nagpur | H26: Capex
B27: 46237.543 | C27: Nirmal and Co - Crs | D27: Nirmal and Co - Crs | E27: 479644.55 | F27: HDFCH01166126622 | G27: Gujarat | H27: Main Operation
B28: 46237.543 | C28: SREERAMA INDUSTRY | D28: SREERAMA INDUSTRIES PRIVATE LIMITED-Crs | E28: 2192060 | F28: HDFCH01166122720 | G28: Vizag | H28: Main Operation
B29: 46237.543 | C29: Siddhi Vinayak Corpo | D29: Siddhi Vinayak Corporation-Crs | E29: 456010 | F29: HDFCH01166122724 | G29: Gujarat | H29: Main Operation
B30: 46237.543 | C30: DOED JUNG KUEN PHEN | D30: DOED JUNG KUEN PHEN TRADING HOUSE-CRS | E30: 500000 | F30: HDFCH01166126641 | G30: Haryana | H30: Trading Business
B31: 46237.543 | C31: Shree Mahalaxmi Tra | D31: Shree Mahalaxmi Traders-Crs | E31: 373688 | F31: HDFCH01166128235 | G31: Gujarat | H31: Main Operation
B32: 46237.543 | C32: Puneet Logistics-Crs | D32: Puneet Logistics-Crs | E32: 100000 | F32: HDFCH01166128321 | G32: Gujarat | H32: Main Operation
B33: 46237.788 | C33: RTGS Dr-SBIN0005996-ArcelormittalNippo-NETBANK MUM-HDFCR52026080391506105 | D33: Arcelormittal Nippon Steel India Limited - Crs | E33: 400000 | F33: HDFCR52026080391506105 | G33: Gujarat | H33: Main Operation
B34: 46237.801 | C34: FT-IOCLXPP1002085506-IOCL | D34: Indian Oil Corporation Limited - Crs | E34: 200000 | F34: 607316199846 | G34: Gujarat | H34: Main Operation
B35: 46237.801 | C35: Csrl Structwel Lab | D35: Csrl-Structwel Lab (Pune) Private Limited Crs | E35: 3933 | F35: 608018651328 | G35: Nagpur | H35: Main Operation
B36: 46237.801 | C36: Bhandari Automobiles | D36: Bhandari Automobiles Pvt Ltd - Crs | E36: 9150 | F36: HDFCH01167731664 | G36: Aggregate | H36: Aggregate Panagarh Crusher
B37: 46237.801 | C37: Dmk Logistic | D37: Dmk Logistic - Crs | E37: 3286.91 | F37: HDFCH01167731665 | G37: Bangalore | H37: Trading Business
B38: 46237.801 | C38: NIGAM CAR SERVICES | D38: NIGAM CAR SERVICES | E38: 20958 | F38: HDFCH01167731666 | G38: Aggregate | H38: Aggregate Panagarh Crusher
B39: 46237.801 | C39: BISWAJIT RUI DAS | D39: BISWAJIT RUI DAS - Crs | E39: 36262.88 | F39: HDFCH01167737254 | G39: Galsi | H39: Main Operation
B40: 46237.801 | C40: DEVENDRA CHAUHAN | D40: DEVENDRA CHAUHAN REFRACTORY WORKS -CRS | E40: 43200 | F40: HDFCH01167734968 | G40: Gujarat | H40: Capex
B41: 46237.801 | C41: Dutta Auto Centre | D41: Dutta Auto Centre | E41: 36049.4 | F41: HDFCH01167731669 | G41: Galsi | H41: Main Operation
B42: 46237.801 | C42: Jai Bhairunath | D42: Jai Bhairunath | E42: 10856 | F42: HDFCH01167734970 | G42: Aggregate | H42: Aggregate Panagarh Crusher
B43: 46237.801 | C43: Tara Shree Enterpri | D43: Tara Shree Enterprises | E43: 27051 | F43: HDFCH01167738312 | G43: Wada | H43: Main Operation
B44: 46237.801 | C44: DEEP ENTERPRISEs | D44: DEEP ENTERPRISES-CRS | E44: 3000 | F44: HDFCH01167737281 | G44: Nagpur | H44: Main Operation
B45: 46237.801 | C45: CtrlP Solutions Pvt | D45: CtrlP Solutions Private Limited - Crs | E45: 700 | F45: HDFCH01167731672 | G45: Head Office | H45: Main Operation
B46: 46237.801 | C46: Ram Innovation soln | D46: Ram Innovation & Solutions-Crs | E46: 1000 | F46: HDFCH01167733955 | G46: Nagpur | H46: Main Operation
B47: 46238.296 | C47: Mehar Engineering | D47: Mehar Engineering Works | E47: 66080 | F47: HDFCH01168143058 | G47: Wada | H47: Main Operation
... B55: 46238.297 | C55: Shri Raghavendra En | D55: Shri Raghavendra Enterprises - Crs | E55: 320322.68 | F55: HDFCH01168143848 | G55: Bangalore | H55: Trading Business
B56: 46238.871 | C56: VRAJ Cement Carrier | D56: VRAJ Cement Carrier LLP Maharashtra - Crs | E56: 514705.92 | F56: 608040098026 | G56: flyash | H56: Flyash Business
B57: 46238.871 | C57: Shahabaz Khan | D57: Shahabaz Khan - Employee | E57: 3000 | F57: HDFCH01170523149 | G57: Flyash | H57: Flyash Business
B58: 46238.871 | C58: Abhay Singh | D58: Abhay Singh-Employee | E58: 10516 | F58: HDFCH01170525172 | G58: Gujarat | H58: Main Operation
B59: 46238.871 | C59: Harsh Raj | D59: Harsh Raj - EMPLOYEE | E59: 20579 | F59: HDFCH01170527900 | G59: Howrah | H59: Main Operation
B60: 46239.296 | C60: Harish Ludhani | D60: Harish Ludhani - Employee | E60: 344995.2 | F60: HDFCH01170780317 | G60: Flyash | H60: Flyash Business
B61: 46239.42 | C61: INFINITY ENGINEERING | D61: Infinity Engineering-Crs | E61: 16530 | F61: HDFCH01171375276 | G61: Gujarat | H61: Main Operation
B62: 46239.42 | C62: DOED JUNG KUEN PHEN | D62: DOED JUNG KUEN PHEN TRADING HOUSE-CRS | E62: 500000 | F62: HDFCH01171371326 | G62: Haryana | H62: Trading Business
B63: 46239.42 | C63: ASHCONNECT | D63: ASHCONNECT GLOBAL TRADING Pvt Ltd- Crs | E63: 561211.29 | F63: HDFCH01171373613 | G63: Flyash | H63: Flyash Business
B64: 46239.42 | C64: FT-IOCLXPP1002085506-IOCL | D64: Indian Oil Corporation Limited - Crs | E64: 58000 | F64: 608050533676 | G64: Gujarat | H64: Main Operation
B65: 46239.42 | C65: FT-IOCLXPP1002085506-IOCL | D65: Indian Oil Corporation Limited - Crs | E65: 42000 | F65: 608050533676 | G65: Flyash | H65: Flyash Business
B66: 46239.42 | C66: FT-IOCLXPP1002085506-IOCL | D66: Indian Oil Corporation Limited - Crs | E66: 100000 | F66: 608050533676 | G66: Aggregate | H66: Aggregate Panagarh Crusher
B67: 46239.42 | C67: Agile Innotech | D67: Agile Innotech - Crs | E67: 11328 | F67: 608040098031 | G67: Galsi | H67: Main Operation
B68: 46239.423 | C68: Sumit Goods Carrier | D68: Sumit Goods Carrier(Arabinda Kumar Das) - CRS | E68: 143200 | F68: 608018651324 | G68: Haryana | H68: Trading Business
B69: 46239.53 | C69: RTGS Dr-DBSS0IN0877-AslLogisticsPrivateLimitedCrs-NETBANK MUM-HDFCR52026080592225225 | D69: Asl Logistics Private Limited-Crs | E69: 774736.17 | F69: HDFCR52026080592225225 | G69: Flyash | H69: Flyash Business
B70: 46239.53 | C70: RDC ICD HDFC CC | D70: RDC CONCRETE (INDIA) Pvt Ltd -ICD | E70: 3697042 | F70: 608050764175 | G70: Head Office | H70: Head Office
B71: 46239.53 | C71: FT-CHETTINAD9214181-Chettinad Cement | D71: Chettinad Cement Corporation Private Limited - Crs | E71: 157729 | F71: 608050764176 | G71: Vizag | H71: Main Operation
B72: 46239.53 | C72: STEEL PLUS | D72: Steel Plus - Crs | E72: 100000 | F72: HDFCH01171883237 | G72: Gujarat | H72: Main Operation
B73: 46239.53 | C73: MSEDCL CRS | D73: MSEDCL - CRS | E73: 626430 | F73: HDFCH01171886663 | G73: Nagpur | H73: Main Operation
B74: 46239.53 | C74: SMAS AUTO | D74: SMAS AUTO LEASING INDIA PRIVATE LIMITED-CRS | E74: 122052.63 | F74: HDFCH01171881192 | G74: Gujarat | H74: Main Operation
B75: 46239.53 | C75: Legacy Transport Pvt | D75: Legacy Transport Private Limited-Crs | E75: 197225 | F75: HDFCH01171886680 | G75: Gujarat | H75: Main Operation
B76: 46239.747 | C76: Shiv Om Prefab | D76: SHIV OM PREFAB INFRA AND LOGISTICS-Crs | E76: 241290 | F76: HDFCH01173351715 | G76: Nagpur | H76: Main Operation
B77: 46239.747 | C77: FT-IOCLXPP1002085506-IOCL | D77: Indian Oil Corporation Limited - Crs | E77: 58000 | F77: 608050533674 | G77: Gujarat | H77: Main Operation
B78: 46239.747 | C78: FT-IOCLXPP1002085506-IOCL | D78: Indian Oil Corporation Limited - Crs | E78: 42000 | F78: 608050533674 | G78: Flyash | H78: Flyash Business
B79: 46239.747 | C79: FT-IOCLXPP1002085506-IOCL | D79: Indian Oil Corporation Limited - Crs | E79: 100000 | F79: 608050533674 | G79: Aggregate | H79: Aggregate Panagarh Crusher
B80: 46240.106 | C80: AUTO TERM LOAN LIQUIDATED AGAINST 5WSLN06240060003 | D80: =VLOOKUP(C80,[1]Payments!$C$4:$D$459,2,0) -> HDFC Term Loan | E80: 1666666.7 | F80: 5WSLN06240060003 | G80: Head Office | H80: Head Office
B81: 46240.506 | C81: Krishna Konar | D81: =VLOOKUP(C81,[1]Payments!$C$4:$D$459,2,0) -> Krishna Konar - Crs | E81: 18000 | F81: HDFCH01174868237 | G81: Galsi | H81: Main Operation
B82: 46240.506 | C82: Krishnendu Konar | D82: =VLOOKUP(C82,[1]Payments!$C$4:$D$459,2,0) -> Krishnendu Konar CRS | E82: 37000 | F82: HDFCH01174871677 | G82: Galsi | H82: Main Operation
B83: 46240.506 | C83: Purnendu Konar | D83: =VLOOKUP(C83,[1]Payments!$C$4:$D$459,2,0) -> Purnendu Konar - Crs | E83: 18000 | F83: HDFCH01174870022 | G83: Galsi | H83: Main Operation
B84: 46240.506 | C84: D K Services | D84: D.K. SERVICES - Crs | E84: 45611.2 | F84: HDFCH01174871684 | G84: Nagpur | H84: Main Operation
B85: 46240.506 | C85: Bhartiben Satishbhai | D85: =VLOOKUP(C85,[1]Payments!$C$4:$D$459,2,0) -> BHARTIBEN SATISHBHAI PATEL-CR | E85: 8000 | F85: HDFCH01174871686 | G85: Gujarat | H85: Main Operation
B86: 46240.506 | C86: Teamlease Salary | D86: =VLOOKUP(C86,[1]Payments!$C$4:$D$459,2,0) -> TEAMLEASE SERVICES LTD. - Crs | E86: 775143.28 | F86: 608061632898 | G86: Galsi | H86: Main Operation
B87: 46240.506 | C87: Teamlease Salary | D87: =VLOOKUP(C87,[1]Payments!$C$4:$D$459,2,0) -> TEAMLEASE SERVICES LTD. - Crs | E87: 876681.34 | F87: 608061632898 | G87: Gujarat | H87: Main Operation
B88: 46240.506 | C88: Teamlease Salary | D88: =VLOOKUP(C88,[1]Payments!$C$4:$D$459,2,0) -> TEAMLEASE SERVICES LTD. - Crs | E88: 33296 | F88: 608061632898 | G88: Haryana | H88: Trading Business
B89: 46240.506 | C89: Teamlease Salary | D89: =VLOOKUP(C89,[1]Payments!$C$4:$D$459,2,0) -> TEAMLEASE SERVICES LTD. - Crs | E89: 1002421 | F89: 608061632898 | G89: Nagpur | H89: Main Operation
B90: 46240.506 | C90: Veena Dilip Bokde | D90: =VLOOKUP(C90,[1]Payments!$C$4:$D$459,2,0) -> Veena Dilip Bokde - Crs | E90: 12000 | F90: HDFCH01174866426 | G90: Nagpur | H90: Main Operation
B91: 46240.506 | C91: Balram Chakrawarti | D91: =VLOOKUP(C91,[1]Payments!$C$4:$D$459,2,0) -> Balram Kumar Chakrawarti - Employee | E91: 73224 | F91: 608061632896 | G91: Head Office | H91: Main Operation
B92: 46240.506 | C92: Subhendu Konar | D92: =VLOOKUP(C92,[1]Payments!$C$4:$D$459,2,0) -> Subhendu Konar - Crs | E92: 37000 | F92: HDFCH01174870799 | G92: Galsi | H92: Main Operation
B93: 46240.506 | C93: Harish Ludhani | D93: =VLOOKUP(C93,[1]Payments!$C$4:$D$459,2,0) -> Harish Ludhani - Employee | E93: 629100 | F93: HDFCH01174868273 | G93: Flyash | H93: Flyash Business
B94: 46240.506 | C94: VANDANA SHARMA | D94: =VLOOKUP(C94,[1]Payments!$C$4:$D$459,2,0) -> VANDANA SHARMA - Crs | E94: 75000 | F94: HDFCH01174871706 | G94: Nagpur | H94: Main Operation
B95: 46240.506 | C95: Balram Chakrawarti | D95: =VLOOKUP(C95,[1]Payments!$C$4:$D$459,2,0) -> Balram Kumar Chakrawarti - Employee | E95: 340200 | F95: 608061632897 | G95: Head Office | H95: Main Operation
B96: 46240.506 | C96: Andezath Joshi | D96: =VLOOKUP(C96,[1]Payments!$C$4:$D$459,2,0) -> Joshi Dharmarajan Andezath - Employee | E96: 150000 | F96: HDFCH01174868278 | G96: Vizag | H96: Main Operation
B97: 46240.506 | C97: Firdosh Eurich | D97: FIRDOSH ERUCH ICHHAPORIA-Crs | E97: 20000 | F97: HDFCH01174870034 | G97: Gujarat | H97: Main Operation
B98: 46240.507 | C98: KAMAL S PATIL | D98: =VLOOKUP(C98,[1]Payments!$C$4:$D$459,2,0) -> KAMAL S PATIL - Crs | E98: 34630.2 | F98: HDFCH01174870954 | G98: Wada | H98: Main Operation
B99: 46240.664 | C99: Dmk Logistic | D99: =VLOOKUP(C99,[1]Payments!$C$4:$D$459,2,0) -> Dmk Logistic - Crs | E99: 462079.8 | F99: HDFCH01175686904 | G99: Bangalore | H99: Trading Business
B100: 46240.795 | C100: AMBUJA CEMENTS | D100: =VLOOKUP(C100,[1]Payments!$C$4:$D$459,2,0) -> AMBUJA CEMENTS LIMITED -Crs | E100: 456116.66 | F100: HDFCH01176741716 | G100: Flyash | H100: Flyash Business
B101: 46240.795 | C101: AMBUJA CEMENTS | D101: =VLOOKUP(C101,[1]Payments!$C$4:$D$459,2,0) -> AMBUJA CEMENTS LIMITED -Crs | E101: 548281.69 | F101: HDFCH01176745244 | G101: Flyash | H101: Flyash Business
B102: 46241.41 | C102: FT-IOCLXPP1002085506-IOCL | D102: Indian Oil Corporation Limited - Crs | E102: 58000 | F102: 608050533675 | G102: Gujarat | H102: Main Operation
B103: 46241.41 | C103: FT-IOCLXPP1002085506-IOCL | D103: Indian Oil Corporation Limited - Crs | E103: 42000 | F103: 608050533675 | G103: Flyash | H103: Flyash Business
B104: 46241.41 | C104: FT-IOCLXPP1002085506-IOCL | D104: Indian Oil Corporation Limited - Crs | E104: 100000 | F104: 608050533675 | G104: Aggregate | H104: Aggregate Panagarh Crusher
B105: 46241.419 | C105: RTGS Dr-SBIN0005996-ArcelormittalNippo-NETBANK MUM-HDFCR52026080793112787 | D105: Arcelormittal Nippon Steel India Limited - Crs | E105: 400000 | F105: HDFCR52026080793112787 | G105: Gujarat | H105: Main Operation
B106: 46241.419 | C106: RTGS Dr-SBIN0005996-ArcelormittalNippo-NETBANK MUM-HDFCR52026080793047543 | D106: Arcelormittal Nippon Steel India Limited - Crs | E106: 400000 | F106: HDFCR52026080793047543 | G106: Gujarat | H106: Main Operation
B107: 46241.6 | C107: DOED JUNG KUEN PHEN | D107: DOED JUNG KUEN PHEN TRADING HOUSE-CRS | E107: 500000 | F107: HDFCH01178768294 | G107: Haryana | H107: Trading Business
B108: 46241.6 | C108: Stsk Controls Autom | D108: Stsk Controls and Automation - Crs | E108: 344000 | F108: HDFCH01178771152 | G108: Tamil Nadu | H108: Capex
...
